Workbook

Sheet 阅读说明
A1: 项目 | B1: 说明
A2: 性质 | B2: 参考解答生成底表，不是公开输入材料；截至2025-04-28的公开预测复核。金额均为万元。
A3: 使用顺序 | B3: 来源—版本—原表—驱动—情景年表—汇总—问题；蓝色数字为录入/参数，公式为黑色。
A4: 基准 | B4: 原表复现使用公开表列两位小数。纠偏分支采用未舍入驱动公式；与原表存在分币级尾差。
A5: 年序 | B5: 报告第一年映射2024，第五年为2028，第十八年为2041；已融资项单列。映射仅用于复现，非实际兑付日历。
A6: 余额假设 | B6: 含已融资项1374.20，期初0，经营盈余全部留存、不计息，无额外注资；计算最大累计资金缺口，非真实账户余额。
A7: 期间限制 | B7: 2022年20年期等按发行年份加期限对应到期年比报告映射晚一年；不杜撰2042经营收益，须补正实际兑付表后更新。
A8: 充电甲 | B8: 文字五年周期甲：2028—2032基期，2033—2037×1.25，2038—2041再×1.10；是解释分支，非认定唯一原意。
A9: 充电乙 | B9: 文字五年周期乙：2028—2032基期，第6年开始按10%每五年递增，2033×1.10、2038再×1.10。
A10: 主复核分支 | B10: 停车按引用文件冻结单价并适用夜间封顶；充电保留0.8为经营假设，比较原表与甲乙周期；管理费2%/5%双分支。
A11: 压力 | B11: 收入下降5%，六项非管理费保持既定路径，管理费按情景费率随收入联动；另复现净收益-5%及收入-5%成本固定。
A12: 阈值 | B12: 1.2是本报告宣称的压力覆盖水平，不在本题中视为统一法定审批门槛；1为全周期收支覆盖界线。
A13: 重算 | B13: 改变参数或情景表后使用Excel/LibreOffice重算。无宏、无外链、无隐藏表。

Sheet 情景汇总
A1: 情景 | B1: 融资版本 | C1: 基准总收入 | D1: 项目净收益 | E1: 债务本息 | F1: 覆盖倍数 | G1: 最小单年差额 | H1: 最大累计缺口 | I1: 最大累计缺口时点 | J1: 期末未补资累计 | K1: 到1.2的额外降幅 | L1: 到1的额外降幅
A2: 原表 | B2: 早版 | C2: =SUM(情景年表!E2:E20) -> 205183.59 | D2: =SUM(情景年表!J2:J20) -> 75456.37 | E2: =SUM(情景年表!M2:M20) -> 49703 | F2: =D2/E2 -> 1.5181452 | G2: =MIN(情景年表!N2:N20) -> -13285.04 | H2: =MAX(0,-MIN(情景年表!O2:O20)) -> 16145.31 | I2: =INDEX(情景年表!D2:D20,MATCH(MIN(情景年表!O2:O20),情景年表!O2:O20,0)) -> 2028 | J2: =情景年表!O20 -> 25753.37 | K2: =IF(情景参数!E2="联动",(D2-1.2*E2)/((1-情景参数!C2)*C2),"不适用") -> 不适用 | L2: =IF(情景参数!E2="联动",(D2-E2)/((1-情景参数!C2)*C2),"不适用") -> 不适用
A3: 原表 | B3: 晚版 | C3: =SUM(情景年表!E21:E39) -> 205183.59 | D3: =SUM(情景年表!J21:J39) -> 75456.37 | E3: =SUM(情景年表!M21:M39) -> 51502.9 | F3: =D3/E3 -> 1.4650897 | G3: =MIN(情景年表!N21:N39) -> -13285.04 | H3: =MAX(0,-MIN(情景年表!O21:O39)) -> 6617.21 | I3: =INDEX(情景年表!D21:D39,MATCH(MIN(情景年表!O21:O39),情景年表!O21:O39,0)) -> 2028 | J3: =情景年表!O39 -> 23953.47 | K3: =IF(情景参数!E2="联动",(D3-1.2*E3)/((1-情景参数!C2)*C3),"不适用") -> 不适用 | L3: =IF(情景参数!E2="联动",(D3-E3)/((1-情景参数!C2)*C3),"不适用") -> 不适用
A4: 统一2% | B4: 早版 | C4: =SUM(情景年表!E40:E58) -> 205183.59 | D4: =SUM(情景年表!J40:J58) -> 75410.004 | E4: =SUM(情景年表!M40:M58) -> 49703 | F4: =D4/E4 -> 1.5172123 | G4: =MIN(情景年表!N40:N58) -> -13294.681 | H4: =MAX(0,-MIN(情景年表!O40:O58)) -> 16145.312 | I4: =INDEX(情景年表!D40:D58,MATCH(MIN(情景年表!O40:O58),情景年表!O40:O58,0)) -> 2028 | J4: =情景年表!O58 -> 25707.004 | K4: =IF(情景参数!E3="联动",(D4-1.2*E4)/((1-情景参数!C3)*C4),"不适用") -> 0.078408645 | L4: =IF(情景参数!E3="联动",(D4-E4)/((1-情景参数!C3)*C4),"不适用") -> 0.12784471
A5: 统一2% | B5: 晚版 | C5: =SUM(情景年表!E59:E77) -> 205183.59 | D5: =SUM(情景年表!J59:J77) -> 75410.004 | E5: =SUM(情景年表!M59:M77) -> 51502.9 | F5: =D5/E5 -> 1.4641895 | G5: =MIN(情景年表!N59:N77) -> -13294.681 | H5: =MAX(0,-MIN(情景年表!O59:O77)) -> 6617.2116 | I5: =INDEX(情景年表!D59:D77,MATCH(MIN(情景年表!O59:O77),情景年表!O59:O77,0)) -> 2028 | J5: =情景年表!O77 -> 23907.104 | K5: =IF(情景参数!E3="联动",(D5-1.2*E5)/((1-情景参数!C3)*C5),"不适用") -> 0.067667245 | L5: =IF(情景参数!E3="联动",(D5-E5)/((1-情景参数!C3)*C5),"不适用") -> 0.11889354
A6: 统一5% | B6: 早版 | C6: =SUM(情景年表!E78:E96) -> 205183.59 | D6: =SUM(情景年表!J78:J96) -> 69254.496 | E6: =SUM(情景年表!M78:M96) -> 49703 | F6: =D6/E6 -> 1.3933665 | G6: =MIN(情景年表!N78:N96) -> -13850.305 | H6: =MAX(0,-MIN(情景年表!O78:O96)) -> 16422.349 | I6: =INDEX(情景年表!D78:D96,MATCH(MIN(情景年表!O78:O96),情景年表!O78:O96,0)) -> 2028 | J6: =情景年表!O96 -> 19551.496 | K6: =IF(情景参数!E4="联动",(D6-1.2*E6)/((1-情景参数!C4)*C6),"不适用") -> 0.04930576 | L6: =IF(情景参数!E4="联动",(D6-E6)/((1-情景参数!C4)*C6),"不适用") -> 0.10030296
A7: 统一5% | B7: 晚版 | C7: =SUM(情景年表!E97:E115) -> 205183.59 | D7: =SUM(情景年表!J97:J115) -> 69254.496 | E7: =SUM(情景年表!M97:M115) -> 51502.9 | F7: =D7/E7 -> 1.3446718 | G7: =MIN(情景年表!N97:N115) -> -13850.305 | H7: =MAX(0,-MIN(情景年表!O97:O115)) -> 6894.249 | I7: =INDEX(情景年表!D97:D115,MATCH(MIN(情景年表!O97:O115),情景年表!O97:O115,0)) -> 2028 | J7: =情景年表!O115 -> 17751.596 | K7: =IF(情景参数!E4="联动",(D7-1.2*E7)/((1-情景参数!C4)*C7),"不适用") -> 0.038225157 | L7: =IF(情景参数!E4="联动",(D7-E7)/((1-情景参数!C4)*C7),"不适用") -> 0.091069129
A8: 收费修正2% | B8: 早版 | C8: =SUM(情景年表!E116:E134) -> 199365.81 | D8: =SUM(情景年表!J116:J134) -> 69708.577 | E8: =SUM(情景年表!M116:M134) -> 49703 | F8: =D8/E8 -> 1.4025024 | G8: =MIN(情景年表!N116:N134) -> -14005.076 | H8: =MAX(0,-MIN(情景年表!O116:O134)) -> 16299.838 | I8: =INDEX(情景年表!D116:D134,MATCH(MIN(情景年表!O116:O134),情景年表!O116:O134,0)) -> 2028 | J8: =情景年表!O134 -> 20005.577 | K8: =IF(情景参数!E5="联动",(D8-1.2*E8)/((1-情景参数!C5)*C8),"不适用") -> 0.051515275 | L8: =IF(情景参数!E5="联动",(D8-E8)/((1-情景参数!C5)*C8),"不适用") -> 0.10239396
A9: 收费修正2% | B9: 晚版 | C9: =SUM(情景年表!E135:E153) -> 199365.81 | D9: =SUM(情景年表!J135:J153) -> 69708.577 | E9: =SUM(情景年表!M135:M153) -> 51502.9 | F9: =D9/E9 -> 1.3534884 | G9: =MIN(情景年表!N135:N153) -> -14005.076 | H9: =MAX(0,-MIN(情景年表!O135:O153)) -> 6771.738 | I9: =INDEX(情景年表!D135:D153,MATCH(MIN(情景年表!O135:O153),情景年表!O135:O153,0)) -> 2028 | J9: =情景年表!O153 -> 18205.677 | K9: =IF(情景参数!E5="联动",(D9-1.2*E9)/((1-情景参数!C5)*C9),"不适用") -> 0.040460425 | L9: =IF(情景参数!E5="联动",(D9-E9)/((1-情景参数!C5)*C9),"不适用") -> 0.093181581
A10: 收费修正5% | B10: 早版 | C10: =SUM(情景年表!E154:E172) -> 199365.81 | D10: =SUM(情景年表!J154:J172) -> 63727.603 | E10: =SUM(情景年表!M154:M172) -> 49703 | F10: =D10/E10 -> 1.2821681 | G10: =MIN(情景年表!N154:N172) -> -14538.953 | H10: =MAX(0,-MIN(情景年表!O154:O172)) -> 16572.145 | I10: =INDEX(情景年表!D154:D172,MATCH(MIN(情景年表!O154:O172),情景年表!O154:O172,0)) -> 2028 | J10: =情景年表!O172 -> 14024.603 | K10: =IF(情景参数!E6="联动",(D10-1.2*E10)/((1-情景参数!C6)*C10),"不适用") -> 0.021563126 | L10: =IF(情景参数!E6="联动",(D10-E10)/((1-情景参数!C6)*C10),"不适用") -> 0.074048503
A11: 收费修正5% | B11: 晚版 | C11: =SUM(情景年表!E173:E191) -> 199365.81 | D11: =SUM(情景年表!J173:J191) -> 63727.603 | E11: =SUM(情景年表!M173:M191) -> 51502.9 | F11: =D11/E11 -> 1.2373595 | G11: =MIN(情景年表!N173:N191) -> -14538.953 | H11: =MAX(0,-MIN(情景年表!O173:O191)) -> 7695.854 | I11: =INDEX(情景年表!D173:D191,MATCH(MIN(情景年表!O173:O191),情景年表!O173:O191,0)) -> 2033 | J11: =情景年表!O191 -> 12224.703 | K11: =IF(情景参数!E6="联动",(D11-1.2*E11)/((1-情景参数!C6)*C11),"不适用") -> 0.010159175 | L11: =IF(情景参数!E6="联动",(D11-E11)/((1-情景参数!C6)*C11),"不适用") -> 0.06454521
A12: 文字周期甲2% | B12: 早版 | C12: =SUM(情景年表!E192:E210) -> 198899.42 | D12: =SUM(情景年表!J192:J210) -> 69251.515 | E12: =SUM(情景年表!M192:M210) -> 49703 | F12: =D12/E12 -> 1.3933065 | G12: =MIN(情景年表!N192:N210) -> -14033.974 | H12: =MAX(0,-MIN(情景年表!O192:O210)) -> 16299.833 | I12: =INDEX(情景年表!D192:D210,MATCH(MIN(情景年表!O192:O210),情景年表!O192:O210,0)) -> 2028 | J12: =情景年表!O210 -> 19548.515 | K12: =IF(情景参数!E7="联动",(D12-1.2*E12)/((1-情景参数!C7)*C12),"不适用") -> 0.049291219 | L12: =IF(情景参数!E7="联动",(D12-E12)/((1-情景参数!C7)*C12),"不适用") -> 0.1002892
A13: 文字周期甲2% | B13: 晚版 | C13: =SUM(情景年表!E211:E229) -> 198899.42 | D13: =SUM(情景年表!J211:J229) -> 69251.515 | E13: =SUM(情景年表!M211:M229) -> 51502.9 | F13: =D13/E13 -> 1.3446139 | G13: =MIN(情景年表!N211:N229) -> -14033.974 | H13: =MAX(0,-MIN(情景年表!O211:O229)) -> 6771.7333 | I13: =INDEX(情景年表!D211:D229,MATCH(MIN(情景年表!O211:O229),情景年表!O211:O229,0)) -> 2028 | J13: =情景年表!O229 -> 17748.615 | K13: =IF(情景参数!E7="联动",(D13-1.2*E13)/((1-情景参数!C7)*C13),"不适用") -> 0.038210447 | L13: =IF(情景参数!E7="联动",(D13-E13)/((1-情景参数!C7)*C13),"不适用") -> 0.091055227
A14: 文字周期甲5% | B14: 早版 | C14: =SUM(情景年表!E230:E248) -> 198899.42 | D14: =SUM(情景年表!J230:J248) -> 63284.532 | E14: =SUM(情景年表!M230:M248) -> 49703 | F14: =D14/E14 -> 1.2732538 | G14: =MIN(情景年表!N230:N248) -> -14566.967 | H14: =MAX(0,-MIN(情景年表!O230:O248)) -> 16572.14 | I14: =INDEX(情景年表!D230:D248,MATCH(MIN(情景年表!O230:O248),情景年表!O230:O248,0)) -> 2028 | J14: =情景年表!O248 -> 13581.532 | K14: =IF(情景参数!E8="联动",(D14-1.2*E14)/((1-情景参数!C8)*C14),"不适用") -> 0.019268837 | L14: =IF(情景参数!E8="联动",(D14-E14)/((1-情景参数!C8)*C14),"不适用") -> 0.071877284
A15: 文字周期甲5% | B15: 晚版 | C15: =SUM(情景年表!E249:E267) -> 198899.42 | D15: =SUM(情景年表!J249:J267) -> 63284.532 | E15: =SUM(情景年表!M249:M267) -> 51502.9 | F15: =D15/E15 -> 1.2287567 | G15: =MIN(情景年表!N249:N267) -> -14566.967 | H15: =MAX(0,-MIN(情景年表!O249:O267)) -> 7925.013 | I15: =INDEX(情景年表!D249:D267,MATCH(MIN(情景年表!O249:O267),情景年表!O249:O267,0)) -> 2033 | J15: =情景年表!O267 -> 11781.632 | K15: =IF(情景参数!E8="联动",(D15-1.2*E15)/((1-情景参数!C8)*C15),"不适用") -> 0.0078381452 | L15: =IF(情景参数!E8="联动",(D15-E15)/((1-情景参数!C8)*C15),"不适用") -> 0.062351708
A16: 文字周期乙5% | B16: 早版 | C16: =SUM(情景年表!E268:E286) -> 198597.05 | D16: =SUM(情景年表!J268:J286) -> 62997.284 | E16: =SUM(情景年表!M268:M286) -> 49703 | F16: =D16/E16 -> 1.2674745 | G16: =MIN(情景年表!N268:N286) -> -14600.581 | H16: =MAX(0,-MIN(情景年表!O268:O286)) -> 16572.14 | I16: =INDEX(情景年表!D268:D286,MATCH(MIN(情景年表!O268:O286),情景年表!O268:O286,0)) -> 2028 | J16: =情景年表!O286 -> 13294.284 | K16: =IF(情景参数!E9="联动",(D16-1.2*E16)/((1-情景参数!C9)*C16),"不适用") -> 0.017775658 | L16: =IF(情景参数!E9="联动",(D16-E16)/((1-情景参数!C9)*C16),"不适用") -> 0.070464202
A17: 文字周期乙5% | B17: 晚版 | C17: =SUM(情景年表!E287:E305) -> 198597.05 | D17: =SUM(情景年表!J287:J305) -> 62997.284 | E17: =SUM(情景年表!M287:M305) -> 51502.9 | F17: =D17/E17 -> 1.2231793 | G17: =MIN(情景年表!N287:N305) -> -14600.581 | H17: =MAX(0,-MIN(情景年表!O287:O305)) -> 7955.5714 | I17: =INDEX(情景年表!D287:D305,MATCH(MIN(情景年表!O287:O305),情景年表!O287:O305,0)) -> 2033 | J17: =情景年表!O305 -> 11494.384 | K17: =IF(情景参数!E9="联动",(D17-1.2*E17)/((1-情景参数!C9)*C17),"不适用") -> 0.006327563 | L17: =IF(情景参数!E9="联动",(D17-E17)/((1-情景参数!C9)*C17),"不适用") -> 0.060924123
A18: 原表净收益降5% | B18: 早版 | C18: =SUM(情景年表!E306:E324) -> 205183.59 | D18: =SUM(情景年表!J306:J324) -> 71683.552 | E18: =SUM(情景年表!M306:M324) -> 49703 | F18: =D18/E18 -> 1.4422379 | G18: =MIN(情景年表!N306:N324) -> -13652.988 | H18: =MAX(0,-MIN(情景年表!O306:O324)) -> 16230.055 | I18: =INDEX(情景年表!D306:D324,MATCH(MIN(情景年表!O306:O324),情景年表!O306:O324,0)) -> 2028 | J18: =情景年表!O324 -> 21980.552 | K18: =IF(情景参数!E10="联动",(D18-1.2*E18)/((1-情景参数!C10)*C18),"不适用") -> 不适用 | L18: =IF(情景参数!E10="联动",(D18-E18)/((1-情景参数!C10)*C18),"不适用") -> 不适用
A19: 原表净收益降5% | B19: 晚版 | C19: =SUM(情景年表!E325:E343) -> 205183.59 | D19: =SUM(情景年表!J325:J343) -> 71683.552 | E19: =SUM(情景年表!M325:M343) -> 51502.9 | F19: =D19/E19 -> 1.3918352 | G19: =MIN(情景年表!N325:N343) -> -13652.988 | H19: =MAX(0,-MIN(情景年表!O325:O343)) -> 6701.9545 | I19: =INDEX(情景年表!D325:D343,MATCH(MIN(情景年表!O325:O343),情景年表!O325:O343,0)) -> 2028 | J19: =情景年表!O343 -> 20180.651 | K19: =IF(情景参数!E10="联动",(D19-1.2*E19)/((1-情景参数!C10)*C19),"不适用") -> 不适用 | L19: =IF(情景参数!E10="联动",(D19-E19)/((1-情景参数!C10)*C19),"不适用") -> 不适用
A20: 原表收入降5%成本固定 | B20: 早版 | C20: =SUM(情景年表!E344:E362) -> 205183.59 | D20: =SUM(情景年表!J344:J362) -> 65197.19 | E20: =SUM(情景年表!M344:M362) -> 49703 | F20: =D20/E20 -> 1.3117355 | G20: =MIN(情景年表!N344:N362) -> -14211.08 | H20: =MAX(0,-MIN(情景年表!O344:O362)) -> 16607.039 | I20: =INDEX(情景年表!D344:D362,MATCH(MIN(情景年表!O344:O362),情景年表!O344:O362,0)) -> 2028 | J20: =情景年表!O362 -> 15494.191 | K20: =IF(情景参数!E11="联动",(D20-1.2*E20)/((1-情景参数!C11)*C20),"不适用") -> 不适用 | L20: =IF(情景参数!E11="联动",(D20-E20)/((1-情景参数!C11)*C20),"不适用") -> 不适用
A21: 原表收入降5%成本固定 | B21: 晚版 | C21: =SUM(情景年表!E363:E381) -> 205183.59 | D21: =SUM(情景年表!J363:J381) -> 65197.19 | E21: =SUM(情景年表!M363:M381) -> 51502.9 | F21: =D21/E21 -> 1.2658936 | G21: =MIN(情景年表!N363:N381) -> -14211.08 | H21: =MAX(0,-MIN(情景年表!O363:O381)) -> 7937.2795 | I21: =INDEX(情景年表!D363:D381,MATCH(MIN(情景年表!O363:O381),情景年表!O363:O381,0)) -> 2033 | J21: =情景年表!O381 -> 13694.29 | K21: =IF(情景参数!E11="联动",(D21-1.2*E21)/((1-情景参数!C11)*C21),"不适用") -> 不适用 | L21: =IF(情景参数!E11="联动",(D21-E21)/((1-情景参数!C11)*C21),"不适用") -> 不适用
A22: 统一2%收入降5% | B22: 早版 | C22: =SUM(情景年表!E382:E400) -> 205183.59 | D22: =SUM(情景年表!J382:J400) -> 65356.008 | E22: =SUM(情景年表!M382:M400) -> 49703 | F22: =D22/E22 -> 1.3149309 | G22: =MIN(情景年表!N382:N400) -> -14202.201 | H22: =MAX(0,-MIN(情景年表!O382:O400)) -> 16597.806 | I22: =INDEX(情景年表!D382:D400,MATCH(MIN(情景年表!O382:O400),情景年表!O382:O400,0)) -> 2028 | J22: =情景年表!O400 -> 15653.008 | K22: =IF(情景参数!E12="联动",(D22-1.2*E22)/((1-情景参数!C12)*C22),"不适用") -> 0.028408645 | L22: =IF(情景参数!E12="联动",(D22-E22)/((1-情景参数!C12)*C22),"不适用") -> 0.077844711
A23: 统一2%收入降5% | B23: 晚版 | C23: =SUM(情景年表!E401:E419) -> 205183.59 | D23: =SUM(情景年表!J401:J419) -> 65356.008 | E23: =SUM(情景年表!M401:M419) -> 51502.9 | F23: =D23/E23 -> 1.2689772 | G23: =MIN(情景年表!N401:N419) -> -14202.201 | H23: =MAX(0,-MIN(情景年表!O401:O419)) -> 7867.5452 | I23: =INDEX(情景年表!D401:D419,MATCH(MIN(情景年表!O401:O419),情景年表!O401:O419,0)) -> 2033 | J23: =情景年表!O419 -> 13853.108 | K23: =IF(情景参数!E12="联动",(D23-1.2*E23)/((1-情景参数!C12)*C23),"不适用") -> 0.017667245 | L23: =IF(情景参数!E12="联动",(D23-E23)/((1-情景参数!C12)*C23),"不适用") -> 0.068893543
A24: 统一5%收入降5% | B24: 早版 | C24: =SUM(情景年表!E420:E438) -> 205183.59 | D24: =SUM(情景年表!J420:J438) -> 59508.276 | E24: =SUM(情景年表!M420:M438) -> 49703 | F24: =D24/E24 -> 1.1972773 | G24: =MIN(情景年表!N420:N438) -> -14730.043 | H24: =MAX(0,-MIN(情景年表!O420:O438)) -> 16860.992 | I24: =INDEX(情景年表!D420:D438,MATCH(MIN(情景年表!O420:O438),情景年表!O420:O438,0)) -> 2028 | J24: =情景年表!O438 -> 9805.2758 | K24: =IF(情景参数!E13="联动",(D24-1.2*E24)/((1-情景参数!C13)*C24),"不适用") -> -0.00069423955 | L24: =IF(情景参数!E13="联动",(D24-E24)/((1-情景参数!C13)*C24),"不适用") -> 0.050302965
A25: 统一5%收入降5% | B25: 晚版 | C25: =SUM(情景年表!E439:E457) -> 205183.59 | D25: =SUM(情景年表!J439:J457) -> 59508.276 | E25: =SUM(情景年表!M439:M457) -> 51502.9 | F25: =D25/E25 -> 1.1554354 | G25: =MIN(情景年表!N439:N457) -> -14730.043 | H25: =MAX(0,-MIN(情景年表!O439:O457)) -> 9855.5567 | I25: =INDEX(情景年表!D439:D457,MATCH(MIN(情景年表!O439:O457),情景年表!O439:O457,0)) -> 2033 | J25: =情景年表!O457 -> 8005.3758 | K25: =IF(情景参数!E13="联动",(D25-1.2*E25)/((1-情景参数!C13)*C25),"不适用") -> -0.011774843 | L25: =IF(情景参数!E13="联动",(D25-E25)/((1-情景参数!C13)*C25),"不适用") -> 0.041069129
A26: 文字周期甲5%收入降5% | B26: 早版 | C26: =SUM(情景年表!E458:E476) -> 198899.42 | D26: =SUM(情景年表!J458:J476) -> 53836.81 | E26: =SUM(情景年表!M458:M476) -> 49703 | F26: =D26/E26 -> 1.0831702 | G26: =MIN(情景年表!N458:N476) -> -15410.872 | H26: =MAX(0,-MIN(情景年表!O458:O476)) -> 17003.293 | I26: =INDEX(情景年表!D458:D476,MATCH(MIN(情景年表!O458:O476),情景年表!O458:O476,0)) -> 2028 | J26: =情景年表!O476 -> 4133.8101 | K26: =IF(情景参数!E14="联动",(D26-1.2*E26)/((1-情景参数!C14)*C26),"不适用") -> -0.030731163 | L26: =IF(情景参数!E14="联动",(D26-E26)/((1-情景参数!C14)*C26),"不适用") -> 0.021877284
A27: 文字周期甲5%收入降5% | B27: 晚版 | C27: =SUM(情景年表!E477:E495) -> 198899.42 | D27: =SUM(情景年表!J477:J495) -> 53836.81 | E27: =SUM(情景年表!M477:M495) -> 51502.9 | F27: =D27/E27 -> 1.0453161 | G27: =MIN(情景年表!N477:N495) -> -15410.872 | H27: =MAX(0,-MIN(情景年表!O477:O495)) -> 11169.225 | I27: =INDEX(情景年表!D477:D495,MATCH(MIN(情景年表!O477:O495),情景年表!O477:O495,0)) -> 2033 | J27: =情景年表!O495 -> 2333.9101 | K27: =IF(情景参数!E14="联动",(D27-1.2*E27)/((1-情景参数!C14)*C27),"不适用") -> -0.042161855 | L27: =IF(情景参数!E14="联动",(D27-E27)/((1-情景参数!C14)*C27),"不适用") -> 0.012351708
A28: 文字周期甲2%收入降5% | B28: 早版 | C28: =SUM(情景年表!E496:E514) -> 198899.42 | D28: =SUM(情景年表!J496:J514) -> 59505.443 | E28: =SUM(情景年表!M496:M514) -> 49703 | F28: =D28/E28 -> 1.1972204 | G28: =MIN(情景年表!N496:N514) -> -14904.529 | H28: =MAX(0,-MIN(情景年表!O496:O514)) -> 16744.602 | I28: =INDEX(情景年表!D496:D514,MATCH(MIN(情景年表!O496:O514),情景年表!O496:O514,0)) -> 2028 | J28: =情景年表!O514 -> 9802.4435 | K28: =IF(情景参数!E15="联动",(D28-1.2*E28)/((1-情景参数!C15)*C28),"不适用") -> -0.00070878066 | L28: =IF(情景参数!E15="联动",(D28-E28)/((1-情景参数!C15)*C28),"不适用") -> 0.050289204
A29: 文字周期甲2%收入降5% | B29: 晚版 | C29: =SUM(情景年表!E515:E533) -> 198899.42 | D29: =SUM(情景年表!J515:J533) -> 59505.443 | E29: =SUM(情景年表!M515:M533) -> 51502.9 | F29: =D29/E29 -> 1.1553804 | G29: =MIN(情景年表!N515:N533) -> -14904.529 | H29: =MAX(0,-MIN(情景年表!O515:O533)) -> 9222.6979 | I29: =INDEX(情景年表!D515:D533,MATCH(MIN(情景年表!O515:O533),情景年表!O515:O533,0)) -> 2033 | J29: =情景年表!O533 -> 8002.5435 | K29: =IF(情景参数!E15="联动",(D29-1.2*E29)/((1-情景参数!C15)*C29),"不适用") -> -0.011789553 | L29: =IF(情景参数!E15="联动",(D29-E29)/((1-情景参数!C15)*C29),"不适用") -> 0.041055227
A30: 收费修正2%收入降5% | B30: 早版 | C30: =SUM(情景年表!E534:E552) -> 199365.81 | D30: =SUM(情景年表!J534:J552) -> 59939.652 | E30: =SUM(情景年表!M534:M552) -> 49703 | F30: =D30/E30 -> 1.2059564 | G30: =MIN(情景年表!N534:N552) -> -14877.075 | H30: =MAX(0,-MIN(情景年表!O534:O552)) -> 16744.606 | I30: =INDEX(情景年表!D534:D552,MATCH(MIN(情景年表!O534:O552),情景年表!O534:O552,0)) -> 2028 | J30: =情景年表!O552 -> 10236.652 | K30: =IF(情景参数!E16="联动",(D30-1.2*E30)/((1-情景参数!C16)*C30),"不适用") -> 0.0015152752 | L30: =IF(情景参数!E16="联动",(D30-E30)/((1-情景参数!C16)*C30),"不适用") -> 0.052393957
A31: 收费修正2%收入降5% | B31: 晚版 | C31: =SUM(情景年表!E553:E571) -> 199365.81 | D31: =SUM(情景年表!J553:J571) -> 59939.652 | E31: =SUM(情景年表!M553:M571) -> 51502.9 | F31: =D31/E31 -> 1.1638112 | G31: =MIN(情景年表!N553:N571) -> -14877.075 | H31: =MAX(0,-MIN(情景年表!O553:O571)) -> 8998.122 | I31: =INDEX(情景年表!D553:D571,MATCH(MIN(情景年表!O553:O571),情景年表!O553:O571,0)) -> 2033 | J31: =情景年表!O571 -> 8436.7522 | K31: =IF(情景参数!E16="联动",(D31-1.2*E31)/((1-情景参数!C16)*C31),"不适用") -> -0.0095395753 | L31: =IF(情景参数!E16="联动",(D31-E31)/((1-情景参数!C16)*C31),"不适用") -> 0.043181581
A32: 收费修正5%收入降5% | B32: 早版 | C32: =SUM(情景年表!E572:E590) -> 199365.81 | D32: =SUM(情景年表!J572:J590) -> 54257.727 | E32: =SUM(情景年表!M572:M590) -> 49703 | F32: =D32/E32 -> 1.0916389 | G32: =MIN(情景年表!N572:N590) -> -15384.258 | H32: =MAX(0,-MIN(情景年表!O572:O590)) -> 17003.298 | I32: =INDEX(情景年表!D572:D590,MATCH(MIN(情景年表!O572:O590),情景年表!O572:O590,0)) -> 2028 | J32: =情景年表!O590 -> 4554.7267 | K32: =IF(情景参数!E17="联动",(D32-1.2*E32)/((1-情景参数!C17)*C32),"不适用") -> -0.028436874 | L32: =IF(情景参数!E17="联动",(D32-E32)/((1-情景参数!C17)*C32),"不适用") -> 0.024048503
A33: 收费修正5%收入降5% | B33: 晚版 | C33: =SUM(情景年表!E591:E609) -> 199365.81 | D33: =SUM(情景年表!J591:J609) -> 54257.727 | E33: =SUM(情景年表!M591:M609) -> 51502.9 | F33: =D33/E33 -> 1.0534888 | G33: =MIN(情景年表!N591:N609) -> -15384.258 | H33: =MAX(0,-MIN(情景年表!O591:O609)) -> 10951.524 | I33: =INDEX(情景年表!D591:D609,MATCH(MIN(情景年表!O591:O609),情景年表!O591:O609,0)) -> 2033 | J33: =情景年表!O609 -> 2754.8267 | K33: =IF(情景参数!E17="联动",(D33-1.2*E33)/((1-情景参数!C17)*C33),"不适用") -> -0.039840825 | L33: =IF(情景参数!E17="联动",(D33-E33)/((1-情景参数!C17)*C33),"不适用") -> 0.01454521
A34: 文字周期乙2% | B34: 早版 | C34: =SUM(情景年表!E610:E628) -> 198597.05 | D34: =SUM(情景年表!J610:J628) -> 68955.195 | E34: =SUM(情景年表!M610:M628) -> 49703 | F34: =D34/E34 -> 1.3873447 | G34: =MIN(情景年表!N610:N628) -> -14068.65 | H34: =MAX(0,-MIN(情景年表!O610:O628)) -> 16299.833 | I34: =INDEX(情景年表!D610:D628,MATCH(MIN(情景年表!O610:O628),情景年表!O610:O628,0)) -> 2028 | J34: =情景年表!O628 -> 19252.195 | K34: =IF(情景参数!E18="联动",(D34-1.2*E34)/((1-情景参数!C18)*C34),"不适用") -> 0.04784375 | L34: =IF(情景参数!E18="联动",(D34-E34)/((1-情景参数!C18)*C34),"不适用") -> 0.09891938
A35: 文字周期乙2% | B35: 晚版 | C35: =SUM(情景年表!E629:E647) -> 198597.05 | D35: =SUM(情景年表!J629:J647) -> 68955.195 | E35: =SUM(情景年表!M629:M647) -> 51502.9 | F35: =D35/E35 -> 1.3388604 | G35: =MIN(情景年表!N629:N647) -> -14068.65 | H35: =MAX(0,-MIN(情景年表!O629:O647)) -> 6771.7333 | I35: =INDEX(情景年表!D629:D647,MATCH(MIN(情景年表!O629:O647),情景年表!O629:O647,0)) -> 2028 | J35: =情景年表!O647 -> 17452.295 | K35: =IF(情景参数!E18="联动",(D35-1.2*E35)/((1-情景参数!C18)*C35),"不适用") -> 0.036746107 | L35: =IF(情景参数!E18="联动",(D35-E35)/((1-情景参数!C18)*C35),"不适用") -> 0.089671344
A36: 文字周期乙2%收入降5% | B36: 早版 | C36: =SUM(情景年表!E648:E666) -> 198597.05 | D36: =SUM(情景年表!J648:J666) -> 59223.94 | E36: =SUM(情景年表!M648:M666) -> 49703 | F36: =D36/E36 -> 1.1915566 | G36: =MIN(情景年表!N648:N666) -> -14937.471 | H36: =MAX(0,-MIN(情景年表!O648:O666)) -> 16744.602 | I36: =INDEX(情景年表!D648:D666,MATCH(MIN(情景年表!O648:O666),情景年表!O648:O666,0)) -> 2028 | J36: =情景年表!O666 -> 9520.9396 | K36: =IF(情景参数!E19="联动",(D36-1.2*E36)/((1-情景参数!C19)*C36),"不适用") -> -0.0021562499 | L36: =IF(情景参数!E19="联动",(D36-E36)/((1-情景参数!C19)*C36),"不适用") -> 0.04891938
A37: 文字周期乙2%收入降5% | B37: 晚版 | C37: =SUM(情景年表!E667:E685) -> 198597.05 | D37: =SUM(情景年表!J667:J685) -> 59223.94 | E37: =SUM(情景年表!M667:M685) -> 51502.9 | F37: =D37/E37 -> 1.1499147 | G37: =MIN(情景年表!N667:N685) -> -14937.471 | H37: =MAX(0,-MIN(情景年表!O667:O685)) -> 9252.6451 | I37: =INDEX(情景年表!D667:D685,MATCH(MIN(情景年表!O667:O685),情景年表!O667:O685,0)) -> 2033 | J37: =情景年表!O685 -> 7721.0396 | K37: =IF(情景参数!E19="联动",(D37-1.2*E37)/((1-情景参数!C19)*C37),"不适用") -> -0.013253893 | L37: =IF(情景参数!E19="联动",(D37-E37)/((1-情景参数!C19)*C37),"不适用") -> 0.039671344
A38: 文字周期乙5%收入降5% | B38: 早版 | C38: =SUM(情景年表!E686:E704) -> 198597.05 | D38: =SUM(情景年表!J686:J704) -> 53563.924 | E38: =SUM(情景年表!M686:M704) -> 49703 | F38: =D38/E38 -> 1.0776799 | G38: =MIN(情景年表!N686:N704) -> -15442.805 | H38: =MAX(0,-MIN(情景年表!O686:O704)) -> 17003.293 | I38: =INDEX(情景年表!D686:D704,MATCH(MIN(情景年表!O686:O704),情景年表!O686:O704,0)) -> 2028 | J38: =情景年表!O704 -> 3860.9237 | K38: =IF(情景参数!E20="联动",(D38-1.2*E38)/((1-情景参数!C20)*C38),"不适用") -> -0.032224342 | L38: =IF(情景参数!E20="联动",(D38-E38)/((1-情景参数!C20)*C38),"不适用") -> 0.020464202
A39: 文字周期乙5%收入降5% | B39: 晚版 | C39: =SUM(情景年表!E705:E723) -> 198597.05 | D39: =SUM(情景年表!J705:J723) -> 53563.924 | E39: =SUM(情景年表!M705:M723) -> 51502.9 | F39: =D39/E39 -> 1.0400176 | G39: =MIN(情景年表!N705:N723) -> -15442.805 | H39: =MAX(0,-MIN(情景年表!O705:O723)) -> 11198.256 | I39: =INDEX(情景年表!D705:D723,MATCH(MIN(情景年表!O705:O723),情景年表!O705:O723,0)) -> 2033 | J39: =情景年表!O723 -> 2061.0237 | K39: =IF(情景参数!E20="联动",(D39-1.2*E39)/((1-情景参数!C20)*C39),"不适用") -> -0.043672437 | L39: =IF(情景参数!E20="联动",(D39-E39)/((1-情景参数!C20)*C39),"不适用") -> 0.010924123

Sheet 来源
A1: 文件 | B1: 机构 | C1: 发布日期或成文日 | D1: 网址 | E1: 用途 | F1: SHA256
A2: 01_专项债收益修正公告_2025年4月28日.html | B2: 广州市南沙区财政局 | C2: 2025-04-28 | D2: https://www.gzns.gov.cn/zwgk/zdlyxxgk/czgl/zfxzwxx/content/post_10241159.html | E2: 披露范围及2024年三期募资合计6400万元；原网页HTML | F2: 0d6e8ab0192ca56d583848b2a5a69aab87b572ab53239479c15e08c2129534d9
A3: 02_十二期_口腔医院专项评价报告.pdf | B3: 广州市光领有限责任会计师事务所；南沙区财政局公开 | C3: 2025-04-28（报告签署2024-03-18） | D3: https://www.gzns.gov.cn/gznsczgz/attachment/7/7807/7807842/10241160.zip | E3: ZIP中的十二期PDF；早版融资、运营及偿债表 | F3: 949ada2b0877a91af86cd6922ed1119c5d1d9c4abde5b33b5104f9060c852600
A4: 03_六十一期_口腔医院专项评价报告.pdf | B4: 广州市光领有限责任会计师事务所；南沙区财政局公开 | C4: 2025-04-28（报告签署2024-08-18） | D4: https://www.gzns.gov.cn/gznsczgz/attachment/7/7807/7807842/10241160.zip | E4: ZIP中的六十一期PDF；晚版融资及对应测算 | F4: 99179865586e35651cde9aaa4802cb4888ac7b6945b760f0464a63424ffbcc80
A5: 04_六十九期_口腔医院专项评价报告.pdf | B5: 广州市光领有限责任会计师事务所；南沙区财政局公开 | C5: 2025-04-28（报告签署2024-08-18） | D5: https://www.gzns.gov.cn/gznsczgz/attachment/7/7807/7807842/10241160.zip | E5: ZIP中的六十九期PDF；附件版本对应核对 | F5: 99179865586e35651cde9aaa4802cb4888ac7b6945b760f0464a63424ffbcc80
A6: 05_机动车停放服务收费管理通知_穗发改规字2021年2号.html | B6: 广州市发展改革委等四部门 | C6: 2021-08-26（成文2021-08-23） | D6: https://fgw.gz.gov.cn/gkmlpt/content/7/7530/post_7530042.html | E6: 停车类别、减免、调价及有效期；原网页HTML | F6: b03afe0e320b5011fcc9256e29a485fd28663d931574f592d8dd67c8891794e5
A7: 06_停车收费通知附件二_收费标准.doc | B7: 广州市发展改革委等四部门 | C7: 2021-08-26 | D7: https://fgw.gz.gov.cn/attachment/7/7475/7475440/7530042.doc | E7: 南沙对应的日夜间收费及封顶；官方原始Word附件 | F7: c863f67c21a6f39e77192e5008049d7f9e7d3756cf9a317658b60cfb11ccdddc
A8: 07_转发新能源汽车用电价格通知_穗发改规字2018年12号.html | B8: 广州市发展改革委 | C8: 2018-09-18（正文落款2018-09-17） | D8: https://fgw.gz.gov.cn/gkmlpt/content/5/5492/post_5492267.html | E8: 历史充电收费文件衔接；原网页HTML | F8: 82a550d435474912ee5290bad5c4518e8b1efe85e2dfbbc7ace41a5c6395ce9e
A9: 08_新能源汽车用电价格通知_粤发改价格2018年313号.pdf | B9: 广东省发展改革委（广州市发展改革委公开附件） | C9: 成文2018-06-28；广州页面2018-09-18 | D9: https://fgw.gz.gov.cn/attachment/7/7504/7504176/5492267.pdf | E9: 报告0.8元引用依据，历史适用条件 | F9: ae991cfc334d92590074d58f23db515f2a8d393deae67fae5c60a251e559cabc
A10: 09_广东省定价目录2022年版及印发通知.pdf | B10: 广东省人民政府办公厅（天河区政府公开原件） | C10: 成文2022-02-24；页面2023-01-17 | D10: https://www.thnet.gov.cn/attachment/7/7224/7224222/8766863.pdf | E10: 2022-03-15起的定价范围；官方PDF，含印发通知及目录 | F10: 488acf62a896683bafb368e79296971b439f9fb1a8857dbcc5687187b3f79c33
A11: 10_贯彻省定价目录通知及解读_官方原网页.html | B11: 广东省发展改革委（汕尾市发展改革局转载） | C11: 2022-03-14（通知成文2022-03-09） | D11: https://www.shanwei.gov.cn/swdpb/zhuanti/zdlyxxgk/jgzc/content/post_998504.html | E11: 新旧文件衔接、严禁保留目录外定价事项；原网页HTML | F11: 2ef53d0c59058327f406999090528882c9512f7bd6425998711fac4cf3a5ae7f

Sheet 版本
A1: 附件 | B1: 报告文号 | C1: 评估截止日 | D1: 签署日 | E1: 拟融资总额 | F1: 已有融资 | G1: 2024待发本金 | H1: 待发期限 | I1: 待发利率 | J1: 报告本息 | K1: 报告覆盖 | L1: 处理
A2: 十二期 | B2: 光领发字（2024）07-100号 | C2: 2024-02-29 | D2: 2024-03-18 | E2: 34000 | F2: 23000 | G2: 11000 | H2: 5 | I2: 0.033 | J2: 49703 | K2: 1.52 | L2: 早版，独立复现
A3: 六十一期 | B3: 光领发字（2024）07-237号 | C3: 2024-07-31 | D3: 2024-08-18 | E3: 34000 | F3: 24400 | G3: 9600 | H3: 10 | I3: 0.036 | J3: 51502.9 | K3: 1.47 | L3: 晚版，主复核融资情景
A4: 六十九期 | B4: 光领发字（2024）07-237号 | C4: 2024-07-31 | D4: 2024-08-18 | E4: 34000 | F4: 24400 | G4: 9600 | H4: 10 | I4: 0.036 | J4: 51502.9 | K4: 1.47 | L4: 与六十一期逐字节相同，不累加
A5: 公告 | B5: 三期合计 | C5: 2025-04-28 | D5: 2025-04-28 | E5: 6400 | L5: 6400仅为2024三期募集额；11000及9600为各时点计划，不等于本批实际发行额

Sheet 参数
A1: 参数 | B1: 值 | C1: 来源及解释
A2: 门诊首年 | B2: 7500 | C2: 报告p4
A3: 住院首年 | B3: 850 | C3: 报告p4
A4: 前五年增长 | B4: 0.1 | C4: 2029—2032四次增长，2028基期
A5: 六至十年增长 | B5: 0.05 | C5: 2033—2037五次增长
A6: 十一年后增长 | B6: 0.02 | C6: 2038起
A7: 车位 | B7: 600 | C7: 报告p4
A8: 全年天数 | B8: 365 | C8: 保持报告365，不另作闰年调整
A9: 日间单价每半小时 | B9: 1.5 | C9: 停车标准副中心外围3小时内
A10: 日间停留小时 | B10: 2 | C10: 报告p4
A11: 日间周转 | B11: 3 | C11: 报告p4
A12: 首五年日间使用率 | B12: 0.8 | C12: 报告p4
A13: 后期日间使用率 | B13: 0.95 | C13: 报告p4
... A33: 六项费用增长 | B33: 0.03 | C33: 报告正文每年增长3%

Sheet 原表收入
A1: 年序 | B1: 映射年份 | C1: 门诊 | D1: 住院 | E1: 停车 | F1: 充电 | G1: 报告合计 | H1: 明细加总 | I1: 明细减报告 | J1: 出处
A2: 1 | B2: 2024 | C2: 0 | D2: 0 | E2: 0 | F2: 0 | G2: 0 | H2: =SUM(C2:F2) -> 0 | I2: =H2-G2 -> 0 | J2: 三报告p5
A3: 2 | B3: 2025 | C3: 0 | D3: 0 | E3: 0 | F3: 0 | G3: 0 | H3: =SUM(C3:F3) -> 0 | I3: =H3-G3 -> 0 | J3: 三报告p5
A4: 3 | B4: 2026 | C4: 0 | D4: 0 | E4: 0 | F4: 0 | G4: 0 | H4: =SUM(C4:F4) -> 0 | I4: =H4-G4 -> 0 | J4: 三报告p5
A5: 4 | B5: 2027 | C5: 0 | D5: 0 | E5: 0 | F5: 0 | G5: 0 | H5: =SUM(C5:F5) -> 0 | I5: =H5-G5 -> 0 | J5: 三报告p5
A6: 5 | B6: 2028 | C6: 7500 | D6: 850 | E6: 670.14 | F6: 214.44 | G6: 9234.58 | H6: =SUM(C6:F6) -> 9234.58 | I6: =H6-G6 -> 0 | J6: 三报告p5
A7: 6 | B7: 2029 | C7: 8250 | D7: 935 | E7: 670.14 | F7: 268.05 | G7: 10123.19 | H7: =SUM(C7:F7) -> 10123.19 | I7: =H7-G7 -> 0 | J7: 三报告p5
A8: 7 | B8: 2030 | C8: 9075 | D8: 1028.5 | E8: 670.14 | F8: 268.05 | G8: 11041.69 | H8: =SUM(C8:F8) -> 11041.69 | I8: =H8-G8 -> 0 | J8: 三报告p5
A9: 8 | B9: 2031 | C9: 9982.5 | D9: 1131.35 | E9: 670.14 | F9: 268.05 | G9: 12052.04 | H9: =SUM(C9:F9) -> 12052.04 | I9: =H9-G9 -> 0 | J9: 三报告p5
A10: 9 | B10: 2032 | C10: 10980.75 | D10: 1244.49 | E10: 670.14 | F10: 268.05 | G10: 13163.43 | H10: =SUM(C10:F10) -> 13163.43 | I10: =H10-G10 -> 0 | J10: 三报告p5
A11: 10 | B11: 2033 | C11: 11529.79 | D11: 1306.71 | E11: 1008.5 | F11: 294.86 | G11: 14139.86 | H11: =SUM(C11:F11) -> 14139.86 | I11: =H11-G11 -> 0 | J11: 三报告p5
A12: 11 | B12: 2034 | C12: 12106.28 | D12: 1372.05 | E12: 1008.5 | F12: 294.86 | G12: 14781.69 | H12: =SUM(C12:F12) -> 14781.69 | I12: =H12-G12 -> 0 | J12: 三报告p5
A13: 12 | B13: 2035 | C13: 12711.59 | D13: 1440.65 | E13: 1008.5 | F13: 294.86 | G13: 15455.6 | H13: =SUM(C13:F13) -> 15455.6 | I13: =H13-G13 -> 0 | J13: 三报告p5
... A19: 18 | B19: 2041 | C19: 15169.78 | D19: 1719.24 | E19: 1307.43 | F19: 324.35 | G19: 18520.8 | H19: =SUM(C19:F19) -> 18520.8 | I19: =H19-G19 -> 0 | J19: 三报告p5
A20: 合计 | C20: =SUM(C2:C19) -> 168415.26 | D20: =SUM(D2:D19) -> 19087.07 | E20: =SUM(E2:E19) -> 13622.92 | F20: =SUM(F2:F19) -> 4058.34 | G20: =SUM(G2:G19) -> 205183.59 | H20: =SUM(H2:H19) -> 205183.59 | I20: =SUM(I2:I19) -> 0

Sheet 原表费用
A1: 年序 | B1: 映射年份 | C1: 工资 | D1: 药品 | E1: 卫生材料 | F1: 水电燃气 | G1: 其他 | H1: 维修 | I1: 管理费 | J1: 报告合计 | K1: 七项加总 | L1: 加总差 | M1: 收入2% | N1: 收入5% | O1: 2%减原管理费 | P1: 有效费率 | Q1: 出处
A2: 1 | B2: 2024 | C2: 0 | D2: 0 | E2: 0 | F2: 0 | G2: 0 | H2: 0 | I2: 0 | J2: 0 | K2: =SUM(C2:I2) -> 0 | L2: =K2-J2 -> 0 | M2: =原表收入!G2*2% -> 0 | N2: =原表收入!G2*5% -> 0 | O2: =M2-I2 -> 0 | P2: =IFERROR(I2/原表收入!G2,0) -> 0 | Q2: 三报告p6
A3: 2 | B3: 2025 | C3: 0 | D3: 0 | E3: 0 | F3: 0 | G3: 0 | H3: 0 | I3: 0 | J3: 0 | K3: =SUM(C3:I3) -> 0 | L3: =K3-J3 -> 0 | M3: =原表收入!G3*2% -> 0 | N3: =原表收入!G3*5% -> 0 | O3: =M3-I3 -> 0 | P3: =IFERROR(I3/原表收入!G3,0) -> 0 | Q3: 三报告p6
A4: 3 | B4: 2026 | C4: 0 | D4: 0 | E4: 0 | F4: 0 | G4: 0 | H4: 0 | I4: 0 | J4: 0 | K4: =SUM(C4:I4) -> 0 | L4: =K4-J4 -> 0 | M4: =原表收入!G4*2% -> 0 | N4: =原表收入!G4*5% -> 0 | O4: =M4-I4 -> 0 | P4: =IFERROR(I4/原表收入!G4,0) -> 0 | Q4: 三报告p6
A5: 4 | B5: 2027 | C5: 0 | D5: 0 | E5: 0 | F5: 0 | G5: 0 | H5: 0 | I5: 0 | J5: 0 | K5: =SUM(C5:I5) -> 0 | L5: =K5-J5 -> 0 | M5: =原表收入!G5*2% -> 0 | N5: =原表收入!G5*5% -> 0 | O5: =M5-I5 -> 0 | P5: =IFERROR(I5/原表收入!G5,0) -> 0 | Q5: 三报告p6
A6: 5 | B6: 2028 | C6: 5600 | D6: 170 | E6: 1470 | F6: 60 | G6: 35 | H6: 20 | I6: 184.69 | J6: 7539.69 | K6: =SUM(C6:I6) -> 7539.69 | L6: =K6-J6 -> 0 | M6: =原表收入!G6*2% -> 184.6916 | N6: =原表收入!G6*5% -> 461.729 | O6: =M6-I6 -> 0.0016 | P6: =IFERROR(I6/原表收入!G6,0) -> 0.019999827 | Q6: 三报告p6
A7: 6 | B7: 2029 | C7: 5768 | D7: 175.1 | E7: 1514.1 | F7: 61.8 | G7: 36.05 | H7: 20.6 | I7: 202.46 | J7: 7778.11 | K7: =SUM(C7:I7) -> 7778.11 | L7: =K7-J7 -> 0 | M7: =原表收入!G7*2% -> 202.4638 | N7: =原表收入!G7*5% -> 506.1595 | O7: =M7-I7 -> 0.0038 | P7: =IFERROR(I7/原表收入!G7,0) -> 0.019999625 | Q7: 三报告p6
A8: 7 | B8: 2030 | C8: 5941.04 | D8: 180.35 | E8: 1559.52 | F8: 63.65 | G8: 37.13 | H8: 21.22 | I8: 220.83 | J8: 8023.74 | K8: =SUM(C8:I8) -> 8023.74 | L8: =K8-J8 -> 0 | M8: =原表收入!G8*2% -> 220.8338 | N8: =原表收入!G8*5% -> 552.0845 | O8: =M8-I8 -> 0.0038 | P8: =IFERROR(I8/原表收入!G8,0) -> 0.019999656 | Q8: 三报告p6
A9: 8 | B9: 2031 | C9: 6119.27 | D9: 185.76 | E9: 1606.31 | F9: 65.56 | G9: 38.25 | H9: 21.85 | I9: 241.04 | J9: 8278.04 | K9: =SUM(C9:I9) -> 8278.04 | L9: =K9-J9 -> 0 | M9: =原表收入!G9*2% -> 241.0408 | N9: =原表收入!G9*5% -> 602.602 | O9: =M9-I9 -> 0.0008 | P9: =IFERROR(I9/原表收入!G9,0) -> 0.019999934 | Q9: 三报告p6
A10: 9 | B10: 2032 | C10: 6302.85 | D10: 191.33 | E10: 1654.5 | F10: 67.53 | G10: 39.39 | H10: 22.51 | I10: 263.27 | J10: 8541.38 | K10: =SUM(C10:I10) -> 8541.38 | L10: =K10-J10 -> 0 | M10: =原表收入!G10*2% -> 263.2686 | N10: =原表收入!G10*5% -> 658.1715 | O10: =M10-I10 -> -0.0014 | P10: =IFERROR(I10/原表收入!G10,0) -> 0.020000106 | Q10: 三报告p6
A11: 10 | B11: 2033 | C11: 6491.94 | D11: 197.07 | E11: 1704.14 | F11: 69.56 | G11: 40.57 | H11: 23.19 | I11: 282.8 | J11: 8809.27 | K11: =SUM(C11:I11) -> 8809.27 | L11: =K11-J11 -> 0 | M11: =原表收入!G11*2% -> 282.7972 | N11: =原表收入!G11*5% -> 706.993 | O11: =M11-I11 -> -0.0028 | P11: =IFERROR(I11/原表收入!G11,0) -> 0.020000198 | Q11: 三报告p6
A12: 11 | B12: 2034 | C12: 6686.7 | D12: 202.98 | E12: 1755.26 | F12: 71.65 | G12: 41.79 | H12: 23.88 | I12: 295.63 | J12: 9077.89 | K12: =SUM(C12:I12) -> 9077.89 | L12: =K12-J12 -> 0 | M12: =原表收入!G12*2% -> 295.6338 | N12: =原表收入!G12*5% -> 739.0845 | O12: =M12-I12 -> 0.0038 | P12: =IFERROR(I12/原表收入!G12,0) -> 0.019999743 | Q12: 三报告p6
A13: 12 | B13: 2035 | C13: 6887.3 | D13: 209.07 | E13: 1807.92 | F13: 73.8 | G13: 43.05 | H13: 24.6 | I13: 309.11 | J13: 9354.85 | K13: =SUM(C13:I13) -> 9354.85 | L13: =K13-J13 -> 0 | M13: =原表收入!G13*2% -> 309.112 | N13: =原表收入!G13*5% -> 772.78 | O13: =M13-I13 -> 0.002 | P13: =IFERROR(I13/原表收入!G13,0) -> 0.019999871 | Q13: 三报告p6
... A19: 18 | B19: 2041 | C19: 8223.8 | D19: 249.63 | E19: 2158.75 | F19: 88.12 | G19: 51.4 | H19: 29.37 | I19: 360.77 | J19: 11161.84 | K19: =SUM(C19:I19) -> 11161.84 | L19: =K19-J19 -> 0 | M19: =原表收入!G19*2% -> 370.416 | N19: =原表收入!G19*5% -> 926.04 | O19: =M19-I19 -> 9.646 | P19: =IFERROR(I19/原表收入!G19,0) -> 0.01947918 | Q19: 三报告p6
A20: 合计 | C20: =SUM(C2:C19) -> 95683.49 | D20: =SUM(D2:D19) -> 2904.54 | E20: =SUM(E2:E19) -> 25116.94 | F20: =SUM(F2:F19) -> 1025.22 | G20: =SUM(G2:G19) -> 598.03 | H20: =SUM(H2:H19) -> 341.74 | I20: =SUM(I2:I19) -> 4057.26 | J20: =SUM(J2:J19) -> 129727.22 | ... O20: =SUM(O2:O19) -> 46.4118

Sheet 融资计划
A1: 版本 | B1: 批次 | C1: 发行年 | D1: 本金 | E1: 利率 | F1: 期限年 | G1: 报告偿本年序 | H1: 年息 | I1: 全期限利息 | J1: 按发行年推到期年 | K1: 报告映射年 | L1: 年差
A2: 早版 | B2: 2022三十期 | C2: 2022 | D2: 20000 | E2: 0.0322 | F2: 20 | G2: 18 | H2: =D2*E2 -> 644 | I2: =H2*F2 -> 12880 | J2: =C2+F2 -> 2042 | K2: =2023+G2 -> 2041 | L2: =J2-K2 -> 1
A3: 早版 | B3: 2023二十二期 | C3: 2023 | D3: 1000 | E3: 0.0292 | F3: 15 | G3: 14 | H3: =D3*E3 -> 29.2 | I3: =H3*F3 -> 438 | J3: =C3+F3 -> 2038 | K3: =2023+G3 -> 2037 | L3: =J3-K3 -> 1
A4: 早版 | B4: 2023三十四期 | C4: 2023 | D4: 2000 | E4: 0.0285 | F4: 10 | G4: 9 | H4: =D4*E4 -> 57 | I4: =H4*F4 -> 570 | J4: =C4+F4 -> 2033 | K4: =2023+G4 -> 2032 | L4: =J4-K4 -> 1
A5: 早版 | B5: 2024待发 | C5: 2024 | D5: 11000 | E5: 0.033 | F5: 5 | G5: 5 | H5: =D5*E5 -> 363 | I5: =H5*F5 -> 1815 | J5: =C5+F5 -> 2029 | K5: =2023+G5 -> 2028 | L5: =J5-K5 -> 1
A6: 晚版 | B6: 2022三十期 | C6: 2022 | D6: 20000 | E6: 0.0322 | F6: 20 | G6: 18 | H6: =D6*E6 -> 644 | I6: =H6*F6 -> 12880 | J6: =C6+F6 -> 2042 | K6: =2023+G6 -> 2041 | L6: =J6-K6 -> 1
A7: 晚版 | B7: 2023二十二期 | C7: 2023 | D7: 1000 | E7: 0.0292 | F7: 15 | G7: 14 | H7: =D7*E7 -> 29.2 | I7: =H7*F7 -> 438 | J7: =C7+F7 -> 2038 | K7: =2023+G7 -> 2037 | L7: =J7-K7 -> 1
A8: 晚版 | B8: 2023三十四期 | C8: 2023 | D8: 2000 | E8: 0.0285 | F8: 10 | G8: 9 | H8: =D8*E8 -> 57 | I8: =H8*F8 -> 570 | J8: =C8+F8 -> 2033 | K8: =2023+G8 -> 2032 | L8: =J8-K8 -> 1
A9: 晚版 | B9: 2024十二期 | C9: 2024 | D9: 1400 | E9: 0.0227 | F9: 5 | G9: 5 | H9: =D9*E9 -> 31.78 | I9: =H9*F9 -> 158.9 | J9: =C9+F9 -> 2029 | K9: =2023+G9 -> 2028 | L9: =J9-K9 -> 1
A10: 晚版 | B10: 2024待发 | C10: 2024 | D10: 9600 | E10: 0.036 | F10: 10 | G10: 10 | H10: =D10*E10 -> 345.6 | I10: =H10*F10 -> 3456 | J10: =C10+F10 -> 2034 | K10: =2023+G10 -> 2033 | L10: =J10-K10 -> 1

Sheet 偿债原表
A1: 年序 | B1: 映射年份 | C1: 早本金 | D1: 早利息 | E1: 早本息 | F1: 晚本金 | G1: 晚利息 | H1: 晚本息 | I1: 早利息复算 | J1: 晚利息复算 | K1: 早差 | L1: 晚差
A2: 0 | B2: 已融资 | C2: 0 | D2: 1374.2 | E2: =C2+D2 -> 1374.2 | F2: 0 | G2: 1374.2 | H2: =F2+G2 -> 1374.2 | I2: =融资计划!H2*2+融资计划!H3+融资计划!H4 -> 1374.2 | J2: =融资计划!H6*2+融资计划!H7+融资计划!H8 -> 1374.2 | K2: =I2-D2 -> 0 | L2: =J2-G2 -> 0
A3: 1 | B3: 2024 | C3: 0 | D3: 1093.2 | E3: =C3+D3 -> 1093.2 | F3: 0 | G3: 1107.58 | H3: =F3+G3 -> 1107.58 | I3: =IF(A3<=融资计划!G2,融资计划!H2,0)+IF(A3<=融资计划!G3,融资计划!H3,0)+IF(A3<=融资计划!G4,融资计划!H4,0)+IF(A3<=融资计划!G5,融资计划!H5,0) -> 1093.2 | J3: =IF(A3<=融资计划!G6,融资计划!H6,0)+IF(A3<=融资计划!G7,融资计划!H7,0)+IF(A3<=融资计划!G8,融资计划!H8,0)+IF(A3<=融资计划!G9,融资计划!H9,0)+IF(A3<=融资计划!G10,融资计划!H10,0) -> 1107.58 | K3: =I3-D3 -> 0 | L3: =J3-G3 -> 0
A4: 2 | B4: 2025 | C4: 0 | D4: 1093.2 | E4: =C4+D4 -> 1093.2 | F4: 0 | G4: 1107.58 | H4: =F4+G4 -> 1107.58 | I4: =IF(A4<=融资计划!G2,融资计划!H2,0)+IF(A4<=融资计划!G3,融资计划!H3,0)+IF(A4<=融资计划!G4,融资计划!H4,0)+IF(A4<=融资计划!G5,融资计划!H5,0) -> 1093.2 | J4: =IF(A4<=融资计划!G6,融资计划!H6,0)+IF(A4<=融资计划!G7,融资计划!H7,0)+IF(A4<=融资计划!G8,融资计划!H8,0)+IF(A4<=融资计划!G9,融资计划!H9,0)+IF(A4<=融资计划!G10,融资计划!H10,0) -> 1107.58 | K4: =I4-D4 -> 0 | L4: =J4-G4 -> 0
A5: 3 | B5: 2026 | C5: 0 | D5: 1093.2 | E5: =C5+D5 -> 1093.2 | F5: 0 | G5: 1107.58 | H5: =F5+G5 -> 1107.58 | I5: =IF(A5<=融资计划!G2,融资计划!H2,0)+IF(A5<=融资计划!G3,融资计划!H3,0)+IF(A5<=融资计划!G4,融资计划!H4,0)+IF(A5<=融资计划!G5,融资计划!H5,0) -> 1093.2 | J5: =IF(A5<=融资计划!G6,融资计划!H6,0)+IF(A5<=融资计划!G7,融资计划!H7,0)+IF(A5<=融资计划!G8,融资计划!H8,0)+IF(A5<=融资计划!G9,融资计划!H9,0)+IF(A5<=融资计划!G10,融资计划!H10,0) -> 1107.58 | K5: =I5-D5 -> 0 | L5: =J5-G5 -> 0
A6: 4 | B6: 2027 | C6: 0 | D6: 1093.2 | E6: =C6+D6 -> 1093.2 | F6: 0 | G6: 1107.58 | H6: =F6+G6 -> 1107.58 | I6: =IF(A6<=融资计划!G2,融资计划!H2,0)+IF(A6<=融资计划!G3,融资计划!H3,0)+IF(A6<=融资计划!G4,融资计划!H4,0)+IF(A6<=融资计划!G5,融资计划!H5,0) -> 1093.2 | J6: =IF(A6<=融资计划!G6,融资计划!H6,0)+IF(A6<=融资计划!G7,融资计划!H7,0)+IF(A6<=融资计划!G8,融资计划!H8,0)+IF(A6<=融资计划!G9,融资计划!H9,0)+IF(A6<=融资计划!G10,融资计划!H10,0) -> 1107.58 | K6: =I6-D6 -> 0 | L6: =J6-G6 -> 0
A7: 5 | B7: 2028 | C7: 11000 | D7: 1093.2 | E7: =C7+D7 -> 12093.2 | F7: 1400 | G7: 1107.58 | H7: =F7+G7 -> 2507.58 | I7: =IF(A7<=融资计划!G2,融资计划!H2,0)+IF(A7<=融资计划!G3,融资计划!H3,0)+IF(A7<=融资计划!G4,融资计划!H4,0)+IF(A7<=融资计划!G5,融资计划!H5,0) -> 1093.2 | J7: =IF(A7<=融资计划!G6,融资计划!H6,0)+IF(A7<=融资计划!G7,融资计划!H7,0)+IF(A7<=融资计划!G8,融资计划!H8,0)+IF(A7<=融资计划!G9,融资计划!H9,0)+IF(A7<=融资计划!G10,融资计划!H10,0) -> 1107.58 | K7: =I7-D7 -> 0 | L7: =J7-G7 -> 0
A8: 6 | B8: 2029 | C8: 0 | D8: 730.2 | E8: =C8+D8 -> 730.2 | F8: 0 | G8: 1075.8 | H8: =F8+G8 -> 1075.8 | I8: =IF(A8<=融资计划!G2,融资计划!H2,0)+IF(A8<=融资计划!G3,融资计划!H3,0)+IF(A8<=融资计划!G4,融资计划!H4,0)+IF(A8<=融资计划!G5,融资计划!H5,0) -> 730.2 | J8: =IF(A8<=融资计划!G6,融资计划!H6,0)+IF(A8<=融资计划!G7,融资计划!H7,0)+IF(A8<=融资计划!G8,融资计划!H8,0)+IF(A8<=融资计划!G9,融资计划!H9,0)+IF(A8<=融资计划!G10,融资计划!H10,0) -> 1075.8 | K8: =I8-D8 -> 0 | L8: =J8-G8 -> 0
A9: 7 | B9: 2030 | C9: 0 | D9: 730.2 | E9: =C9+D9 -> 730.2 | F9: 0 | G9: 1075.8 | H9: =F9+G9 -> 1075.8 | I9: =IF(A9<=融资计划!G2,融资计划!H2,0)+IF(A9<=融资计划!G3,融资计划!H3,0)+IF(A9<=融资计划!G4,融资计划!H4,0)+IF(A9<=融资计划!G5,融资计划!H5,0) -> 730.2 | J9: =IF(A9<=融资计划!G6,融资计划!H6,0)+IF(A9<=融资计划!G7,融资计划!H7,0)+IF(A9<=融资计划!G8,融资计划!H8,0)+IF(A9<=融资计划!G9,融资计划!H9,0)+IF(A9<=融资计划!G10,融资计划!H10,0) -> 1075.8 | K9: =I9-D9 -> 0 | L9: =J9-G9 -> 0
A10: 8 | B10: 2031 | C10: 0 | D10: 730.2 | E10: =C10+D10 -> 730.2 | F10: 0 | G10: 1075.8 | H10: =F10+G10 -> 1075.8 | I10: =IF(A10<=融资计划!G2,融资计划!H2,0)+IF(A10<=融资计划!G3,融资计划!H3,0)+IF(A10<=融资计划!G4,融资计划!H4,0)+IF(A10<=融资计划!G5,融资计划!H5,0) -> 730.2 | J10: =IF(A10<=融资计划!G6,融资计划!H6,0)+IF(A10<=融资计划!G7,融资计划!H7,0)+IF(A10<=融资计划!G8,融资计划!H8,0)+IF(A10<=融资计划!G9,融资计划!H9,0)+IF(A10<=融资计划!G10,融资计划!H10,0) -> 1075.8 | K10: =I10-D10 -> 0 | L10: =J10-G10 -> 0
A11: 9 | B11: 2032 | C11: 2000 | D11: 730.2 | E11: =C11+D11 -> 2730.2 | F11: 2000 | G11: 1075.8 | H11: =F11+G11 -> 3075.8 | I11: =IF(A11<=融资计划!G2,融资计划!H2,0)+IF(A11<=融资计划!G3,融资计划!H3,0)+IF(A11<=融资计划!G4,融资计划!H4,0)+IF(A11<=融资计划!G5,融资计划!H5,0) -> 730.2 | J11: =IF(A11<=融资计划!G6,融资计划!H6,0)+IF(A11<=融资计划!G7,融资计划!H7,0)+IF(A11<=融资计划!G8,融资计划!H8,0)+IF(A11<=融资计划!G9,融资计划!H9,0)+IF(A11<=融资计划!G10,融资计划!H10,0) -> 1075.8 | K11: =I11-D11 -> 0 | L11: =J11-G11 -> 0
A12: 10 | B12: 2033 | C12: 0 | D12: 673.2 | E12: =C12+D12 -> 673.2 | F12: 9600 | G12: 1018.8 | H12: =F12+G12 -> 10618.8 | I12: =IF(A12<=融资计划!G2,融资计划!H2,0)+IF(A12<=融资计划!G3,融资计划!H3,0)+IF(A12<=融资计划!G4,融资计划!H4,0)+IF(A12<=融资计划!G5,融资计划!H5,0) -> 673.2 | J12: =IF(A12<=融资计划!G6,融资计划!H6,0)+IF(A12<=融资计划!G7,融资计划!H7,0)+IF(A12<=融资计划!G8,融资计划!H8,0)+IF(A12<=融资计划!G9,融资计划!H9,0)+IF(A12<=融资计划!G10,融资计划!H10,0) -> 1018.8 | K12: =I12-D12 -> 0 | L12: =J12-G12 -> 0
A13: 11 | B13: 2034 | C13: 0 | D13: 673.2 | E13: =C13+D13 -> 673.2 | F13: 0 | G13: 673.2 | H13: =F13+G13 -> 673.2 | I13: =IF(A13<=融资计划!G2,融资计划!H2,0)+IF(A13<=融资计划!G3,融资计划!H3,0)+IF(A13<=融资计划!G4,融资计划!H4,0)+IF(A13<=融资计划!G5,融资计划!H5,0) -> 673.2 | J13: =IF(A13<=融资计划!G6,融资计划!H6,0)+IF(A13<=融资计划!G7,融资计划!H7,0)+IF(A13<=融资计划!G8,融资计划!H8,0)+IF(A13<=融资计划!G9,融资计划!H9,0)+IF(A13<=融资计划!G10,融资计划!H10,0) -> 673.2 | K13: =I13-D13 -> 0 | L13: =J13-G13 -> 0
A14: 12 | B14: 2035 | C14: 0 | D14: 673.2 | E14: =C14+D14 -> 673.2 | F14: 0 | G14: 673.2 | H14: =F14+G14 -> 673.2 | I14: =IF(A14<=融资计划!G2,融资计划!H2,0)+IF(A14<=融资计划!G3,融资计划!H3,0)+IF(A14<=融资计划!G4,融资计划!H4,0)+IF(A14<=融资计划!G5,融资计划!H5,0) -> 673.2 | J14: =IF(A14<=融资计划!G6,融资计划!H6,0)+IF(A14<=融资计划!G7,融资计划!H7,0)+IF(A14<=融资计划!G8,融资计划!H8,0)+IF(A14<=融资计划!G9,融资计划!H9,0)+IF(A14<=融资计划!G10,融资计划!H10,0) -> 673.2 | K14: =I14-D14 -> 0 | L14: =J14-G14 -> 0
A15: 13 | B15: 2036 | C15: 0 | D15: 673.2 | E15: =C15+D15 -> 673.2 | F15: 0 | G15: 673.2 | H15: =F15+G15 -> 673.2 | I15: =IF(A15<=融资计划!G2,融资计划!H2,0)+IF(A15<=融资计划!G3,融资计划!H3,0)+IF(A15<=融资计划!G4,融资计划!H4,0)+IF(A15<=融资计划!G5,融资计划!H5,0) -> 673.2 | J15: =IF(A15<=融资计划!G6,融资计划!H6,0)+IF(A15<=融资计划!G7,融资计划!H7,0)+IF(A15<=融资计划!G8,融资计划!H8,0)+IF(A15<=融资计划!G9,融资计划!H9,0)+IF(A15<=融资计划!G10,融资计划!H10,0) -> 673.2 | K15: =I15-D15 -> 0 | L15: =J15-G15 -> 0
A16: 14 | B16: 2037 | C16: 1000 | D16: 673.2 | E16: =C16+D16 -> 1673.2 | F16: 1000 | G16: 673.2 | H16: =F16+G16 -> 1673.2 | I16: =IF(A16<=融资计划!G2,融资计划!H2,0)+IF(A16<=融资计划!G3,融资计划!H3,0)+IF(A16<=融资计划!G4,融资计划!H4,0)+IF(A16<=融资计划!G5,融资计划!H5,0) -> 673.2 | J16: =IF(A16<=融资计划!G6,融资计划!H6,0)+IF(A16<=融资计划!G7,融资计划!H7,0)+IF(A16<=融资计划!G8,融资计划!H8,0)+IF(A16<=融资计划!G9,融资计划!H9,0)+IF(A16<=融资计划!G10,融资计划!H10,0) -> 673.2 | K16: =I16-D16 -> 0 | L16: =J16-G16 -> 0
A17: 15 | B17: 2038 | C17: 0 | D17: 644 | E17: =C17+D17 -> 644 | F17: 0 | G17: 644 | H17: =F17+G17 -> 644 | I17: =IF(A17<=融资计划!G2,融资计划!H2,0)+IF(A17<=融资计划!G3,融资计划!H3,0)+IF(A17<=融资计划!G4,融资计划!H4,0)+IF(A17<=融资计划!G5,融资计划!H5,0) -> 644 | J17: =IF(A17<=融资计划!G6,融资计划!H6,0)+IF(A17<=融资计划!G7,融资计划!H7,0)+IF(A17<=融资计划!G8,融资计划!H8,0)+IF(A17<=融资计划!G9,融资计划!H9,0)+IF(A17<=融资计划!G10,融资计划!H10,0) -> 644 | K17: =I17-D17 -> 0 | L17: =J17-G17 -> 0
A18: 16 | B18: 2039 | C18: 0 | D18: 644 | E18: =C18+D18 -> 644 | F18: 0 | G18: 644 | H18: =F18+G18 -> 644 | I18: =IF(A18<=融资计划!G2,融资计划!H2,0)+IF(A18<=融资计划!G3,融资计划!H3,0)+IF(A18<=融资计划!G4,融资计划!H4,0)+IF(A18<=融资计划!G5,融资计划!H5,0) -> 644 | J18: =IF(A18<=融资计划!G6,融资计划!H6,0)+IF(A18<=融资计划!G7,融资计划!H7,0)+IF(A18<=融资计划!G8,融资计划!H8,0)+IF(A18<=融资计划!G9,融资计划!H9,0)+IF(A18<=融资计划!G10,融资计划!H10,0) -> 644 | K18: =I18-D18 -> 0 | L18: =J18-G18 -> 0
A19: 17 | B19: 2040 | C19: 0 | D19: 644 | E19: =C19+D19 -> 644 | F19: 0 | G19: 644 | H19: =F19+G19 -> 644 | I19: =IF(A19<=融资计划!G2,融资计划!H2,0)+IF(A19<=融资计划!G3,融资计划!H3,0)+IF(A19<=融资计划!G4,融资计划!H4,0)+IF(A19<=融资计划!G5,融资计划!H5,0) -> 644 | J19: =IF(A19<=融资计划!G6,融资计划!H6,0)+IF(A19<=融资计划!G7,融资计划!H7,0)+IF(A19<=融资计划!G8,融资计划!H8,0)+IF(A19<=融资计划!G9,融资计划!H9,0)+IF(A19<=融资计划!G10,融资计划!H10,0) -> 644 | K19: =I19-D19 -> 0 | L19: =J19-G19 -> 0
A20: 18 | B20: 2041 | C20: 20000 | D20: 644 | E20: =C20+D20 -> 20644 | F20: 20000 | G20: 644 | H20: =F20+G20 -> 20644 | I20: =IF(A20<=融资计划!G2,融资计划!H2,0)+IF(A20<=融资计划!G3,融资计划!H3,0)+IF(A20<=融资计划!G4,融资计划!H4,0)+IF(A20<=融资计划!G5,融资计划!H5,0) -> 644 | J20: =IF(A20<=融资计划!G6,融资计划!H6,0)+IF(A20<=融资计划!G7,融资计划!H7,0)+IF(A20<=融资计划!G8,融资计划!H8,0)+IF(A20<=融资计划!G9,融资计划!H9,0)+IF(A20<=融资计划!G10,融资计划!H10,0) -> 644 | K20: =I20-D20 -> 0 | L20: =J20-G20 -> 0
A21: 合计 | C21: =SUM(C2:C20) -> 34000 | D21: =SUM(D2:D20) -> 15703 | E21: =SUM(E2:E20) -> 49703 | F21: =SUM(F2:F20) -> 34000 | G21: =SUM(G2:G20) -> 17502.9 | H21: =SUM(H2:H20) -> 51502.9 | I21: =SUM(I2:I20) -> 15703 | J21: =SUM(J2:J20) -> 17502.9 | ... L21: =SUM(L2:L20) -> 0

Sheet 驱动复算
A1: 年序 | B1: 年份 | C1: 运营年 | D1: 门诊 | E1: 住院 | F1: 医疗合计 | G1: 日间原价 | H1: 夜间原价 | I1: 日间使用率 | J1: 夜间使用率 | K1: 原停车复算 | L1: 封顶冻结停车 | M1: 原表充电 | N1: 充电甲 | O1: 充电乙 | P1: 非管理费用 | Q1: 表列总收入 | R1: 停车修正收入 | S1: 停车加充电甲收入 | T1: 停车加充电乙收入 | U1: 原表成本 | V1: 原表净收益 | W1: 原表管理费 | X1: 原停车减表列
A2: 1 | B2: 2024 | C2: 0 | D2: 0 | E2: 0 | F2: 0 | G2: 0 | H2: 0 | I2: 0 | J2: 0 | K2: 0 | L2: 0 | M2: 0 | N2: 0 | O2: 0 | P2: 0 | Q2: 0 | R2: 0 | S2: 0 | T2: 0 | U2: 0 | V2: 0 | W2: 0 | X2: 0
A3: 2 | B3: 2025 | C3: 0 | D3: 0 | E3: 0 | F3: 0 | G3: 0 | H3: 0 | I3: 0 | J3: 0 | K3: 0 | L3: 0 | M3: 0 | N3: 0 | O3: 0 | P3: 0 | Q3: 0 | R3: 0 | S3: 0 | T3: 0 | U3: 0 | V3: 0 | W3: 0 | X3: 0
A4: 3 | B4: 2026 | C4: 0 | D4: 0 | E4: 0 | F4: 0 | G4: 0 | H4: 0 | I4: 0 | J4: 0 | K4: 0 | L4: 0 | M4: 0 | N4: 0 | O4: 0 | P4: 0 | Q4: 0 | R4: 0 | S4: 0 | T4: 0 | U4: 0 | V4: 0 | W4: 0 | X4: 0
A5: 4 | B5: 2027 | C5: 0 | D5: 0 | E5: 0 | F5: 0 | G5: 0 | H5: 0 | I5: 0 | J5: 0 | K5: 0 | L5: 0 | M5: 0 | N5: 0 | O5: 0 | P5: 0 | Q5: 0 | R5: 0 | S5: 0 | T5: 0 | U5: 0 | V5: 0 | W5: 0 | X5: 0
A6: 5 | B6: 2028 | C6: 1 | D6: =参数!$B$2*(1+参数!$B$4)^MIN(C6-1,4)*(1+参数!$B$5)^MIN(MAX(C6-5,0),5)*(1+参数!$B$6)^MAX(C6-10,0) -> 7500 | E6: =参数!$B$3*(1+参数!$B$4)^MIN(C6-1,4)*(1+参数!$B$5)^MIN(MAX(C6-5,0),5)*(1+参数!$B$6)^MAX(C6-10,0) -> 850 | F6: =D6+E6 -> 8350 | G6: =参数!$B$9+INT((C6-1)/5)*参数!$B$20 -> 1.5 | H6: =参数!$B$14+INT((C6-1)/5)*参数!$B$20 -> 1 | I6: =IF(C6<=5,参数!$B$12,参数!$B$13) -> 0.8 | J6: =IF(C6<=5,参数!$B$17,参数!$B$18) -> 0.9 | K6: =参数!$B$7*参数!$B$8*(参数!$B$10*2*G6*参数!$B$11*I6+参数!$B$15*2*H6*参数!$B$16*J6)/10000 -> 670.14 | L6: =参数!$B$7*参数!$B$8*(参数!$B$10*2*参数!$B$9*参数!$B$11*I6+MIN(参数!$B$15*2*参数!$B$14,参数!$B$19)*参数!$B$16*J6)/10000 -> 512.46 | M6: =原表收入!F6 -> 214.44 | N6: =参数!$B$7*参数!$B$21*参数!$B$22*参数!$B$23*参数!$B$24*参数!$B$8/10000*IF(C6<=5,1,IF(C6<=10,1+参数!$B$25,(1+参数!$B$25)*(1+参数!$B$26))) -> 214.4448 | O6: =参数!$B$7*参数!$B$21*参数!$B$22*参数!$B$23*参数!$B$24*参数!$B$8/10000*(1+参数!$B$26)^INT((C6-1)/5) -> 214.4448 | P6: =SUM(参数!$B$27:$B$32)*(1+参数!$B$33)^(C6-1) -> 7355 | Q6: =原表收入!G6 -> 9234.58 | R6: =F6+L6+M6 -> 9076.9 | S6: =F6+L6+N6 -> 9076.9048 | T6: =F6+L6+O6 -> 9076.9048 | U6: =原表费用!J6 -> 7539.69 | V6: =Q6-U6 -> 1694.89 | W6: =原表费用!I6 -> 184.69 | X6: =K6-原表收入!E6 -> 0
A7: 6 | B7: 2029 | C7: 2 | D7: =参数!$B$2*(1+参数!$B$4)^MIN(C7-1,4)*(1+参数!$B$5)^MIN(MAX(C7-5,0),5)*(1+参数!$B$6)^MAX(C7-10,0) -> 8250 | E7: =参数!$B$3*(1+参数!$B$4)^MIN(C7-1,4)*(1+参数!$B$5)^MIN(MAX(C7-5,0),5)*(1+参数!$B$6)^MAX(C7-10,0) -> 935 | F7: =D7+E7 -> 9185 | G7: =参数!$B$9+INT((C7-1)/5)*参数!$B$20 -> 1.5 | H7: =参数!$B$14+INT((C7-1)/5)*参数!$B$20 -> 1 | I7: =IF(C7<=5,参数!$B$12,参数!$B$13) -> 0.8 | J7: =IF(C7<=5,参数!$B$17,参数!$B$18) -> 0.9 | K7: =参数!$B$7*参数!$B$8*(参数!$B$10*2*G7*参数!$B$11*I7+参数!$B$15*2*H7*参数!$B$16*J7)/10000 -> 670.14 | L7: =参数!$B$7*参数!$B$8*(参数!$B$10*2*参数!$B$9*参数!$B$11*I7+MIN(参数!$B$15*2*参数!$B$14,参数!$B$19)*参数!$B$16*J7)/10000 -> 512.46 | M7: =原表收入!F7 -> 268.05 | N7: =参数!$B$7*参数!$B$21*参数!$B$22*参数!$B$23*参数!$B$24*参数!$B$8/10000*IF(C7<=5,1,IF(C7<=10,1+参数!$B$25,(1+参数!$B$25)*(1+参数!$B$26))) -> 214.4448 | O7: =参数!$B$7*参数!$B$21*参数!$B$22*参数!$B$23*参数!$B$24*参数!$B$8/10000*(1+参数!$B$26)^INT((C7-1)/5) -> 214.4448 | P7: =SUM(参数!$B$27:$B$32)*(1+参数!$B$33)^(C7-1) -> 7575.65 | Q7: =原表收入!G7 -> 10123.19 | R7: =F7+L7+M7 -> 9965.51 | S7: =F7+L7+N7 -> 9911.9048 | T7: =F7+L7+O7 -> 9911.9048 | U7: =原表费用!J7 -> 7778.11 | V7: =Q7-U7 -> 2345.08 | W7: =原表费用!I7 -> 202.46 | X7: =K7-原表收入!E7 -> 0
A8: 7 | B8: 2030 | C8: 3 | D8: =参数!$B$2*(1+参数!$B$4)^MIN(C8-1,4)*(1+参数!$B$5)^MIN(MAX(C8-5,0),5)*(1+参数!$B$6)^MAX(C8-10,0) -> 9075 | E8: =参数!$B$3*(1+参数!$B$4)^MIN(C8-1,4)*(1+参数!$B$5)^MIN(MAX(C8-5,0),5)*(1+参数!$B$6)^MAX(C8-10,0) -> 1028.5 | F8: =D8+E8 -> 10103.5 | G8: =参数!$B$9+INT((C8-1)/5)*参数!$B$20 -> 1.5 | H8: =参数!$B$14+INT((C8-1)/5)*参数!$B$20 -> 1 | I8: =IF(C8<=5,参数!$B$12,参数!$B$13) -> 0.8 | J8: =IF(C8<=5,参数!$B$17,参数!$B$18) -> 0.9 | K8: =参数!$B$7*参数!$B$8*(参数!$B$10*2*G8*参数!$B$11*I8+参数!$B$15*2*H8*参数!$B$16*J8)/10000 -> 670.14 | L8: =参数!$B$7*参数!$B$8*(参数!$B$10*2*参数!$B$9*参数!$B$11*I8+MIN(参数!$B$15*2*参数!$B$14,参数!$B$19)*参数!$B$16*J8)/10000 -> 512.46 | M8: =原表收入!F8 -> 268.05 | N8: =参数!$B$7*参数!$B$21*参数!$B$22*参数!$B$23*参数!$B$24*参数!$B$8/10000*IF(C8<=5,1,IF(C8<=10,1+参数!$B$25,(1+参数!$B$25)*(1+参数!$B$26))) -> 214.4448 | O8: =参数!$B$7*参数!$B$21*参数!$B$22*参数!$B$23*参数!$B$24*参数!$B$8/10000*(1+参数!$B$26)^INT((C8-1)/5) -> 214.4448 | P8: =SUM(参数!$B$27:$B$32)*(1+参数!$B$33)^(C8-1) -> 7802.9195 | Q8: =原表收入!G8 -> 11041.69 | R8: =F8+L8+M8 -> 10884.01 | S8: =F8+L8+N8 -> 10830.405 | T8: =F8+L8+O8 -> 10830.405 | U8: =原表费用!J8 -> 8023.74 | V8: =Q8-U8 -> 3017.95 | W8: =原表费用!I8 -> 220.83 | X8: =K8-原表收入!E8 -> 0
A9: 8 | B9: 2031 | C9: 4 | D9: =参数!$B$2*(1+参数!$B$4)^MIN(C9-1,4)*(1+参数!$B$5)^MIN(MAX(C9-5,0),5)*(1+参数!$B$6)^MAX(C9-10,0) -> 9982.5 | E9: =参数!$B$3*(1+参数!$B$4)^MIN(C9-1,4)*(1+参数!$B$5)^MIN(MAX(C9-5,0),5)*(1+参数!$B$6)^MAX(C9-10,0) -> 1131.35 | F9: =D9+E9 -> 11113.85 | G9: =参数!$B$9+INT((C9-1)/5)*参数!$B$20 -> 1.5 | H9: =参数!$B$14+INT((C9-1)/5)*参数!$B$20 -> 1 | I9: =IF(C9<=5,参数!$B$12,参数!$B$13) -> 0.8 | J9: =IF(C9<=5,参数!$B$17,参数!$B$18) -> 0.9 | K9: =参数!$B$7*参数!$B$8*(参数!$B$10*2*G9*参数!$B$11*I9+参数!$B$15*2*H9*参数!$B$16*J9)/10000 -> 670.14 | L9: =参数!$B$7*参数!$B$8*(参数!$B$10*2*参数!$B$9*参数!$B$11*I9+MIN(参数!$B$15*2*参数!$B$14,参数!$B$19)*参数!$B$16*J9)/10000 -> 512.46 | M9: =原表收入!F9 -> 268.05 | N9: =参数!$B$7*参数!$B$21*参数!$B$22*参数!$B$23*参数!$B$24*参数!$B$8/10000*IF(C9<=5,1,IF(C9<=10,1+参数!$B$25,(1+参数!$B$25)*(1+参数!$B$26))) -> 214.4448 | O9: =参数!$B$7*参数!$B$21*参数!$B$22*参数!$B$23*参数!$B$24*参数!$B$8/10000*(1+参数!$B$26)^INT((C9-1)/5) -> 214.4448 | P9: =SUM(参数!$B$27:$B$32)*(1+参数!$B$33)^(C9-1) -> 8037.0071 | Q9: =原表收入!G9 -> 12052.04 | R9: =F9+L9+M9 -> 11894.36 | S9: =F9+L9+N9 -> 11840.755 | T9: =F9+L9+O9 -> 11840.755 | U9: =原表费用!J9 -> 8278.04 | V9: =Q9-U9 -> 3774 | W9: =原表费用!I9 -> 241.04 | X9: =K9-原表收入!E9 -> 0
A10: 9 | B10: 2032 | C10: 5 | D10: =参数!$B$2*(1+参数!$B$4)^MIN(C10-1,4)*(1+参数!$B$5)^MIN(MAX(C10-5,0),5)*(1+参数!$B$6)^MAX(C10-10,0) -> 10980.75 | E10: =参数!$B$3*(1+参数!$B$4)^MIN(C10-1,4)*(1+参数!$B$5)^MIN(MAX(C10-5,0),5)*(1+参数!$B$6)^MAX(C10-10,0) -> 1244.485 | F10: =D10+E10 -> 12225.235 | G10: =参数!$B$9+INT((C10-1)/5)*参数!$B$20 -> 1.5 | H10: =参数!$B$14+INT((C10-1)/5)*参数!$B$20 -> 1 | I10: =IF(C10<=5,参数!$B$12,参数!$B$13) -> 0.8 | J10: =IF(C10<=5,参数!$B$17,参数!$B$18) -> 0.9 | K10: =参数!$B$7*参数!$B$8*(参数!$B$10*2*G10*参数!$B$11*I10+参数!$B$15*2*H10*参数!$B$16*J10)/10000 -> 670.14 | L10: =参数!$B$7*参数!$B$8*(参数!$B$10*2*参数!$B$9*参数!$B$11*I10+MIN(参数!$B$15*2*参数!$B$14,参数!$B$19)*参数!$B$16*J10)/10000 -> 512.46 | M10: =原表收入!F10 -> 268.05 | N10: =参数!$B$7*参数!$B$21*参数!$B$22*参数!$B$23*参数!$B$24*参数!$B$8/10000*IF(C10<=5,1,IF(C10<=10,1+参数!$B$25,(1+参数!$B$25)*(1+参数!$B$26))) -> 214.4448 | O10: =参数!$B$7*参数!$B$21*参数!$B$22*参数!$B$23*参数!$B$24*参数!$B$8/10000*(1+参数!$B$26)^INT((C10-1)/5) -> 214.4448 | P10: =SUM(参数!$B$27:$B$32)*(1+参数!$B$33)^(C10-1) -> 8278.1173 | Q10: =原表收入!G10 -> 13163.43 | R10: =F10+L10+M10 -> 13005.745 | S10: =F10+L10+N10 -> 12952.14 | T10: =F10+L10+O10 -> 12952.14 | U10: =原表费用!J10 -> 8541.38 | V10: =Q10-U10 -> 4622.05 | W10: =原表费用!I10 -> 263.27 | X10: =K10-原表收入!E10 -> 0
A11: 10 | B11: 2033 | C11: 6 | D11: =参数!$B$2*(1+参数!$B$4)^MIN(C11-1,4)*(1+参数!$B$5)^MIN(MAX(C11-5,0),5)*(1+参数!$B$6)^MAX(C11-10,0) -> 11529.788 | E11: =参数!$B$3*(1+参数!$B$4)^MIN(C11-1,4)*(1+参数!$B$5)^MIN(MAX(C11-5,0),5)*(1+参数!$B$6)^MAX(C11-10,0) -> 1306.7093 | F11: =D11+E11 -> 12836.497 | G11: =参数!$B$9+INT((C11-1)/5)*参数!$B$20 -> 2 | H11: =参数!$B$14+INT((C11-1)/5)*参数!$B$20 -> 1.5 | I11: =IF(C11<=5,参数!$B$12,参数!$B$13) -> 0.95 | J11: =IF(C11<=5,参数!$B$17,参数!$B$18) -> 0.95 | K11: =参数!$B$7*参数!$B$8*(参数!$B$10*2*G11*参数!$B$11*I11+参数!$B$15*2*H11*参数!$B$16*J11)/10000 -> 1061.055 | L11: =参数!$B$7*参数!$B$8*(参数!$B$10*2*参数!$B$9*参数!$B$11*I11+MIN(参数!$B$15*2*参数!$B$14,参数!$B$19)*参数!$B$16*J11)/10000 -> 582.54 | M11: =原表收入!F11 -> 294.86 | N11: =参数!$B$7*参数!$B$21*参数!$B$22*参数!$B$23*参数!$B$24*参数!$B$8/10000*IF(C11<=5,1,IF(C11<=10,1+参数!$B$25,(1+参数!$B$25)*(1+参数!$B$26))) -> 268.056 | O11: =参数!$B$7*参数!$B$21*参数!$B$22*参数!$B$23*参数!$B$24*参数!$B$8/10000*(1+参数!$B$26)^INT((C11-1)/5) -> 235.88928 | P11: =SUM(参数!$B$27:$B$32)*(1+参数!$B$33)^(C11-1) -> 8526.4608 | Q11: =原表收入!G11 -> 14139.86 | R11: =F11+L11+M11 -> 13713.897 | S11: =F11+L11+N11 -> 13687.093 | T11: =F11+L11+O11 -> 13654.926 | U11: =原表费用!J11 -> 8809.27 | V11: =Q11-U11 -> 5330.59 | W11: =原表费用!I11 -> 282.8 | X11: =K11-原表收入!E11 -> 52.555
A12: 11 | B12: 2034 | C12: 7 | D12: =参数!$B$2*(1+参数!$B$4)^MIN(C12-1,4)*(1+参数!$B$5)^MIN(MAX(C12-5,0),5)*(1+参数!$B$6)^MAX(C12-10,0) -> 12106.277 | E12: =参数!$B$3*(1+参数!$B$4)^MIN(C12-1,4)*(1+参数!$B$5)^MIN(MAX(C12-5,0),5)*(1+参数!$B$6)^MAX(C12-10,0) -> 1372.0447 | F12: =D12+E12 -> 13478.322 | G12: =参数!$B$9+INT((C12-1)/5)*参数!$B$20 -> 2 | H12: =参数!$B$14+INT((C12-1)/5)*参数!$B$20 -> 1.5 | I12: =IF(C12<=5,参数!$B$12,参数!$B$13) -> 0.95 | J12: =IF(C12<=5,参数!$B$17,参数!$B$18) -> 0.95 | K12: =参数!$B$7*参数!$B$8*(参数!$B$10*2*G12*参数!$B$11*I12+参数!$B$15*2*H12*参数!$B$16*J12)/10000 -> 1061.055 | L12: =参数!$B$7*参数!$B$8*(参数!$B$10*2*参数!$B$9*参数!$B$11*I12+MIN(参数!$B$15*2*参数!$B$14,参数!$B$19)*参数!$B$16*J12)/10000 -> 582.54 | M12: =原表收入!F12 -> 294.86 | N12: =参数!$B$7*参数!$B$21*参数!$B$22*参数!$B$23*参数!$B$24*参数!$B$8/10000*IF(C12<=5,1,IF(C12<=10,1+参数!$B$25,(1+参数!$B$25)*(1+参数!$B$26))) -> 268.056 | O12: =参数!$B$7*参数!$B$21*参数!$B$22*参数!$B$23*参数!$B$24*参数!$B$8/10000*(1+参数!$B$26)^INT((C12-1)/5) -> 235.88928 | P12: =SUM(参数!$B$27:$B$32)*(1+参数!$B$33)^(C12-1) -> 8782.2546 | Q12: =原表收入!G12 -> 14781.69 | R12: =F12+L12+M12 -> 14355.722 | S12: =F12+L12+N12 -> 14328.918 | T12: =F12+L12+O12 -> 14296.751 | U12: =原表费用!J12 -> 9077.89 | V12: =Q12-U12 -> 5703.8 | W12: =原表费用!I12 -> 295.63 | X12: =K12-原表收入!E12 -> 52.555
A13: 12 | B13: 2035 | C13: 8 | D13: =参数!$B$2*(1+参数!$B$4)^MIN(C13-1,4)*(1+参数!$B$5)^MIN(MAX(C13-5,0),5)*(1+参数!$B$6)^MAX(C13-10,0) -> 12711.591 | E13: =参数!$B$3*(1+参数!$B$4)^MIN(C13-1,4)*(1+参数!$B$5)^MIN(MAX(C13-5,0),5)*(1+参数!$B$6)^MAX(C13-10,0) -> 1440.6469 | F13: =D13+E13 -> 14152.238 | G13: =参数!$B$9+INT((C13-1)/5)*参数!$B$20 -> 2 | H13: =参数!$B$14+INT((C13-1)/5)*参数!$B$20 -> 1.5 | I13: =IF(C13<=5,参数!$B$12,参数!$B$13) -> 0.95 | J13: =IF(C13<=5,参数!$B$17,参数!$B$18) -> 0.95 | K13: =参数!$B$7*参数!$B$8*(参数!$B$10*2*G13*参数!$B$11*I13+参数!$B$15*2*H13*参数!$B$16*J13)/10000 -> 1061.055 | L13: =参数!$B$7*参数!$B$8*(参数!$B$10*2*参数!$B$9*参数!$B$11*I13+MIN(参数!$B$15*2*参数!$B$14,参数!$B$19)*参数!$B$16*J13)/10000 -> 582.54 | M13: =原表收入!F13 -> 294.86 | N13: =参数!$B$7*参数!$B$21*参数!$B$22*参数!$B$23*参数!$B$24*参数!$B$8/10000*IF(C13<=5,1,IF(C13<=10,1+参数!$B$25,(1+参数!$B$25)*(1+参数!$B$26))) -> 268.056 | O13: =参数!$B$7*参数!$B$21*参数!$B$22*参数!$B$23*参数!$B$24*参数!$B$8/10000*(1+参数!$B$26)^INT((C13-1)/5) -> 235.88928 | P13: =SUM(参数!$B$27:$B$32)*(1+参数!$B$33)^(C13-1) -> 9045.7223 | Q13: =原表收入!G13 -> 15455.6 | R13: =F13+L13+M13 -> 15029.638 | S13: =F13+L13+N13 -> 15002.834 | T13: =F13+L13+O13 -> 14970.667 | U13: =原表费用!J13 -> 9354.85 | V13: =Q13-U13 -> 6100.75 | W13: =原表费用!I13 -> 309.11 | X13: =K13-原表收入!E13 -> 52.555
A14: 13 | B14: 2036 | C14: 9 | D14: =参数!$B$2*(1+参数!$B$4)^MIN(C14-1,4)*(1+参数!$B$5)^MIN(MAX(C14-5,0),5)*(1+参数!$B$6)^MAX(C14-10,0) -> 13347.17 | E14: =参数!$B$3*(1+参数!$B$4)^MIN(C14-1,4)*(1+参数!$B$5)^MIN(MAX(C14-5,0),5)*(1+参数!$B$6)^MAX(C14-10,0) -> 1512.6793 | F14: =D14+E14 -> 14859.85 | G14: =参数!$B$9+INT((C14-1)/5)*参数!$B$20 -> 2 | H14: =参数!$B$14+INT((C14-1)/5)*参数!$B$20 -> 1.5 | I14: =IF(C14<=5,参数!$B$12,参数!$B$13) -> 0.95 | J14: =IF(C14<=5,参数!$B$17,参数!$B$18) -> 0.95 | K14: =参数!$B$7*参数!$B$8*(参数!$B$10*2*G14*参数!$B$11*I14+参数!$B$15*2*H14*参数!$B$16*J14)/10000 -> 1061.055 | L14: =参数!$B$7*参数!$B$8*(参数!$B$10*2*参数!$B$9*参数!$B$11*I14+MIN(参数!$B$15*2*参数!$B$14,参数!$B$19)*参数!$B$16*J14)/10000 -> 582.54 | M14: =原表收入!F14 -> 294.86 | N14: =参数!$B$7*参数!$B$21*参数!$B$22*参数!$B$23*参数!$B$24*参数!$B$8/10000*IF(C14<=5,1,IF(C14<=10,1+参数!$B$25,(1+参数!$B$25)*(1+参数!$B$26))) -> 268.056 | O14: =参数!$B$7*参数!$B$21*参数!$B$22*参数!$B$23*参数!$B$24*参数!$B$8/10000*(1+参数!$B$26)^INT((C14-1)/5) -> 235.88928 | P14: =SUM(参数!$B$27:$B$32)*(1+参数!$B$33)^(C14-1) -> 9317.0939 | Q14: =原表收入!G14 -> 16163.21 | R14: =F14+L14+M14 -> 15737.25 | S14: =F14+L14+N14 -> 15710.446 | T14: =F14+L14+O14 -> 15678.279 | U14: =原表费用!J14 -> 9640.37 | V14: =Q14-U14 -> 6522.84 | W14: =原表费用!I14 -> 323.26 | X14: =K14-原表收入!E14 -> 52.555
A15: 14 | B15: 2037 | C15: 10 | D15: =参数!$B$2*(1+参数!$B$4)^MIN(C15-1,4)*(1+参数!$B$5)^MIN(MAX(C15-5,0),5)*(1+参数!$B$6)^MAX(C15-10,0) -> 14014.529 | E15: =参数!$B$3*(1+参数!$B$4)^MIN(C15-1,4)*(1+参数!$B$5)^MIN(MAX(C15-5,0),5)*(1+参数!$B$6)^MAX(C15-10,0) -> 1588.3133 | F15: =D15+E15 -> 15602.842 | G15: =参数!$B$9+INT((C15-1)/5)*参数!$B$20 -> 2 | H15: =参数!$B$14+INT((C15-1)/5)*参数!$B$20 -> 1.5 | I15: =IF(C15<=5,参数!$B$12,参数!$B$13) -> 0.95 | J15: =IF(C15<=5,参数!$B$17,参数!$B$18) -> 0.95 | K15: =参数!$B$7*参数!$B$8*(参数!$B$10*2*G15*参数!$B$11*I15+参数!$B$15*2*H15*参数!$B$16*J15)/10000 -> 1061.055 | L15: =参数!$B$7*参数!$B$8*(参数!$B$10*2*参数!$B$9*参数!$B$11*I15+MIN(参数!$B$15*2*参数!$B$14,参数!$B$19)*参数!$B$16*J15)/10000 -> 582.54 | M15: =原表收入!F15 -> 294.86 | N15: =参数!$B$7*参数!$B$21*参数!$B$22*参数!$B$23*参数!$B$24*参数!$B$8/10000*IF(C15<=5,1,IF(C15<=10,1+参数!$B$25,(1+参数!$B$25)*(1+参数!$B$26))) -> 268.056 | O15: =参数!$B$7*参数!$B$21*参数!$B$22*参数!$B$23*参数!$B$24*参数!$B$8/10000*(1+参数!$B$26)^INT((C15-1)/5) -> 235.88928 | P15: =SUM(参数!$B$27:$B$32)*(1+参数!$B$33)^(C15-1) -> 9596.6068 | Q15: =原表收入!G15 -> 16906.2 | R15: =F15+L15+M15 -> 16480.242 | S15: =F15+L15+N15 -> 16453.438 | T15: =F15+L15+O15 -> 16421.271 | U15: =原表费用!J15 -> 9925.83 | V15: =Q15-U15 -> 6980.37 | W15: =原表费用!I15 -> 329.21 | X15: =K15-原表收入!E15 -> 52.555
A16: 15 | B16: 2038 | C16: 11 | D16: =参数!$B$2*(1+参数!$B$4)^MIN(C16-1,4)*(1+参数!$B$5)^MIN(MAX(C16-5,0),5)*(1+参数!$B$6)^MAX(C16-10,0) -> 14294.819 | E16: =参数!$B$3*(1+参数!$B$4)^MIN(C16-1,4)*(1+参数!$B$5)^MIN(MAX(C16-5,0),5)*(1+参数!$B$6)^MAX(C16-10,0) -> 1620.0795 | F16: =D16+E16 -> 15914.899 | G16: =参数!$B$9+INT((C16-1)/5)*参数!$B$20 -> 2.5 | H16: =参数!$B$14+INT((C16-1)/5)*参数!$B$20 -> 2 | I16: =IF(C16<=5,参数!$B$12,参数!$B$13) -> 0.95 | J16: =IF(C16<=5,参数!$B$17,参数!$B$18) -> 0.95 | K16: =参数!$B$7*参数!$B$8*(参数!$B$10*2*G16*参数!$B$11*I16+参数!$B$15*2*H16*参数!$B$16*J16)/10000 -> 1373.13 | L16: =参数!$B$7*参数!$B$8*(参数!$B$10*2*参数!$B$9*参数!$B$11*I16+MIN(参数!$B$15*2*参数!$B$14,参数!$B$19)*参数!$B$16*J16)/10000 -> 582.54 | M16: =原表收入!F16 -> 324.35 | N16: =参数!$B$7*参数!$B$21*参数!$B$22*参数!$B$23*参数!$B$24*参数!$B$8/10000*IF(C16<=5,1,IF(C16<=10,1+参数!$B$25,(1+参数!$B$25)*(1+参数!$B$26))) -> 294.8616 | O16: =参数!$B$7*参数!$B$21*参数!$B$22*参数!$B$23*参数!$B$24*参数!$B$8/10000*(1+参数!$B$26)^INT((C16-1)/5) -> 259.47821 | P16: =SUM(参数!$B$27:$B$32)*(1+参数!$B$33)^(C16-1) -> 9884.505 | Q16: =原表收入!G16 -> 17546.68 | R16: =F16+L16+M16 -> 16821.789 | S16: =F16+L16+N16 -> 16792.3 | T16: =F16+L16+O16 -> 16756.917 | U16: =原表费用!J16 -> 10226.35 | V16: =Q16-U16 -> 7320.33 | W16: =原表费用!I16 -> 341.84 | X16: =K16-原表收入!E16 -> 65.7
A17: 16 | B17: 2039 | C17: 12 | D17: =参数!$B$2*(1+参数!$B$4)^MIN(C17-1,4)*(1+参数!$B$5)^MIN(MAX(C17-5,0),5)*(1+参数!$B$6)^MAX(C17-10,0) -> 14580.716 | E17: =参数!$B$3*(1+参数!$B$4)^MIN(C17-1,4)*(1+参数!$B$5)^MIN(MAX(C17-5,0),5)*(1+参数!$B$6)^MAX(C17-10,0) -> 1652.4811 | F17: =D17+E17 -> 16233.197 | G17: =参数!$B$9+INT((C17-1)/5)*参数!$B$20 -> 2.5 | H17: =参数!$B$14+INT((C17-1)/5)*参数!$B$20 -> 2 | I17: =IF(C17<=5,参数!$B$12,参数!$B$13) -> 0.95 | J17: =IF(C17<=5,参数!$B$17,参数!$B$18) -> 0.95 | K17: =参数!$B$7*参数!$B$8*(参数!$B$10*2*G17*参数!$B$11*I17+参数!$B$15*2*H17*参数!$B$16*J17)/10000 -> 1373.13 | L17: =参数!$B$7*参数!$B$8*(参数!$B$10*2*参数!$B$9*参数!$B$11*I17+MIN(参数!$B$15*2*参数!$B$14,参数!$B$19)*参数!$B$16*J17)/10000 -> 582.54 | M17: =原表收入!F17 -> 324.35 | N17: =参数!$B$7*参数!$B$21*参数!$B$22*参数!$B$23*参数!$B$24*参数!$B$8/10000*IF(C17<=5,1,IF(C17<=10,1+参数!$B$25,(1+参数!$B$25)*(1+参数!$B$26))) -> 294.8616 | O17: =参数!$B$7*参数!$B$21*参数!$B$22*参数!$B$23*参数!$B$24*参数!$B$8/10000*(1+参数!$B$26)^INT((C17-1)/5) -> 259.47821 | P17: =SUM(参数!$B$27:$B$32)*(1+参数!$B$33)^(C17-1) -> 10181.04 | Q17: =原表收入!G17 -> 17864.98 | R17: =F17+L17+M17 -> 17140.087 | S17: =F17+L17+N17 -> 17110.598 | T17: =F17+L17+O17 -> 17075.215 | U17: =原表费用!J17 -> 10529.06 | V17: =Q17-U17 -> 7335.92 | W17: =原表费用!I17 -> 348.02 | X17: =K17-原表收入!E17 -> 65.7
... A19: 18 | B19: 2041 | C19: 14 | D19: =参数!$B$2*(1+参数!$B$4)^MIN(C19-1,4)*(1+参数!$B$5)^MIN(MAX(C19-5,0),5)*(1+参数!$B$6)^MAX(C19-10,0) -> 15169.777 | E19: =参数!$B$3*(1+参数!$B$4)^MIN(C19-1,4)*(1+参数!$B$5)^MIN(MAX(C19-5,0),5)*(1+参数!$B$6)^MAX(C19-10,0) -> 1719.2414 | F19: =D19+E19 -> 16889.018 | G19: =参数!$B$9+INT((C19-1)/5)*参数!$B$20 -> 2.5 | H19: =参数!$B$14+INT((C19-1)/5)*参数!$B$20 -> 2 | I19: =IF(C19<=5,参数!$B$12,参数!$B$13) -> 0.95 | J19: =IF(C19<=5,参数!$B$17,参数!$B$18) -> 0.95 | K19: =参数!$B$7*参数!$B$8*(参数!$B$10*2*G19*参数!$B$11*I19+参数!$B$15*2*H19*参数!$B$16*J19)/10000 -> 1373.13 | L19: =参数!$B$7*参数!$B$8*(参数!$B$10*2*参数!$B$9*参数!$B$11*I19+MIN(参数!$B$15*2*参数!$B$14,参数!$B$19)*参数!$B$16*J19)/10000 -> 582.54 | M19: =原表收入!F19 -> 324.35 | N19: =参数!$B$7*参数!$B$21*参数!$B$22*参数!$B$23*参数!$B$24*参数!$B$8/10000*IF(C19<=5,1,IF(C19<=10,1+参数!$B$25,(1+参数!$B$25)*(1+参数!$B$26))) -> 294.8616 | O19: =参数!$B$7*参数!$B$21*参数!$B$22*参数!$B$23*参数!$B$24*参数!$B$8/10000*(1+参数!$B$26)^INT((C19-1)/5) -> 259.47821 | P19: =SUM(参数!$B$27:$B$32)*(1+参数!$B$33)^(C19-1) -> 10801.065 | Q19: =原表收入!G19 -> 18520.8 | R19: =F19+L19+M19 -> 17795.908 | S19: =F19+L19+N19 -> 17766.42 | T19: =F19+L19+O19 -> 17731.036 | U19: =原表费用!J19 -> 11161.84 | V19: =Q19-U19 -> 7358.96 | W19: =原表费用!I19 -> 360.77 | X19: =K19-原表收入!E19 -> 65.7
A20: 合计 | D20: =SUM(D2:D19) -> 168415.25 | E20: =SUM(E2:E19) -> 19087.061 | F20: =SUM(F2:F19) -> 187502.31 | K20: =SUM(K2:K19) -> 14148.495 | L20: =SUM(L2:L19) -> 7805.16 | M20: =SUM(M2:M19) -> 4058.34 | N20: =SUM(N2:N19) -> 3591.9504 | O20: =SUM(O2:O19) -> 3289.5832 | P20: =SUM(P2:P19) -> 125669.91 | Q20: =SUM(Q2:Q19) -> 205183.59 | R20: =SUM(R2:R19) -> 199365.81 | ... X20: =SUM(X2:X19) -> 525.575

Sheet 情景参数
A1: 情景 | B1: 驱动收入列号 | C1: 管理费率 | D1: 收入降幅 | E1: 成本处理 | F1: 净收益降幅
A2: 原表 | B2: 17 | C2: 0 | D2: 0 | E2: 原表 | F2: 0
A3: 统一2% | B3: 17 | C3: 0.02 | D3: 0 | E3: 联动 | F3: 0
A4: 统一5% | B4: 17 | C4: 0.05 | D4: 0 | E4: 联动 | F4: 0
A5: 收费修正2% | B5: 18 | C5: 0.02 | D5: 0 | E5: 联动 | F5: 0
A6: 收费修正5% | B6: 18 | C6: 0.05 | D6: 0 | E6: 联动 | F6: 0
A7: 文字周期甲2% | B7: 19 | C7: 0.02 | D7: 0 | E7: 联动 | F7: 0
A8: 文字周期甲5% | B8: 19 | C8: 0.05 | D8: 0 | E8: 联动 | F8: 0
A9: 文字周期乙5% | B9: 20 | C9: 0.05 | D9: 0 | E9: 联动 | F9: 0
A10: 原表净收益降5% | B10: 17 | C10: 0 | D10: 0 | E10: 原表 | F10: 0.05
A11: 原表收入降5%成本固定 | B11: 17 | C11: 0 | D11: 0.05 | E11: 原表 | F11: 0
A12: 统一2%收入降5% | B12: 17 | C12: 0.02 | D12: 0.05 | E12: 联动 | F12: 0
A13: 统一5%收入降5% | B13: 17 | C13: 0.05 | D13: 0.05 | E13: 联动 | F13: 0
... A20: 文字周期乙5%收入降5% | B20: 20 | C20: 0.05 | D20: 0.05 | E20: 联动 | F20: 0

Sheet 情景年表
A1: 情景 | B1: 融资版本 | C1: 年序 | D1: 年份 | E1: 基准收入 | F1: 压力后收入 | G1: 非管理费 | H1: 管理费 | I1: 成本 | J1: 净收益 | K1: 本金 | L1: 利息 | M1: 本息 | N1: 单年差额 | O1: 未补资累计 | P1: 本年所需新增补资 | Q1: 已补资累计 | R1: 补资后余额
A2: 原表 | B2: 早版 | C2: 0 | D2: 已融资 | E2: =0 -> 0 | F2: =E2*(1-情景参数!D2) -> 0 | G2: =0 -> 0 | H2: =0 -> 0 | I2: =0 -> 0 | J2: =(F2-I2)*(1-情景参数!F2) -> 0 | K2: =偿债原表!C2 -> 0 | L2: =偿债原表!D2 -> 1374.2 | M2: =K2+L2 -> 1374.2 | N2: =J2-M2 -> -1374.2 | O2: =N2 -> -1374.2 | P2: =MAX(0,-N2) -> 1374.2 | Q2: =P2 -> 1374.2 | R2: =O2+Q2 -> 0
A3: 原表 | B3: 早版 | C3: 1 | D3: 2024 | E3: =INDEX(驱动复算!A2:X2,1,情景参数!B2) -> 0 | F3: =E3*(1-情景参数!D2) -> 0 | G3: =IF(情景参数!E2="原表",驱动复算!U2-驱动复算!W2,驱动复算!P2) -> 0 | H3: =IF(情景参数!E2="原表",驱动复算!W2,F3*情景参数!C2) -> 0 | I3: =IF(情景参数!E2="原表",驱动复算!U2,G3+H3) -> 0 | J3: =(F3-I3)*(1-情景参数!F2) -> 0 | K3: =偿债原表!C3 -> 0 | L3: =偿债原表!D3 -> 1093.2 | M3: =K3+L3 -> 1093.2 | N3: =J3-M3 -> -1093.2 | O3: =O2+N3 -> -2467.4 | P3: =MAX(0,-(R2+N3)) -> 1093.2 | Q3: =Q2+P3 -> 2467.4 | R3: =O3+Q3 -> 0
A4: 原表 | B4: 早版 | C4: 2 | D4: 2025 | E4: =INDEX(驱动复算!A3:X3,1,情景参数!B2) -> 0 | F4: =E4*(1-情景参数!D2) -> 0 | G4: =IF(情景参数!E2="原表",驱动复算!U3-驱动复算!W3,驱动复算!P3) -> 0 | H4: =IF(情景参数!E2="原表",驱动复算!W3,F4*情景参数!C2) -> 0 | I4: =IF(情景参数!E2="原表",驱动复算!U3,G4+H4) -> 0 | J4: =(F4-I4)*(1-情景参数!F2) -> 0 | K4: =偿债原表!C4 -> 0 | L4: =偿债原表!D4 -> 1093.2 | M4: =K4+L4 -> 1093.2 | N4: =J4-M4 -> -1093.2 | O4: =O3+N4 -> -3560.6 | P4: =MAX(0,-(R3+N4)) -> 1093.2 | Q4: =Q3+P4 -> 3560.6 | R4: =O4+Q4 -> 0
A5: 原表 | B5: 早版 | C5: 3 | D5: 2026 | E5: =INDEX(驱动复算!A4:X4,1,情景参数!B2) -> 0 | F5: =E5*(1-情景参数!D2) -> 0 | G5: =IF(情景参数!E2="原表",驱动复算!U4-驱动复算!W4,驱动复算!P4) -> 0 | H5: =IF(情景参数!E2="原表",驱动复算!W4,F5*情景参数!C2) -> 0 | I5: =IF(情景参数!E2="原表",驱动复算!U4,G5+H5) -> 0 | J5: =(F5-I5)*(1-情景参数!F2) -> 0 | K5: =偿债原表!C5 -> 0 | L5: =偿债原表!D5 -> 1093.2 | M5: =K5+L5 -> 1093.2 | N5: =J5-M5 -> -1093.2 | O5: =O4+N5 -> -4653.8 | P5: =MAX(0,-(R4+N5)) -> 1093.2 | Q5: =Q4+P5 -> 4653.8 | R5: =O5+Q5 -> 0
A6: 原表 | B6: 早版 | C6: 4 | D6: 2027 | E6: =INDEX(驱动复算!A5:X5,1,情景参数!B2) -> 0 | F6: =E6*(1-情景参数!D2) -> 0 | G6: =IF(情景参数!E2="原表",驱动复算!U5-驱动复算!W5,驱动复算!P5) -> 0 | H6: =IF(情景参数!E2="原表",驱动复算!W5,F6*情景参数!C2) -> 0 | I6: =IF(情景参数!E2="原表",驱动复算!U5,G6+H6) -> 0 | J6: =(F6-I6)*(1-情景参数!F2) -> 0 | K6: =偿债原表!C6 -> 0 | L6: =偿债原表!D6 -> 1093.2 | M6: =K6+L6 -> 1093.2 | N6: =J6-M6 -> -1093.2 | O6: =O5+N6 -> -5747 | P6: =MAX(0,-(R5+N6)) -> 1093.2 | Q6: =Q5+P6 -> 5747 | R6: =O6+Q6 -> 0
A7: 原表 | B7: 早版 | C7: 5 | D7: 2028 | E7: =INDEX(驱动复算!A6:X6,1,情景参数!B2) -> 9234.58 | F7: =E7*(1-情景参数!D2) -> 9234.58 | G7: =IF(情景参数!E2="原表",驱动复算!U6-驱动复算!W6,驱动复算!P6) -> 7355 | H7: =IF(情景参数!E2="原表",驱动复算!W6,F7*情景参数!C2) -> 184.69 | I7: =IF(情景参数!E2="原表",驱动复算!U6,G7+H7) -> 7539.69 | J7: =(F7-I7)*(1-情景参数!F2) -> 1694.89 | K7: =偿债原表!C7 -> 11000 | L7: =偿债原表!D7 -> 1093.2 | M7: =K7+L7 -> 12093.2 | N7: =J7-M7 -> -10398.31 | O7: =O6+N7 -> -16145.31 | P7: =MAX(0,-(R6+N7)) -> 10398.31 | Q7: =Q6+P7 -> 16145.31 | R7: =O7+Q7 -> 0
A8: 原表 | B8: 早版 | C8: 6 | D8: 2029 | E8: =INDEX(驱动复算!A7:X7,1,情景参数!B2) -> 10123.19 | F8: =E8*(1-情景参数!D2) -> 10123.19 | G8: =IF(情景参数!E2="原表",驱动复算!U7-驱动复算!W7,驱动复算!P7) -> 7575.65 | H8: =IF(情景参数!E2="原表",驱动复算!W7,F8*情景参数!C2) -> 202.46 | I8: =IF(情景参数!E2="原表",驱动复算!U7,G8+H8) -> 7778.11 | J8: =(F8-I8)*(1-情景参数!F2) -> 2345.08 | K8: =偿债原表!C8 -> 0 | L8: =偿债原表!D8 -> 730.2 | M8: =K8+L8 -> 730.2 | N8: =J8-M8 -> 1614.88 | O8: =O7+N8 -> -14530.43 | P8: =MAX(0,-(R7+N8)) -> 0 | Q8: =Q7+P8 -> 16145.31 | R8: =O8+Q8 -> 1614.88
A9: 原表 | B9: 早版 | C9: 7 | D9: 2030 | E9: =INDEX(驱动复算!A8:X8,1,情景参数!B2) -> 11041.69 | F9: =E9*(1-情景参数!D2) -> 11041.69 | G9: =IF(情景参数!E2="原表",驱动复算!U8-驱动复算!W8,驱动复算!P8) -> 7802.91 | H9: =IF(情景参数!E2="原表",驱动复算!W8,F9*情景参数!C2) -> 220.83 | I9: =IF(情景参数!E2="原表",驱动复算!U8,G9+H9) -> 8023.74 | J9: =(F9-I9)*(1-情景参数!F2) -> 3017.95 | K9: =偿债原表!C9 -> 0 | L9: =偿债原表!D9 -> 730.2 | M9: =K9+L9 -> 730.2 | N9: =J9-M9 -> 2287.75 | O9: =O8+N9 -> -12242.68 | P9: =MAX(0,-(R8+N9)) -> 0 | Q9: =Q8+P9 -> 16145.31 | R9: =O9+Q9 -> 3902.63
A10: 原表 | B10: 早版 | C10: 8 | D10: 2031 | E10: =INDEX(驱动复算!A9:X9,1,情景参数!B2) -> 12052.04 | F10: =E10*(1-情景参数!D2) -> 12052.04 | G10: =IF(情景参数!E2="原表",驱动复算!U9-驱动复算!W9,驱动复算!P9) -> 8037 | H10: =IF(情景参数!E2="原表",驱动复算!W9,F10*情景参数!C2) -> 241.04 | I10: =IF(情景参数!E2="原表",驱动复算!U9,G10+H10) -> 8278.04 | J10: =(F10-I10)*(1-情景参数!F2) -> 3774 | K10: =偿债原表!C10 -> 0 | L10: =偿债原表!D10 -> 730.2 | M10: =K10+L10 -> 730.2 | N10: =J10-M10 -> 3043.8 | O10: =O9+N10 -> -9198.88 | P10: =MAX(0,-(R9+N10)) -> 0 | Q10: =Q9+P10 -> 16145.31 | R10: =O10+Q10 -> 6946.43
A11: 原表 | B11: 早版 | C11: 9 | D11: 2032 | E11: =INDEX(驱动复算!A10:X10,1,情景参数!B2) -> 13163.43 | F11: =E11*(1-情景参数!D2) -> 13163.43 | G11: =IF(情景参数!E2="原表",驱动复算!U10-驱动复算!W10,驱动复算!P10) -> 8278.11 | H11: =IF(情景参数!E2="原表",驱动复算!W10,F11*情景参数!C2) -> 263.27 | I11: =IF(情景参数!E2="原表",驱动复算!U10,G11+H11) -> 8541.38 | J11: =(F11-I11)*(1-情景参数!F2) -> 4622.05 | K11: =偿债原表!C11 -> 2000 | L11: =偿债原表!D11 -> 730.2 | M11: =K11+L11 -> 2730.2 | N11: =J11-M11 -> 1891.85 | O11: =O10+N11 -> -7307.03 | P11: =MAX(0,-(R10+N11)) -> 0 | Q11: =Q10+P11 -> 16145.31 | R11: =O11+Q11 -> 8838.28
A12: 原表 | B12: 早版 | C12: 10 | D12: 2033 | E12: =INDEX(驱动复算!A11:X11,1,情景参数!B2) -> 14139.86 | F12: =E12*(1-情景参数!D2) -> 14139.86 | G12: =IF(情景参数!E2="原表",驱动复算!U11-驱动复算!W11,驱动复算!P11) -> 8526.47 | H12: =IF(情景参数!E2="原表",驱动复算!W11,F12*情景参数!C2) -> 282.8 | I12: =IF(情景参数!E2="原表",驱动复算!U11,G12+H12) -> 8809.27 | J12: =(F12-I12)*(1-情景参数!F2) -> 5330.59 | K12: =偿债原表!C12 -> 0 | L12: =偿债原表!D12 -> 673.2 | M12: =K12+L12 -> 673.2 | N12: =J12-M12 -> 4657.39 | O12: =O11+N12 -> -2649.64 | P12: =MAX(0,-(R11+N12)) -> 0 | Q12: =Q11+P12 -> 16145.31 | R12: =O12+Q12 -> 13495.67
A13: 原表 | B13: 早版 | C13: 11 | D13: 2034 | E13: =INDEX(驱动复算!A12:X12,1,情景参数!B2) -> 14781.69 | F13: =E13*(1-情景参数!D2) -> 14781.69 | G13: =IF(情景参数!E2="原表",驱动复算!U12-驱动复算!W12,驱动复算!P12) -> 8782.26 | H13: =IF(情景参数!E2="原表",驱动复算!W12,F13*情景参数!C2) -> 295.63 | I13: =IF(情景参数!E2="原表",驱动复算!U12,G13+H13) -> 9077.89 | J13: =(F13-I13)*(1-情景参数!F2) -> 5703.8 | K13: =偿债原表!C13 -> 0 | L13: =偿债原表!D13 -> 673.2 | M13: =K13+L13 -> 673.2 | N13: =J13-M13 -> 5030.6 | O13: =O12+N13 -> 2380.96 | P13: =MAX(0,-(R12+N13)) -> 0 | Q13: =Q12+P13 -> 16145.31 | R13: =O13+Q13 -> 18526.27
A14: 原表 | B14: 早版 | C14: 12 | D14: 2035 | E14: =INDEX(驱动复算!A13:X13,1,情景参数!B2) -> 15455.6 | F14: =E14*(1-情景参数!D2) -> 15455.6 | G14: =IF(情景参数!E2="原表",驱动复算!U13-驱动复算!W13,驱动复算!P13) -> 9045.74 | H14: =IF(情景参数!E2="原表",驱动复算!W13,F14*情景参数!C2) -> 309.11 | I14: =IF(情景参数!E2="原表",驱动复算!U13,G14+H14) -> 9354.85 | J14: =(F14-I14)*(1-情景参数!F2) -> 6100.75 | K14: =偿债原表!C14 -> 0 | L14: =偿债原表!D14 -> 673.2 | M14: =K14+L14 -> 673.2 | N14: =J14-M14 -> 5427.55 | O14: =O13+N14 -> 7808.51 | P14: =MAX(0,-(R13+N14)) -> 0 | Q14: =Q13+P14 -> 16145.31 | R14: =O14+Q14 -> 23953.82
A15: 原表 | B15: 早版 | C15: 13 | D15: 2036 | E15: =INDEX(驱动复算!A14:X14,1,情景参数!B2) -> 16163.21 | F15: =E15*(1-情景参数!D2) -> 16163.21 | G15: =IF(情景参数!E2="原表",驱动复算!U14-驱动复算!W14,驱动复算!P14) -> 9317.11 | H15: =IF(情景参数!E2="原表",驱动复算!W14,F15*情景参数!C2) -> 323.26 | I15: =IF(情景参数!E2="原表",驱动复算!U14,G15+H15) -> 9640.37 | J15: =(F15-I15)*(1-情景参数!F2) -> 6522.84 | K15: =偿债原表!C15 -> 0 | L15: =偿债原表!D15 -> 673.2 | M15: =K15+L15 -> 673.2 | N15: =J15-M15 -> 5849.64 | O15: =O14+N15 -> 13658.15 | P15: =MAX(0,-(R14+N15)) -> 0 | Q15: =Q14+P15 -> 16145.31 | R15: =O15+Q15 -> 29803.46
A16: 原表 | B16: 早版 | C16: 14 | D16: 2037 | E16: =INDEX(驱动复算!A15:X15,1,情景参数!B2) -> 16906.2 | F16: =E16*(1-情景参数!D2) -> 16906.2 | G16: =IF(情景参数!E2="原表",驱动复算!U15-驱动复算!W15,驱动复算!P15) -> 9596.62 | H16: =IF(情景参数!E2="原表",驱动复算!W15,F16*情景参数!C2) -> 329.21 | I16: =IF(情景参数!E2="原表",驱动复算!U15,G16+H16) -> 9925.83 | J16: =(F16-I16)*(1-情景参数!F2) -> 6980.37 | K16: =偿债原表!C16 -> 1000 | L16: =偿债原表!D16 -> 673.2 | M16: =K16+L16 -> 1673.2 | N16: =J16-M16 -> 5307.17 | O16: =O15+N16 -> 18965.32 | P16: =MAX(0,-(R15+N16)) -> 0 | Q16: =Q15+P16 -> 16145.31 | R16: =O16+Q16 -> 35110.63
A17: 原表 | B17: 早版 | C17: 15 | D17: 2038 | E17: =INDEX(驱动复算!A16:X16,1,情景参数!B2) -> 17546.68 | F17: =E17*(1-情景参数!D2) -> 17546.68 | G17: =IF(情景参数!E2="原表",驱动复算!U16-驱动复算!W16,驱动复算!P16) -> 9884.51 | H17: =IF(情景参数!E2="原表",驱动复算!W16,F17*情景参数!C2) -> 341.84 | I17: =IF(情景参数!E2="原表",驱动复算!U16,G17+H17) -> 10226.35 | J17: =(F17-I17)*(1-情景参数!F2) -> 7320.33 | K17: =偿债原表!C17 -> 0 | L17: =偿债原表!D17 -> 644 | M17: =K17+L17 -> 644 | N17: =J17-M17 -> 6676.33 | O17: =O16+N17 -> 25641.65 | P17: =MAX(0,-(R16+N17)) -> 0 | Q17: =Q16+P17 -> 16145.31 | R17: =O17+Q17 -> 41786.96
A18: 原表 | B18: 早版 | C18: 16 | D18: 2039 | E18: =INDEX(驱动复算!A17:X17,1,情景参数!B2) -> 17864.98 | F18: =E18*(1-情景参数!D2) -> 17864.98 | G18: =IF(情景参数!E2="原表",驱动复算!U17-驱动复算!W17,驱动复算!P17) -> 10181.04 | H18: =IF(情景参数!E2="原表",驱动复算!W17,F18*情景参数!C2) -> 348.02 | I18: =IF(情景参数!E2="原表",驱动复算!U17,G18+H18) -> 10529.06 | J18: =(F18-I18)*(1-情景参数!F2) -> 7335.92 | K18: =偿债原表!C18 -> 0 | L18: =偿债原表!D18 -> 644 | M18: =K18+L18 -> 644 | N18: =J18-M18 -> 6691.92 | O18: =O17+N18 -> 32333.57 | P18: =MAX(0,-(R17+N18)) -> 0 | Q18: =Q17+P18 -> 16145.31 | R18: =O18+Q18 -> 48478.88
A19: 原表 | B19: 早版 | C19: 17 | D19: 2040 | E19: =INDEX(驱动复算!A18:X18,1,情景参数!B2) -> 18189.64 | F19: =E19*(1-情景参数!D2) -> 18189.64 | G19: =IF(情景参数!E2="原表",驱动复算!U18-驱动复算!W18,驱动复算!P18) -> 10486.47 | H19: =IF(情景参数!E2="原表",驱动复算!W18,F19*情景参数!C2) -> 354.33 | I19: =IF(情景参数!E2="原表",驱动复算!U18,G19+H19) -> 10840.8 | J19: =(F19-I19)*(1-情景参数!F2) -> 7348.84 | K19: =偿债原表!C19 -> 0 | L19: =偿债原表!D19 -> 644 | M19: =K19+L19 -> 644 | N19: =J19-M19 -> 6704.84 | O19: =O18+N19 -> 39038.41 | P19: =MAX(0,-(R18+N19)) -> 0 | Q19: =Q18+P19 -> 16145.31 | R19: =O19+Q19 -> 55183.72
A20: 原表 | B20: 早版 | C20: 18 | D20: 2041 | E20: =INDEX(驱动复算!A19:X19,1,情景参数!B2) -> 18520.8 | F20: =E20*(1-情景参数!D2) -> 18520.8 | G20: =IF(情景参数!E2="原表",驱动复算!U19-驱动复算!W19,驱动复算!P19) -> 10801.07 | H20: =IF(情景参数!E2="原表",驱动复算!W19,F20*情景参数!C2) -> 360.77 | I20: =IF(情景参数!E2="原表",驱动复算!U19,G20+H20) -> 11161.84 | J20: =(F20-I20)*(1-情景参数!F2) -> 7358.96 | K20: =偿债原表!C20 -> 20000 | L20: =偿债原表!D20 -> 644 | M20: =K20+L20 -> 20644 | N20: =J20-M20 -> -13285.04 | O20: =O19+N20 -> 25753.37 | P20: =MAX(0,-(R19+N20)) -> 0 | Q20: =Q19+P20 -> 16145.31 | R20: =O20+Q20 -> 41898.68
A21: 原表 | B21: 晚版 | C21: 0 | D21: 已融资 | E21: =0 -> 0 | F21: =E21*(1-情景参数!D2) -> 0 | G21: =0 -> 0 | H21: =0 -> 0 | I21: =0 -> 0 | J21: =(F21-I21)*(1-情景参数!F2) -> 0 | K21: =偿债原表!F2 -> 0 | L21: =偿债原表!G2 -> 1374.2 | M21: =K21+L21 -> 1374.2 | N21: =J21-M21 -> -1374.2 | O21: =N21 -> -1374.2 | P21: =MAX(0,-N21) -> 1374.2 | Q21: =P21 -> 1374.2 | R21: =O21+Q21 -> 0
A22: 原表 | B22: 晚版 | C22: 1 | D22: 2024 | E22: =INDEX(驱动复算!A2:X2,1,情景参数!B2) -> 0 | F22: =E22*(1-情景参数!D2) -> 0 | G22: =IF(情景参数!E2="原表",驱动复算!U2-驱动复算!W2,驱动复算!P2) -> 0 | H22: =IF(情景参数!E2="原表",驱动复算!W2,F22*情景参数!C2) -> 0 | I22: =IF(情景参数!E2="原表",驱动复算!U2,G22+H22) -> 0 | J22: =(F22-I22)*(1-情景参数!F2) -> 0 | K22: =偿债原表!F3 -> 0 | L22: =偿债原表!G3 -> 1107.58 | M22: =K22+L22 -> 1107.58 | N22: =J22-M22 -> -1107.58 | O22: =O21+N22 -> -2481.78 | P22: =MAX(0,-(R21+N22)) -> 1107.58 | Q22: =Q21+P22 -> 2481.78 | R22: =O22+Q22 -> 0
A23: 原表 | B23: 晚版 | C23: 2 | D23: 2025 | E23: =INDEX(驱动复算!A3:X3,1,情景参数!B2) -> 0 | F23: =E23*(1-情景参数!D2) -> 0 | G23: =IF(情景参数!E2="原表",驱动复算!U3-驱动复算!W3,驱动复算!P3) -> 0 | H23: =IF(情景参数!E2="原表",驱动复算!W3,F23*情景参数!C2) -> 0 | I23: =IF(情景参数!E2="原表",驱动复算!U3,G23+H23) -> 0 | J23: =(F23-I23)*(1-情景参数!F2) -> 0 | K23: =偿债原表!F4 -> 0 | L23: =偿债原表!G4 -> 1107.58 | M23: =K23+L23 -> 1107.58 | N23: =J23-M23 -> -1107.58 | O23: =O22+N23 -> -3589.36 | P23: =MAX(0,-(R22+N23)) -> 1107.58 | Q23: =Q22+P23 -> 3589.36 | R23: =O23+Q23 -> 0
A24: 原表 | B24: 晚版 | C24: 3 | D24: 2026 | E24: =INDEX(驱动复算!A4:X4,1,情景参数!B2) -> 0 | F24: =E24*(1-情景参数!D2) -> 0 | G24: =IF(情景参数!E2="原表",驱动复算!U4-驱动复算!W4,驱动复算!P4) -> 0 | H24: =IF(情景参数!E2="原表",驱动复算!W4,F24*情景参数!C2) -> 0 | I24: =IF(情景参数!E2="原表",驱动复算!U4,G24+H24) -> 0 | J24: =(F24-I24)*(1-情景参数!F2) -> 0 | K24: =偿债原表!F5 -> 0 | L24: =偿债原表!G5 -> 1107.58 | M24: =K24+L24 -> 1107.58 | N24: =J24-M24 -> -1107.58 | O24: =O23+N24 -> -4696.94 | P24: =MAX(0,-(R23+N24)) -> 1107.58 | Q24: =Q23+P24 -> 4696.94 | R24: =O24+Q24 -> 0
A25: 原表 | B25: 晚版 | C25: 4 | D25: 2027 | E25: =INDEX(驱动复算!A5:X5,1,情景参数!B2) -> 0 | F25: =E25*(1-情景参数!D2) -> 0 | G25: =IF(情景参数!E2="原表",驱动复算!U5-驱动复算!W5,驱动复算!P5) -> 0 | H25: =IF(情景参数!E2="原表",驱动复算!W5,F25*情景参数!C2) -> 0 | I25: =IF(情景参数!E2="原表",驱动复算!U5,G25+H25) -> 0 | J25: =(F25-I25)*(1-情景参数!F2) -> 0 | K25: =偿债原表!F6 -> 0 | L25: =偿债原表!G6 -> 1107.58 | M25: =K25+L25 -> 1107.58 | N25: =J25-M25 -> -1107.58 | O25: =O24+N25 -> -5804.52 | P25: =MAX(0,-(R24+N25)) -> 1107.58 | Q25: =Q24+P25 -> 5804.52 | R25: =O25+Q25 -> 0
A26: 原表 | B26: 晚版 | C26: 5 | D26: 2028 | E26: =INDEX(驱动复算!A6:X6,1,情景参数!B2) -> 9234.58 | F26: =E26*(1-情景参数!D2) -> 9234.58 | G26: =IF(情景参数!E2="原表",驱动复算!U6-驱动复算!W6,驱动复算!P6) -> 7355 | H26: =IF(情景参数!E2="原表",驱动复算!W6,F26*情景参数!C2) -> 184.69 | I26: =IF(情景参数!E2="原表",驱动复算!U6,G26+H26) -> 7539.69 | J26: =(F26-I26)*(1-情景参数!F2) -> 1694.89 | K26: =偿债原表!F7 -> 1400 | L26: =偿债原表!G7 -> 1107.58 | M26: =K26+L26 -> 2507.58 | N26: =J26-M26 -> -812.69 | O26: =O25+N26 -> -6617.21 | P26: =MAX(0,-(R25+N26)) -> 812.69 | Q26: =Q25+P26 -> 6617.21 | R26: =O26+Q26 -> 0
A27: 原表 | B27: 晚版 | C27: 6 | D27: 2029 | E27: =INDEX(驱动复算!A7:X7,1,情景参数!B2) -> 10123.19 | F27: =E27*(1-情景参数!D2) -> 10123.19 | G27: =IF(情景参数!E2="原表",驱动复算!U7-驱动复算!W7,驱动复算!P7) -> 7575.65 | H27: =IF(情景参数!E2="原表",驱动复算!W7,F27*情景参数!C2) -> 202.46 | I27: =IF(情景参数!E2="原表",驱动复算!U7,G27+H27) -> 7778.11 | J27: =(F27-I27)*(1-情景参数!F2) -> 2345.08 | K27: =偿债原表!F8 -> 0 | L27: =偿债原表!G8 -> 1075.8 | M27: =K27+L27 -> 1075.8 | N27: =J27-M27 -> 1269.28 | O27: =O26+N27 -> -5347.93 | P27: =MAX(0,-(R26+N27)) -> 0 | Q27: =Q26+P27 -> 6617.21 | R27: =O27+Q27 -> 1269.28
A28: 原表 | B28: 晚版 | C28: 7 | D28: 2030 | E28: =INDEX(驱动复算!A8:X8,1,情景参数!B2) -> 11041.69 | F28: =E28*(1-情景参数!D2) -> 11041.69 | G28: =IF(情景参数!E2="原表",驱动复算!U8-驱动复算!W8,驱动复算!P8) -> 7802.91 | H28: =IF(情景参数!E2="原表",驱动复算!W8,F28*情景参数!C2) -> 220.83 | I28: =IF(情景参数!E2="原表",驱动复算!U8,G28+H28) -> 8023.74 | J28: =(F28-I28)*(1-情景参数!F2) -> 3017.95 | K28: =偿债原表!F9 -> 0 | L28: =偿债原表!G9 -> 1075.8 | M28: =K28+L28 -> 1075.8 | N28: =J28-M28 -> 1942.15 | O28: =O27+N28 -> -3405.78 | P28: =MAX(0,-(R27+N28)) -> 0 | Q28: =Q27+P28 -> 6617.21 | R28: =O28+Q28 -> 3211.43
A29: 原表 | B29: 晚版 | C29: 8 | D29: 2031 | E29: =INDEX(驱动复算!A9:X9,1,情景参数!B2) -> 12052.04 | F29: =E29*(1-情景参数!D2) -> 12052.04 | G29: =IF(情景参数!E2="原表",驱动复算!U9-驱动复算!W9,驱动复算!P9) -> 8037 | H29: =IF(情景参数!E2="原表",驱动复算!W9,F29*情景参数!C2) -> 241.04 | I29: =IF(情景参数!E2="原表",驱动复算!U9,G29+H29) -> 8278.04 | J29: =(F29-I29)*(1-情景参数!F2) -> 3774 | K29: =偿债原表!F10 -> 0 | L29: =偿债原表!G10 -> 1075.8 | M29: =K29+L29 -> 1075.8 | N29: =J29-M29 -> 2698.2 | O29: =O28+N29 -> -707.58 | P29: =MAX(0,-(R28+N29)) -> 0 | Q29: =Q28+P29 -> 6617.21 | R29: =O29+Q29 -> 5909.63
A30: 原表 | B30: 晚版 | C30: 9 | D30: 2032 | E30: =INDEX(驱动复算!A10:X10,1,情景参数!B2) -> 13163.43 | F30: =E30*(1-情景参数!D2) -> 13163.43 | G30: =IF(情景参数!E2="原表",驱动复算!U10-驱动复算!W10,驱动复算!P10) -> 8278.11 | H30: =IF(情景参数!E2="原表",驱动复算!W10,F30*情景参数!C2) -> 263.27 | I30: =IF(情景参数!E2="原表",驱动复算!U10,G30+H30) -> 8541.38 | J30: =(F30-I30)*(1-情景参数!F2) -> 4622.05 | K30: =偿债原表!F11 -> 2000 | L30: =偿债原表!G11 -> 1075.8 | M30: =K30+L30 -> 3075.8 | N30: =J30-M30 -> 1546.25 | O30: =O29+N30 -> 838.67 | P30: =MAX(0,-(R29+N30)) -> 0 | Q30: =Q29+P30 -> 6617.21 | R30: =O30+Q30 -> 7455.88
A31: 原表 | B31: 晚版 | C31: 10 | D31: 2033 | E31: =INDEX(驱动复算!A11:X11,1,情景参数!B2) -> 14139.86 | F31: =E31*(1-情景参数!D2) -> 14139.86 | G31: =IF(情景参数!E2="原表",驱动复算!U11-驱动复算!W11,驱动复算!P11) -> 8526.47 | H31: =IF(情景参数!E2="原表",驱动复算!W11,F31*情景参数!C2) -> 282.8 | I31: =IF(情景参数!E2="原表",驱动复算!U11,G31+H31) -> 8809.27 | J31: =(F31-I31)*(1-情景参数!F2) -> 5330.59 | K31: =偿债原表!F12 -> 9600 | L31: =偿债原表!G12 -> 1018.8 | M31: =K31+L31 -> 10618.8 | N31: =J31-M31 -> -5288.21 | O31: =O30+N31 -> -4449.54 | P31: =MAX(0,-(R30+N31)) -> 0 | Q31: =Q30+P31 -> 6617.21 | R31: =O31+Q31 -> 2167.67
A32: 原表 | B32: 晚版 | C32: 11 | D32: 2034 | E32: =INDEX(驱动复算!A12:X12,1,情景参数!B2) -> 14781.69 | F32: =E32*(1-情景参数!D2) -> 14781.69 | G32: =IF(情景参数!E2="原表",驱动复算!U12-驱动复算!W12,驱动复算!P12) -> 8782.26 | H32: =IF(情景参数!E2="原表",驱动复算!W12,F32*情景参数!C2) -> 295.63 | I32: =IF(情景参数!E2="原表",驱动复算!U12,G32+H32) -> 9077.89 | J32: =(F32-I32)*(1-情景参数!F2) -> 5703.8 | K32: =偿债原表!F13 -> 0 | L32: =偿债原表!G13 -> 673.2 | M32: =K32+L32 -> 673.2 | N32: =J32-M32 -> 5030.6 | O32: =O31+N32 -> 581.06 | P32: =MAX(0,-(R31+N32)) -> 0 | Q32: =Q31+P32 -> 6617.21 | R32: =O32+Q32 -> 7198.27
A33: 原表 | B33: 晚版 | C33: 12 | D33: 2035 | E33: =INDEX(驱动复算!A13:X13,1,情景参数!B2) -> 15455.6 | F33: =E33*(1-情景参数!D2) -> 15455.6 | G33: =IF(情景参数!E2="原表",驱动复算!U13-驱动复算!W13,驱动复算!P13) -> 9045.74 | H33: =IF(情景参数!E2="原表",驱动复算!W13,F33*情景参数!C2) -> 309.11 | I33: =IF(情景参数!E2="原表",驱动复算!U13,G33+H33) -> 9354.85 | J33: =(F33-I33)*(1-情景参数!F2) -> 6100.75 | K33: =偿债原表!F14 -> 0 | L33: =偿债原表!G14 -> 673.2 | M33: =K33+L33 -> 673.2 | N33: =J33-M33 -> 5427.55 | O33: =O32+N33 -> 6008.61 | P33: =MAX(0,-(R32+N33)) -> 0 | Q33: =Q32+P33 -> 6617.21 | R33: =O33+Q33 -> 12625.82
A34: 原表 | B34: 晚版 | C34: 13 | D34: 2036 | E34: =INDEX(驱动复算!A14:X14,1,情景参数!B2) -> 16163.21 | F34: =E34*(1-情景参数!D2) -> 16163.21 | G34: =IF(情景参数!E2="原表",驱动复算!U14-驱动复算!W14,驱动复算!P14) -> 9317.11 | H34: =IF(情景参数!E2="原表",驱动复算!W14,F34*情景参数!C2) -> 323.26 | I34: =IF(情景参数!E2="原表",驱动复算!U14,G34+H34) -> 9640.37 | J34: =(F34-I34)*(1-情景参数!F2) -> 6522.84 | K34: =偿债原表!F15 -> 0 | L34: =偿债原表!G15 -> 673.2 | M34: =K34+L34 -> 673.2 | N34: =J34-M34 -> 5849.64 | O34: =O33+N34 -> 11858.25 | P34: =MAX(0,-(R33+N34)) -> 0 | Q34: =Q33+P34 -> 6617.21 | R34: =O34+Q34 -> 18475.46
A35: 原表 | B35: 晚版 | C35: 14 | D35: 2037 | E35: =INDEX(驱动复算!A15:X15,1,情景参数!B2) -> 16906.2 | F35: =E35*(1-情景参数!D2) -> 16906.2 | G35: =IF(情景参数!E2="原表",驱动复算!U15-驱动复算!W15,驱动复算!P15) -> 9596.62 | H35: =IF(情景参数!E2="原表",驱动复算!W15,F35*情景参数!C2) -> 329.21 | I35: =IF(情景参数!E2="原表",驱动复算!U15,G35+H35) -> 9925.83 | J35: =(F35-I35)*(1-情景参数!F2) -> 6980.37 | K35: =偿债原表!F16 -> 1000 | L35: =偿债原表!G16 -> 673.2 | M35: =K35+L35 -> 1673.2 | N35: =J35-M35 -> 5307.17 | O35: =O34+N35 -> 17165.42 | P35: =MAX(0,-(R34+N35)) -> 0 | Q35: =Q34+P35 -> 6617.21 | R35: =O35+Q35 -> 23782.63
A36: 原表 | B36: 晚版 | C36: 15 | D36: 2038 | E36: =INDEX(驱动复算!A16:X16,1,情景参数!B2) -> 17546.68 | F36: =E36*(1-情景参数!D2) -> 17546.68 | G36: =IF(情景参数!E2="原表",驱动复算!U16-驱动复算!W16,驱动复算!P16) -> 9884.51 | H36: =IF(情景参数!E2="原表",驱动复算!W16,F36*情景参数!C2) -> 341.84 | I36: =IF(情景参数!E2="原表",驱动复算!U16,G36+H36) -> 10226.35 | J36: =(F36-I36)*(1-情景参数!F2) -> 7320.33 | K36: =偿债原表!F17 -> 0 | L36: =偿债原表!G17 -> 644 | M36: =K36+L36 -> 644 | N36: =J36-M36 -> 6676.33 | O36: =O35+N36 -> 23841.75 | P36: =MAX(0,-(R35+N36)) -> 0 | Q36: =Q35+P36 -> 6617.21 | R36: =O36+Q36 -> 30458.96
A37: 原表 | B37: 晚版 | C37: 16 | D37: 2039 | E37: =INDEX(驱动复算!A17:X17,1,情景参数!B2) -> 17864.98 | F37: =E37*(1-情景参数!D2) -> 17864.98 | G37: =IF(情景参数!E2="原表",驱动复算!U17-驱动复算!W17,驱动复算!P17) -> 10181.04 | H37: =IF(情景参数!E2="原表",驱动复算!W17,F37*情景参数!C2) -> 348.02 | I37: =IF(情景参数!E2="原表",驱动复算!U17,G37+H37) -> 10529.06 | J37: =(F37-I37)*(1-情景参数!F2) -> 7335.92 | K37: =偿债原表!F18 -> 0 | L37: =偿债原表!G18 -> 644 | M37: =K37+L37 -> 644 | N37: =J37-M37 -> 6691.92 | O37: =O36+N37 -> 30533.67 | P37: =MAX(0,-(R36+N37)) -> 0 | Q37: =Q36+P37 -> 6617.21 | R37: =O37+Q37 -> 37150.88
A38: 原表 | B38: 晚版 | C38: 17 | D38: 2040 | E38: =INDEX(驱动复算!A18:X18,1,情景参数!B2) -> 18189.64 | F38: =E38*(1-情景参数!D2) -> 18189.64 | G38: =IF(情景参数!E2="原表",驱动复算!U18-驱动复算!W18,驱动复算!P18) -> 10486.47 | H38: =IF(情景参数!E2="原表",驱动复算!W18,F38*情景参数!C2) -> 354.33 | I38: =IF(情景参数!E2="原表",驱动复算!U18,G38+H38) -> 10840.8 | J38: =(F38-I38)*(1-情景参数!F2) -> 7348.84 | K38: =偿债原表!F19 -> 0 | L38: =偿债原表!G19 -> 644 | M38: =K38+L38 -> 644 | N38: =J38-M38 -> 6704.84 | O38: =O37+N38 -> 37238.51 | P38: =MAX(0,-(R37+N38)) -> 0 | Q38: =Q37+P38 -> 6617.21 | R38: =O38+Q38 -> 43855.72
A39: 原表 | B39: 晚版 | C39: 18 | D39: 2041 | E39: =INDEX(驱动复算!A19:X19,1,情景参数!B2) -> 18520.8 | F39: =E39*(1-情景参数!D2) -> 18520.8 | G39: =IF(情景参数!E2="原表",驱动复算!U19-驱动复算!W19,驱动复算!P19) -> 10801.07 | H39: =IF(情景参数!E2="原表",驱动复算!W19,F39*情景参数!C2) -> 360.77 | I39: =IF(情景参数!E2="原表",驱动复算!U19,G39+H39) -> 11161.84 | J39: =(F39-I39)*(1-情景参数!F2) -> 7358.96 | K39: =偿债原表!F20 -> 20000 | L39: =偿债原表!G20 -> 644 | M39: =K39+L39 -> 20644 | N39: =J39-M39 -> -13285.04 | O39: =O38+N39 -> 23953.47 | P39: =MAX(0,-(R38+N39)) -> 0 | Q39: =Q38+P39 -> 6617.21 | R39: =O39+Q39 -> 30570.68
A40: 统一2% | B40: 早版 | C40: 0 | D40: 已融资 | E40: =0 -> 0 | F40: =E40*(1-情景参数!D3) -> 0 | G40: =0 -> 0 | H40: =0 -> 0 | I40: =0 -> 0 | J40: =(F40-I40)*(1-情景参数!F3) -> 0 | K40: =偿债原表!C2 -> 0 | L40: =偿债原表!D2 -> 1374.2 | M40: =K40+L40 -> 1374.2 | N40: =J40-M40 -> -1374.2 | O40: =N40 -> -1374.2 | P40: =MAX(0,-N40) -> 1374.2 | Q40: =P40 -> 1374.2 | R40: =O40+Q40 -> 0
A41: 统一2% | B41: 早版 | C41: 1 | D41: 2024 | E41: =INDEX(驱动复算!A2:X2,1,情景参数!B3) -> 0 | F41: =E41*(1-情景参数!D3) -> 0 | G41: =IF(情景参数!E3="原表",驱动复算!U2-驱动复算!W2,驱动复算!P2) -> 0 | H41: =IF(情景参数!E3="原表",驱动复算!W2,F41*情景参数!C3) -> 0 | I41: =IF(情景参数!E3="原表",驱动复算!U2,G41+H41) -> 0 | J41: =(F41-I41)*(1-情景参数!F3) -> 0 | K41: =偿债原表!C3 -> 0 | L41: =偿债原表!D3 -> 1093.2 | M41: =K41+L41 -> 1093.2 | N41: =J41-M41 -> -1093.2 | O41: =O40+N41 -> -2467.4 | P41: =MAX(0,-(R40+N41)) -> 1093.2 | Q41: =Q40+P41 -> 2467.4 | R41: =O41+Q41 -> 0
A42: 统一2% | B42: 早版 | C42: 2 | D42: 2025 | E42: =INDEX(驱动复算!A3:X3,1,情景参数!B3) -> 0 | F42: =E42*(1-情景参数!D3) -> 0 | G42: =IF(情景参数!E3="原表",驱动复算!U3-驱动复算!W3,驱动复算!P3) -> 0 | H42: =IF(情景参数!E3="原表",驱动复算!W3,F42*情景参数!C3) -> 0 | I42: =IF(情景参数!E3="原表",驱动复算!U3,G42+H42) -> 0 | J42: =(F42-I42)*(1-情景参数!F3) -> 0 | K42: =偿债原表!C4 -> 0 | L42: =偿债原表!D4 -> 1093.2 | M42: =K42+L42 -> 1093.2 | N42: =J42-M42 -> -1093.2 | O42: =O41+N42 -> -3560.6 | P42: =MAX(0,-(R41+N42)) -> 1093.2 | Q42: =Q41+P42 -> 3560.6 | R42: =O42+Q42 -> 0
A43: 统一2% | B43: 早版 | C43: 3 | D43: 2026 | E43: =INDEX(驱动复算!A4:X4,1,情景参数!B3) -> 0 | F43: =E43*(1-情景参数!D3) -> 0 | G43: =IF(情景参数!E3="原表",驱动复算!U4-驱动复算!W4,驱动复算!P4) -> 0 | H43: =IF(情景参数!E3="原表",驱动复算!W4,F43*情景参数!C3) -> 0 | I43: =IF(情景参数!E3="原表",驱动复算!U4,G43+H43) -> 0 | J43: =(F43-I43)*(1-情景参数!F3) -> 0 | K43: =偿债原表!C5 -> 0 | L43: =偿债原表!D5 -> 1093.2 | M43: =K43+L43 -> 1093.2 | N43: =J43-M43 -> -1093.2 | O43: =O42+N43 -> -4653.8 | P43: =MAX(0,-(R42+N43)) -> 1093.2 | Q43: =Q42+P43 -> 4653.8 | R43: =O43+Q43 -> 0
A44: 统一2% | B44: 早版 | C44: 4 | D44: 2027 | E44: =INDEX(驱动复算!A5:X5,1,情景参数!B3) -> 0 | F44: =E44*(1-情景参数!D3) -> 0 | G44: =IF(情景参数!E3="原表",驱动复算!U5-驱动复算!W5,驱动复算!P5) -> 0 | H44: =IF(情景参数!E3="原表",驱动复算!W5,F44*情景参数!C3) -> 0 | I44: =IF(情景参数!E3="原表",驱动复算!U5,G44+H44) -> 0 | J44: =(F44-I44)*(1-情景参数!F3) -> 0 | K44: =偿债原表!C6 -> 0 | L44: =偿债原表!D6 -> 1093.2 | M44: =K44+L44 -> 1093.2 | N44: =J44-M44 -> -1093.2 | O44: =O43+N44 -> -5747 | P44: =MAX(0,-(R43+N44)) -> 1093.2 | Q44: =Q43+P44 -> 5747 | R44: =O44+Q44 -> 0
A45: 统一2% | B45: 早版 | C45: 5 | D45: 2028 | E45: =INDEX(驱动复算!A6:X6,1,情景参数!B3) -> 9234.58 | F45: =E45*(1-情景参数!D3) -> 9234.58 | G45: =IF(情景参数!E3="原表",驱动复算!U6-驱动复算!W6,驱动复算!P6) -> 7355 | H45: =IF(情景参数!E3="原表",驱动复算!W6,F45*情景参数!C3) -> 184.6916 | I45: =IF(情景参数!E3="原表",驱动复算!U6,G45+H45) -> 7539.6916 | J45: =(F45-I45)*(1-情景参数!F3) -> 1694.8884 | K45: =偿债原表!C7 -> 11000 | L45: =偿债原表!D7 -> 1093.2 | M45: =K45+L45 -> 12093.2 | N45: =J45-M45 -> -10398.312 | O45: =O44+N45 -> -16145.312 | P45: =MAX(0,-(R44+N45)) -> 10398.312 | Q45: =Q44+P45 -> 16145.312 | R45: =O45+Q45 -> 0
A46: 统一2% | B46: 早版 | C46: 6 | D46: 2029 | E46: =INDEX(驱动复算!A7:X7,1,情景参数!B3) -> 10123.19 | F46: =E46*(1-情景参数!D3) -> 10123.19 | G46: =IF(情景参数!E3="原表",驱动复算!U7-驱动复算!W7,驱动复算!P7) -> 7575.65 | H46: =IF(情景参数!E3="原表",驱动复算!W7,F46*情景参数!C3) -> 202.4638 | I46: =IF(情景参数!E3="原表",驱动复算!U7,G46+H46) -> 7778.1138 | J46: =(F46-I46)*(1-情景参数!F3) -> 2345.0762 | K46: =偿债原表!C8 -> 0 | L46: =偿债原表!D8 -> 730.2 | M46: =K46+L46 -> 730.2 | N46: =J46-M46 -> 1614.8762 | O46: =O45+N46 -> -14530.435 | P46: =MAX(0,-(R45+N46)) -> 0 | Q46: =Q45+P46 -> 16145.312 | R46: =O46+Q46 -> 1614.8762
A47: 统一2% | B47: 早版 | C47: 7 | D47: 2030 | E47: =INDEX(驱动复算!A8:X8,1,情景参数!B3) -> 11041.69 | F47: =E47*(1-情景参数!D3) -> 11041.69 | G47: =IF(情景参数!E3="原表",驱动复算!U8-驱动复算!W8,驱动复算!P8) -> 7802.9195 | H47: =IF(情景参数!E3="原表",驱动复算!W8,F47*情景参数!C3) -> 220.8338 | I47: =IF(情景参数!E3="原表",驱动复算!U8,G47+H47) -> 8023.7533 | J47: =(F47-I47)*(1-情景参数!F3) -> 3017.9367 | K47: =偿债原表!C9 -> 0 | L47: =偿债原表!D9 -> 730.2 | M47: =K47+L47 -> 730.2 | N47: =J47-M47 -> 2287.7367 | O47: =O46+N47 -> -12242.699 | P47: =MAX(0,-(R46+N47)) -> 0 | Q47: =Q46+P47 -> 16145.312 | R47: =O47+Q47 -> 3902.6129
A48: 统一2% | B48: 早版 | C48: 8 | D48: 2031 | E48: =INDEX(驱动复算!A9:X9,1,情景参数!B3) -> 12052.04 | F48: =E48*(1-情景参数!D3) -> 12052.04 | G48: =IF(情景参数!E3="原表",驱动复算!U9-驱动复算!W9,驱动复算!P9) -> 8037.0071 | H48: =IF(情景参数!E3="原表",驱动复算!W9,F48*情景参数!C3) -> 241.0408 | I48: =IF(情景参数!E3="原表",驱动复算!U9,G48+H48) -> 8278.0479 | J48: =(F48-I48)*(1-情景参数!F3) -> 3773.9921 | K48: =偿债原表!C10 -> 0 | L48: =偿债原表!D10 -> 730.2 | M48: =K48+L48 -> 730.2 | N48: =J48-M48 -> 3043.7921 | O48: =O47+N48 -> -9198.9066 | P48: =MAX(0,-(R47+N48)) -> 0 | Q48: =Q47+P48 -> 16145.312 | R48: =O48+Q48 -> 6946.405
A49: 统一2% | B49: 早版 | C49: 9 | D49: 2032 | E49: =INDEX(驱动复算!A10:X10,1,情景参数!B3) -> 13163.43 | F49: =E49*(1-情景参数!D3) -> 13163.43 | G49: =IF(情景参数!E3="原表",驱动复算!U10-驱动复算!W10,驱动复算!P10) -> 8278.1173 | H49: =IF(情景参数!E3="原表",驱动复算!W10,F49*情景参数!C3) -> 263.2686 | I49: =IF(情景参数!E3="原表",驱动复算!U10,G49+H49) -> 8541.3859 | J49: =(F49-I49)*(1-情景参数!F3) -> 4622.0441 | K49: =偿债原表!C11 -> 2000 | L49: =偿债原表!D11 -> 730.2 | M49: =K49+L49 -> 2730.2 | N49: =J49-M49 -> 1891.8441 | O49: =O48+N49 -> -7307.0625 | P49: =MAX(0,-(R48+N49)) -> 0 | Q49: =Q48+P49 -> 16145.312 | R49: =O49+Q49 -> 8838.2491
A50: 统一2% | B50: 早版 | C50: 10 | D50: 2033 | E50: =INDEX(驱动复算!A11:X11,1,情景参数!B3) -> 14139.86 | F50: =E50*(1-情景参数!D3) -> 14139.86 | G50: =IF(情景参数!E3="原表",驱动复算!U11-驱动复算!W11,驱动复算!P11) -> 8526.4608 | H50: =IF(情景参数!E3="原表",驱动复算!W11,F50*情景参数!C3) -> 282.7972 | I50: =IF(情景参数!E3="原表",驱动复算!U11,G50+H50) -> 8809.258 | J50: =(F50-I50)*(1-情景参数!F3) -> 5330.602 | K50: =偿债原表!C12 -> 0 | L50: =偿债原表!D12 -> 673.2 | M50: =K50+L50 -> 673.2 | N50: =J50-M50 -> 4657.402 | O50: =O49+N50 -> -2649.6605 | P50: =MAX(0,-(R49+N50)) -> 0 | Q50: =Q49+P50 -> 16145.312 | R50: =O50+Q50 -> 13495.651
A51: 统一2% | B51: 早版 | C51: 11 | D51: 2034 | E51: =INDEX(驱动复算!A12:X12,1,情景参数!B3) -> 14781.69 | F51: =E51*(1-情景参数!D3) -> 14781.69 | G51: =IF(情景参数!E3="原表",驱动复算!U12-驱动复算!W12,驱动复算!P12) -> 8782.2546 | H51: =IF(情景参数!E3="原表",驱动复算!W12,F51*情景参数!C3) -> 295.6338 | I51: =IF(情景参数!E3="原表",驱动复算!U12,G51+H51) -> 9077.8884 | J51: =(F51-I51)*(1-情景参数!F3) -> 5703.8016 | K51: =偿债原表!C13 -> 0 | L51: =偿债原表!D13 -> 673.2 | M51: =K51+L51 -> 673.2 | N51: =J51-M51 -> 5030.6016 | O51: =O50+N51 -> 2380.9411 | P51: =MAX(0,-(R50+N51)) -> 0 | Q51: =Q50+P51 -> 16145.312 | R51: =O51+Q51 -> 18526.253
A52: 统一2% | B52: 早版 | C52: 12 | D52: 2035 | E52: =INDEX(驱动复算!A13:X13,1,情景参数!B3) -> 15455.6 | F52: =E52*(1-情景参数!D3) -> 15455.6 | G52: =IF(情景参数!E3="原表",驱动复算!U13-驱动复算!W13,驱动复算!P13) -> 9045.7223 | H52: =IF(情景参数!E3="原表",驱动复算!W13,F52*情景参数!C3) -> 309.112 | I52: =IF(情景参数!E3="原表",驱动复算!U13,G52+H52) -> 9354.8343 | J52: =(F52-I52)*(1-情景参数!F3) -> 6100.7657 | K52: =偿债原表!C14 -> 0 | L52: =偿债原表!D14 -> 673.2 | M52: =K52+L52 -> 673.2 | N52: =J52-M52 -> 5427.5657 | O52: =O51+N52 -> 7808.5068 | P52: =MAX(0,-(R51+N52)) -> 0 | Q52: =Q51+P52 -> 16145.312 | R52: =O52+Q52 -> 23953.818
A53: 统一2% | B53: 早版 | C53: 13 | D53: 2036 | E53: =INDEX(驱动复算!A14:X14,1,情景参数!B3) -> 16163.21 | F53: =E53*(1-情景参数!D3) -> 16163.21 | G53: =IF(情景参数!E3="原表",驱动复算!U14-驱动复算!W14,驱动复算!P14) -> 9317.0939 | H53: =IF(情景参数!E3="原表",驱动复算!W14,F53*情景参数!C3) -> 323.2642 | I53: =IF(情景参数!E3="原表",驱动复算!U14,G53+H53) -> 9640.3581 | J53: =(F53-I53)*(1-情景参数!F3) -> 6522.8519 | K53: =偿债原表!C15 -> 0 | L53: =偿债原表!D15 -> 673.2 | M53: =K53+L53 -> 673.2 | N53: =J53-M53 -> 5849.6519 | O53: =O52+N53 -> 13658.159 | P53: =MAX(0,-(R52+N53)) -> 0 | Q53: =Q52+P53 -> 16145.312 | R53: =O53+Q53 -> 29803.47
A54: 统一2% | B54: 早版 | C54: 14 | D54: 2037 | E54: =INDEX(驱动复算!A15:X15,1,情景参数!B3) -> 16906.2 | F54: =E54*(1-情景参数!D3) -> 16906.2 | G54: =IF(情景参数!E3="原表",驱动复算!U15-驱动复算!W15,驱动复算!P15) -> 9596.6068 | H54: =IF(情景参数!E3="原表",驱动复算!W15,F54*情景参数!C3) -> 338.124 | I54: =IF(情景参数!E3="原表",驱动复算!U15,G54+H54) -> 9934.7308 | J54: =(F54-I54)*(1-情景参数!F3) -> 6971.4692 | K54: =偿债原表!C16 -> 1000 | L54: =偿债原表!D16 -> 673.2 | M54: =K54+L54 -> 1673.2 | N54: =J54-M54 -> 5298.2692 | O54: =O53+N54 -> 18956.428 | P54: =MAX(0,-(R53+N54)) -> 0 | Q54: =Q53+P54 -> 16145.312 | R54: =O54+Q54 -> 35101.739
A55: 统一2% | B55: 早版 | C55: 15 | D55: 2038 | E55: =INDEX(驱动复算!A16:X16,1,情景参数!B3) -> 17546.68 | F55: =E55*(1-情景参数!D3) -> 17546.68 | G55: =IF(情景参数!E3="原表",驱动复算!U16-驱动复算!W16,驱动复算!P16) -> 9884.505 | H55: =IF(情景参数!E3="原表",驱动复算!W16,F55*情景参数!C3) -> 350.9336 | I55: =IF(情景参数!E3="原表",驱动复算!U16,G55+H55) -> 10235.439 | J55: =(F55-I55)*(1-情景参数!F3) -> 7311.2414 | K55: =偿债原表!C17 -> 0 | L55: =偿债原表!D17 -> 644 | M55: =K55+L55 -> 644 | N55: =J55-M55 -> 6667.2414 | O55: =O54+N55 -> 25623.669 | P55: =MAX(0,-(R54+N55)) -> 0 | Q55: =Q54+P55 -> 16145.312 | R55: =O55+Q55 -> 41768.981
A56: 统一2% | B56: 早版 | C56: 16 | D56: 2039 | E56: =INDEX(驱动复算!A17:X17,1,情景参数!B3) -> 17864.98 | F56: =E56*(1-情景参数!D3) -> 17864.98 | G56: =IF(情景参数!E3="原表",驱动复算!U17-驱动复算!W17,驱动复算!P17) -> 10181.04 | H56: =IF(情景参数!E3="原表",驱动复算!W17,F56*情景参数!C3) -> 357.2996 | I56: =IF(情景参数!E3="原表",驱动复算!U17,G56+H56) -> 10538.34 | J56: =(F56-I56)*(1-情景参数!F3) -> 7326.6403 | K56: =偿债原表!C18 -> 0 | L56: =偿债原表!D18 -> 644 | M56: =K56+L56 -> 644 | N56: =J56-M56 -> 6682.6403 | O56: =O55+N56 -> 32306.31 | P56: =MAX(0,-(R55+N56)) -> 0 | Q56: =Q55+P56 -> 16145.312 | R56: =O56+Q56 -> 48451.621
A57: 统一2% | B57: 早版 | C57: 17 | D57: 2040 | E57: =INDEX(驱动复算!A18:X18,1,情景参数!B3) -> 18189.64 | F57: =E57*(1-情景参数!D3) -> 18189.64 | G57: =IF(情景参数!E3="原表",驱动复算!U18-驱动复算!W18,驱动复算!P18) -> 10486.471 | H57: =IF(情景参数!E3="原表",驱动复算!W18,F57*情景参数!C3) -> 363.7928 | I57: =IF(情景参数!E3="原表",驱动复算!U18,G57+H57) -> 10850.264 | J57: =(F57-I57)*(1-情景参数!F3) -> 7339.3759 | K57: =偿债原表!C19 -> 0 | L57: =偿债原表!D19 -> 644 | M57: =K57+L57 -> 644 | N57: =J57-M57 -> 6695.3759 | O57: =O56+N57 -> 39001.685 | P57: =MAX(0,-(R56+N57)) -> 0 | Q57: =Q56+P57 -> 16145.312 | R57: =O57+Q57 -> 55146.997
A58: 统一2% | B58: 早版 | C58: 18 | D58: 2041 | E58: =INDEX(驱动复算!A19:X19,1,情景参数!B3) -> 18520.8 | F58: =E58*(1-情景参数!D3) -> 18520.8 | G58: =IF(情景参数!E3="原表",驱动复算!U19-驱动复算!W19,驱动复算!P19) -> 10801.065 | H58: =IF(情景参数!E3="原表",驱动复算!W19,F58*情景参数!C3) -> 370.416 | I58: =IF(情景参数!E3="原表",驱动复算!U19,G58+H58) -> 11171.481 | J58: =(F58-I58)*(1-情景参数!F3) -> 7349.3185 | K58: =偿债原表!C20 -> 20000 | L58: =偿债原表!D20 -> 644 | M58: =K58+L58 -> 20644 | N58: =J58-M58 -> -13294.681 | O58: =O57+N58 -> 25707.004 | P58: =MAX(0,-(R57+N58)) -> 0 | Q58: =Q57+P58 -> 16145.312 | R58: =O58+Q58 -> 41852.316
A59: 统一2% | B59: 晚版 | C59: 0 | D59: 已融资 | E59: =0 -> 0 | F59: =E59*(1-情景参数!D3) -> 0 | G59: =0 -> 0 | H59: =0 -> 0 | I59: =0 -> 0 | J59: =(F59-I59)*(1-情景参数!F3) -> 0 | K59: =偿债原表!F2 -> 0 | L59: =偿债原表!G2 -> 1374.2 | M59: =K59+L59 -> 1374.2 | N59: =J59-M59 -> -1374.2 | O59: =N59 -> -1374.2 | P59: =MAX(0,-N59) -> 1374.2 | Q59: =P59 -> 1374.2 | R59: =O59+Q59 -> 0
A60: 统一2% | B60: 晚版 | C60: 1 | D60: 2024 | E60: =INDEX(驱动复算!A2:X2,1,情景参数!B3) -> 0 | F60: =E60*(1-情景参数!D3) -> 0 | G60: =IF(情景参数!E3="原表",驱动复算!U2-驱动复算!W2,驱动复算!P2) -> 0 | H60: =IF(情景参数!E3="原表",驱动复算!W2,F60*情景参数!C3) -> 0 | I60: =IF(情景参数!E3="原表",驱动复算!U2,G60+H60) -> 0 | J60: =(F60-I60)*(1-情景参数!F3) -> 0 | K60: =偿债原表!F3 -> 0 | L60: =偿债原表!G3 -> 1107.58 | M60: =K60+L60 -> 1107.58 | N60: =J60-M60 -> -1107.58 | O60: =O59+N60 -> -2481.78 | P60: =MAX(0,-(R59+N60)) -> 1107.58 | Q60: =Q59+P60 -> 2481.78 | R60: =O60+Q60 -> 0
A61: 统一2% | B61: 晚版 | C61: 2 | D61: 2025 | E61: =INDEX(驱动复算!A3:X3,1,情景参数!B3) -> 0 | F61: =E61*(1-情景参数!D3) -> 0 | G61: =IF(情景参数!E3="原表",驱动复算!U3-驱动复算!W3,驱动复算!P3) -> 0 | H61: =IF(情景参数!E3="原表",驱动复算!W3,F61*情景参数!C3) -> 0 | I61: =IF(情景参数!E3="原表",驱动复算!U3,G61+H61) -> 0 | J61: =(F61-I61)*(1-情景参数!F3) -> 0 | K61: =偿债原表!F4 -> 0 | L61: =偿债原表!G4 -> 1107.58 | M61: =K61+L61 -> 1107.58 | N61: =J61-M61 -> -1107.58 | O61: =O60+N61 -> -3589.36 | P61: =MAX(0,-(R60+N61)) -> 1107.58 | Q61: =Q60+P61 -> 3589.36 | R61: =O61+Q61 -> 0
A62: 统一2% | B62: 晚版 | C62: 3 | D62: 2026 | E62: =INDEX(驱动复算!A4:X4,1,情景参数!B3) -> 0 | F62: =E62*(1-情景参数!D3) -> 0 | G62: =IF(情景参数!E3="原表",驱动复算!U4-驱动复算!W4,驱动复算!P4) -> 0 | H62: =IF(情景参数!E3="原表",驱动复算!W4,F62*情景参数!C3) -> 0 | I62: =IF(情景参数!E3="原表",驱动复算!U4,G62+H62) -> 0 | J62: =(F62-I62)*(1-情景参数!F3) -> 0 | K62: =偿债原表!F5 -> 0 | L62: =偿债原表!G5 -> 1107.58 | M62: =K62+L62 -> 1107.58 | N62: =J62-M62 -> -1107.58 | O62: =O61+N62 -> -4696.94 | P62: =MAX(0,-(R61+N62)) -> 1107.58 | Q62: =Q61+P62 -> 4696.94 | R62: =O62+Q62 -> 0
A63: 统一2% | B63: 晚版 | C63: 4 | D63: 2027 | E63: =INDEX(驱动复算!A5:X5,1,情景参数!B3) -> 0 | F63: =E63*(1-情景参数!D3) -> 0 | G63: =IF(情景参数!E3="原表",驱动复算!U5-驱动复算!W5,驱动复算!P5) -> 0 | H63: =IF(情景参数!E3="原表",驱动复算!W5,F63*情景参数!C3) -> 0 | I63: =IF(情景参数!E3="原表",驱动复算!U5,G63+H63) -> 0 | J63: =(F63-I63)*(1-情景参数!F3) -> 0 | K63: =偿债原表!F6 -> 0 | L63: =偿债原表!G6 -> 1107.58 | M63: =K63+L63 -> 1107.58 | N63: =J63-M63 -> -1107.58 | O63: =O62+N63 -> -5804.52 | P63: =MAX(0,-(R62+N63)) -> 1107.58 | Q63: =Q62+P63 -> 5804.52 | R63: =O63+Q63 -> 0
A64: 统一2% | B64: 晚版 | C64: 5 | D64: 2028 | E64: =INDEX(驱动复算!A6:X6,1,情景参数!B3) -> 9234.58 | F64: =E64*(1-情景参数!D3) -> 9234.58 | G64: =IF(情景参数!E3="原表",驱动复算!U6-驱动复算!W6,驱动复算!P6) -> 7355 | H64: =IF(情景参数!E3="原表",驱动复算!W6,F64*情景参数!C3) -> 184.6916 | I64: =IF(情景参数!E3="原表",驱动复算!U6,G64+H64) -> 7539.6916 | J64: =(F64-I64)*(1-情景参数!F3) -> 1694.8884 | K64: =偿债原表!F7 -> 1400 | L64: =偿债原表!G7 -> 1107.58 | M64: =K64+L64 -> 2507.58 | N64: =J64-M64 -> -812.6916 | O64: =O63+N64 -> -6617.2116 | P64: =MAX(0,-(R63+N64)) -> 812.6916 | Q64: =Q63+P64 -> 6617.2116 | R64: =O64+Q64 -> 0
A65: 统一2% | B65: 晚版 | C65: 6 | D65: 2029 | E65: =INDEX(驱动复算!A7:X7,1,情景参数!B3) -> 10123.19 | F65: =E65*(1-情景参数!D3) -> 10123.19 | G65: =IF(情景参数!E3="原表",驱动复算!U7-驱动复算!W7,驱动复算!P7) -> 7575.65 | H65: =IF(情景参数!E3="原表",驱动复算!W7,F65*情景参数!C3) -> 202.4638 | I65: =IF(情景参数!E3="原表",驱动复算!U7,G65+H65) -> 7778.1138 | J65: =(F65-I65)*(1-情景参数!F3) -> 2345.0762 | K65: =偿债原表!F8 -> 0 | L65: =偿债原表!G8 -> 1075.8 | M65: =K65+L65 -> 1075.8 | N65: =J65-M65 -> 1269.2762 | O65: =O64+N65 -> -5347.9354 | P65: =MAX(0,-(R64+N65)) -> 0 | Q65: =Q64+P65 -> 6617.2116 | R65: =O65+Q65 -> 1269.2762
A66: 统一2% | B66: 晚版 | C66: 7 | D66: 2030 | E66: =INDEX(驱动复算!A8:X8,1,情景参数!B3) -> 11041.69 | F66: =E66*(1-情景参数!D3) -> 11041.69 | G66: =IF(情景参数!E3="原表",驱动复算!U8-驱动复算!W8,驱动复算!P8) -> 7802.9195 | H66: =IF(情景参数!E3="原表",驱动复算!W8,F66*情景参数!C3) -> 220.8338 | I66: =IF(情景参数!E3="原表",驱动复算!U8,G66+H66) -> 8023.7533 | J66: =(F66-I66)*(1-情景参数!F3) -> 3017.9367 | K66: =偿债原表!F9 -> 0 | L66: =偿债原表!G9 -> 1075.8 | M66: =K66+L66 -> 1075.8 | N66: =J66-M66 -> 1942.1367 | O66: =O65+N66 -> -3405.7987 | P66: =MAX(0,-(R65+N66)) -> 0 | Q66: =Q65+P66 -> 6617.2116 | R66: =O66+Q66 -> 3211.4129
A67: 统一2% | B67: 晚版 | C67: 8 | D67: 2031 | E67: =INDEX(驱动复算!A9:X9,1,情景参数!B3) -> 12052.04 | F67: =E67*(1-情景参数!D3) -> 12052.04 | G67: =IF(情景参数!E3="原表",驱动复算!U9-驱动复算!W9,驱动复算!P9) -> 8037.0071 | H67: =IF(情景参数!E3="原表",驱动复算!W9,F67*情景参数!C3) -> 241.0408 | I67: =IF(情景参数!E3="原表",驱动复算!U9,G67+H67) -> 8278.0479 | J67: =(F67-I67)*(1-情景参数!F3) -> 3773.9921 | K67: =偿债原表!F10 -> 0 | L67: =偿债原表!G10 -> 1075.8 | M67: =K67+L67 -> 1075.8 | N67: =J67-M67 -> 2698.1921 | O67: =O66+N67 -> -707.60658 | P67: =MAX(0,-(R66+N67)) -> 0 | Q67: =Q66+P67 -> 6617.2116 | R67: =O67+Q67 -> 5909.605
A68: 统一2% | B68: 晚版 | C68: 9 | D68: 2032 | E68: =INDEX(驱动复算!A10:X10,1,情景参数!B3) -> 13163.43 | F68: =E68*(1-情景参数!D3) -> 13163.43 | G68: =IF(情景参数!E3="原表",驱动复算!U10-驱动复算!W10,驱动复算!P10) -> 8278.1173 | H68: =IF(情景参数!E3="原表",驱动复算!W10,F68*情景参数!C3) -> 263.2686 | I68: =IF(情景参数!E3="原表",驱动复算!U10,G68+H68) -> 8541.3859 | J68: =(F68-I68)*(1-情景参数!F3) -> 4622.0441 | K68: =偿债原表!F11 -> 2000 | L68: =偿债原表!G11 -> 1075.8 | M68: =K68+L68 -> 3075.8 | N68: =J68-M68 -> 1546.2441 | O68: =O67+N68 -> 838.63752 | P68: =MAX(0,-(R67+N68)) -> 0 | Q68: =Q67+P68 -> 6617.2116 | R68: =O68+Q68 -> 7455.8491
A69: 统一2% | B69: 晚版 | C69: 10 | D69: 2033 | E69: =INDEX(驱动复算!A11:X11,1,情景参数!B3) -> 14139.86 | F69: =E69*(1-情景参数!D3) -> 14139.86 | G69: =IF(情景参数!E3="原表",驱动复算!U11-驱动复算!W11,驱动复算!P11) -> 8526.4608 | H69: =IF(情景参数!E3="原表",驱动复算!W11,F69*情景参数!C3) -> 282.7972 | I69: =IF(情景参数!E3="原表",驱动复算!U11,G69+H69) -> 8809.258 | J69: =(F69-I69)*(1-情景参数!F3) -> 5330.602 | K69: =偿债原表!F12 -> 9600 | L69: =偿债原表!G12 -> 1018.8 | M69: =K69+L69 -> 10618.8 | N69: =J69-M69 -> -5288.198 | O69: =O68+N69 -> -4449.5605 | P69: =MAX(0,-(R68+N69)) -> 0 | Q69: =Q68+P69 -> 6617.2116 | R69: =O69+Q69 -> 2167.6511
A70: 统一2% | B70: 晚版 | C70: 11 | D70: 2034 | E70: =INDEX(驱动复算!A12:X12,1,情景参数!B3) -> 14781.69 | F70: =E70*(1-情景参数!D3) -> 14781.69 | G70: =IF(情景参数!E3="原表",驱动复算!U12-驱动复算!W12,驱动复算!P12) -> 8782.2546 | H70: =IF(情景参数!E3="原表",驱动复算!W12,F70*情景参数!C3) -> 295.6338 | I70: =IF(情景参数!E3="原表",驱动复算!U12,G70+H70) -> 9077.8884 | J70: =(F70-I70)*(1-情景参数!F3) -> 5703.8016 | K70: =偿债原表!F13 -> 0 | L70: =偿债原表!G13 -> 673.2 | M70: =K70+L70 -> 673.2 | N70: =J70-M70 -> 5030.6016 | O70: =O69+N70 -> 581.04106 | P70: =MAX(0,-(R69+N70)) -> 0 | Q70: =Q69+P70 -> 6617.2116 | R70: =O70+Q70 -> 7198.2527
A71: 统一2% | B71: 晚版 | C71: 12 | D71: 2035 | E71: =INDEX(驱动复算!A13:X13,1,情景参数!B3) -> 15455.6 | F71: =E71*(1-情景参数!D3) -> 15455.6 | G71: =IF(情景参数!E3="原表",驱动复算!U13-驱动复算!W13,驱动复算!P13) -> 9045.7223 | H71: =IF(情景参数!E3="原表",驱动复算!W13,F71*情景参数!C3) -> 309.112 | I71: =IF(情景参数!E3="原表",驱动复算!U13,G71+H71) -> 9354.8343 | J71: =(F71-I71)*(1-情景参数!F3) -> 6100.7657 | K71: =偿债原表!F14 -> 0 | L71: =偿债原表!G14 -> 673.2 | M71: =K71+L71 -> 673.2 | N71: =J71-M71 -> 5427.5657 | O71: =O70+N71 -> 6008.6068 | P71: =MAX(0,-(R70+N71)) -> 0 | Q71: =Q70+P71 -> 6617.2116 | R71: =O71+Q71 -> 12625.818
A72: 统一2% | B72: 晚版 | C72: 13 | D72: 2036 | E72: =INDEX(驱动复算!A14:X14,1,情景参数!B3) -> 16163.21 | F72: =E72*(1-情景参数!D3) -> 16163.21 | G72: =IF(情景参数!E3="原表",驱动复算!U14-驱动复算!W14,驱动复算!P14) -> 9317.0939 | H72: =IF(情景参数!E3="原表",驱动复算!W14,F72*情景参数!C3) -> 323.2642 | I72: =IF(情景参数!E3="原表",驱动复算!U14,G72+H72) -> 9640.3581 | J72: =(F72-I72)*(1-情景参数!F3) -> 6522.8519 | K72: =偿债原表!F15 -> 0 | L72: =偿债原表!G15 -> 673.2 | M72: =K72+L72 -> 673.2 | N72: =J72-M72 -> 5849.6519 | O72: =O71+N72 -> 11858.259 | P72: =MAX(0,-(R71+N72)) -> 0 | Q72: =Q71+P72 -> 6617.2116 | R72: =O72+Q72 -> 18475.47
A73: 统一2% | B73: 晚版 | C73: 14 | D73: 2037 | E73: =INDEX(驱动复算!A15:X15,1,情景参数!B3) -> 16906.2 | F73: =E73*(1-情景参数!D3) -> 16906.2 | G73: =IF(情景参数!E3="原表",驱动复算!U15-驱动复算!W15,驱动复算!P15) -> 9596.6068 | H73: =IF(情景参数!E3="原表",驱动复算!W15,F73*情景参数!C3) -> 338.124 | I73: =IF(情景参数!E3="原表",驱动复算!U15,G73+H73) -> 9934.7308 | J73: =(F73-I73)*(1-情景参数!F3) -> 6971.4692 | K73: =偿债原表!F16 -> 1000 | L73: =偿债原表!G16 -> 673.2 | M73: =K73+L73 -> 1673.2 | N73: =J73-M73 -> 5298.2692 | O73: =O72+N73 -> 17156.528 | P73: =MAX(0,-(R72+N73)) -> 0 | Q73: =Q72+P73 -> 6617.2116 | R73: =O73+Q73 -> 23773.739
A74: 统一2% | B74: 晚版 | C74: 15 | D74: 2038 | E74: =INDEX(驱动复算!A16:X16,1,情景参数!B3) -> 17546.68 | F74: =E74*(1-情景参数!D3) -> 17546.68 | G74: =IF(情景参数!E3="原表",驱动复算!U16-驱动复算!W16,驱动复算!P16) -> 9884.505 | H74: =IF(情景参数!E3="原表",驱动复算!W16,F74*情景参数!C3) -> 350.9336 | I74: =IF(情景参数!E3="原表",驱动复算!U16,G74+H74) -> 10235.439 | J74: =(F74-I74)*(1-情景参数!F3) -> 7311.2414 | K74: =偿债原表!F17 -> 0 | L74: =偿债原表!G17 -> 644 | M74: =K74+L74 -> 644 | N74: =J74-M74 -> 6667.2414 | O74: =O73+N74 -> 23823.769 | P74: =MAX(0,-(R73+N74)) -> 0 | Q74: =Q73+P74 -> 6617.2116 | R74: =O74+Q74 -> 30440.981
A75: 统一2% | B75: 晚版 | C75: 16 | D75: 2039 | E75: =INDEX(驱动复算!A17:X17,1,情景参数!B3) -> 17864.98 | F75: =E75*(1-情景参数!D3) -> 17864.98 | G75: =IF(情景参数!E3="原表",驱动复算!U17-驱动复算!W17,驱动复算!P17) -> 10181.04 | H75: =IF(情景参数!E3="原表",驱动复算!W17,F75*情景参数!C3) -> 357.2996 | I75: =IF(情景参数!E3="原表",驱动复算!U17,G75+H75) -> 10538.34 | J75: =(F75-I75)*(1-情景参数!F3) -> 7326.6403 | K75: =偿债原表!F18 -> 0 | L75: =偿债原表!G18 -> 644 | M75: =K75+L75 -> 644 | N75: =J75-M75 -> 6682.6403 | O75: =O74+N75 -> 30506.41 | P75: =MAX(0,-(R74+N75)) -> 0 | Q75: =Q74+P75 -> 6617.2116 | R75: =O75+Q75 -> 37123.621
A76: 统一2% | B76: 晚版 | C76: 17 | D76: 2040 | E76: =INDEX(驱动复算!A18:X18,1,情景参数!B3) -> 18189.64 | F76: =E76*(1-情景参数!D3) -> 18189.64 | G76: =IF(情景参数!E3="原表",驱动复算!U18-驱动复算!W18,驱动复算!P18) -> 10486.471 | H76: =IF(情景参数!E3="原表",驱动复算!W18,F76*情景参数!C3) -> 363.7928 | I76: =IF(情景参数!E3="原表",驱动复算!U18,G76+H76) -> 10850.264 | J76: =(F76-I76)*(1-情景参数!F3) -> 7339.3759 | K76: =偿债原表!F19 -> 0 | L76: =偿债原表!G19 -> 644 | M76: =K76+L76 -> 644 | N76: =J76-M76 -> 6695.3759 | O76: =O75+N76 -> 37201.785 | P76: =MAX(0,-(R75+N76)) -> 0 | Q76: =Q75+P76 -> 6617.2116 | R76: =O76+Q76 -> 43818.997
A77: 统一2% | B77: 晚版 | C77: 18 | D77: 2041 | E77: =INDEX(驱动复算!A19:X19,1,情景参数!B3) -> 18520.8 | F77: =E77*(1-情景参数!D3) -> 18520.8 | G77: =IF(情景参数!E3="原表",驱动复算!U19-驱动复算!W19,驱动复算!P19) -> 10801.065 | H77: =IF(情景参数!E3="原表",驱动复算!W19,F77*情景参数!C3) -> 370.416 | I77: =IF(情景参数!E3="原表",驱动复算!U19,G77+H77) -> 11171.481 | J77: =(F77-I77)*(1-情景参数!F3) -> 7349.3185 | K77: =偿债原表!F20 -> 20000 | L77: =偿债原表!G20 -> 644 | M77: =K77+L77 -> 20644 | N77: =J77-M77 -> -13294.681 | O77: =O76+N77 -> 23907.104 | P77: =MAX(0,-(R76+N77)) -> 0 | Q77: =Q76+P77 -> 6617.2116 | R77: =O77+Q77 -> 30524.316
A78: 统一5% | B78: 早版 | C78: 0 | D78: 已融资 | E78: =0 -> 0 | F78: =E78*(1-情景参数!D4) -> 0 | G78: =0 -> 0 | H78: =0 -> 0 | I78: =0 -> 0 | J78: =(F78-I78)*(1-情景参数!F4) -> 0 | K78: =偿债原表!C2 -> 0 | L78: =偿债原表!D2 -> 1374.2 | M78: =K78+L78 -> 1374.2 | N78: =J78-M78 -> -1374.2 | O78: =N78 -> -1374.2 | P78: =MAX(0,-N78) -> 1374.2 | Q78: =P78 -> 1374.2 | R78: =O78+Q78 -> 0
A79: 统一5% | B79: 早版 | C79: 1 | D79: 2024 | E79: =INDEX(驱动复算!A2:X2,1,情景参数!B4) -> 0 | F79: =E79*(1-情景参数!D4) -> 0 | G79: =IF(情景参数!E4="原表",驱动复算!U2-驱动复算!W2,驱动复算!P2) -> 0 | H79: =IF(情景参数!E4="原表",驱动复算!W2,F79*情景参数!C4) -> 0 | I79: =IF(情景参数!E4="原表",驱动复算!U2,G79+H79) -> 0 | J79: =(F79-I79)*(1-情景参数!F4) -> 0 | K79: =偿债原表!C3 -> 0 | L79: =偿债原表!D3 -> 1093.2 | M79: =K79+L79 -> 1093.2 | N79: =J79-M79 -> -1093.2 | O79: =O78+N79 -> -2467.4 | P79: =MAX(0,-(R78+N79)) -> 1093.2 | Q79: =Q78+P79 -> 2467.4 | R79: =O79+Q79 -> 0
A80: 统一5% | B80: 早版 | C80: 2 | D80: 2025 | E80: =INDEX(驱动复算!A3:X3,1,情景参数!B4) -> 0 | F80: =E80*(1-情景参数!D4) -> 0 | G80: =IF(情景参数!E4="原表",驱动复算!U3-驱动复算!W3,驱动复算!P3) -> 0 | H80: =IF(情景参数!E4="原表",驱动复算!W3,F80*情景参数!C4) -> 0 | I80: =IF(情景参数!E4="原表",驱动复算!U3,G80+H80) -> 0 | J80: =(F80-I80)*(1-情景参数!F4) -> 0 | K80: =偿债原表!C4 -> 0 | L80: =偿债原表!D4 -> 1093.2 | M80: =K80+L80 -> 1093.2 | N80: =J80-M80 -> -1093.2 | O80: =O79+N80 -> -3560.6 | P80: =MAX(0,-(R79+N80)) -> 1093.2 | Q80: =Q79+P80 -> 3560.6 | R80: =O80+Q80 -> 0
A81: 统一5% | B81: 早版 | C81: 3 | D81: 2026 | E81: =INDEX(驱动复算!A4:X4,1,情景参数!B4) -> 0 | F81: =E81*(1-情景参数!D4) -> 0 | G81: =IF(情景参数!E4="原表",驱动复算!U4-驱动复算!W4,驱动复算!P4) -> 0 | H81: =IF(情景参数!E4="原表",驱动复算!W4,F81*情景参数!C4) -> 0 | I81: =IF(情景参数!E4="原表",驱动复算!U4,G81+H81) -> 0 | J81: =(F81-I81)*(1-情景参数!F4) -> 0 | K81: =偿债原表!C5 -> 0 | L81: =偿债原表!D5 -> 1093.2 | M81: =K81+L81 -> 1093.2 | N81: =J81-M81 -> -1093.2 | O81: =O80+N81 -> -4653.8 | P81: =MAX(0,-(R80+N81)) -> 1093.2 | Q81: =Q80+P81 -> 4653.8 | R81: =O81+Q81 -> 0
A82: 统一5% | B82: 早版 | C82: 4 | D82: 2027 | E82: =INDEX(驱动复算!A5:X5,1,情景参数!B4) -> 0 | F82: =E82*(1-情景参数!D4) -> 0 | G82: =IF(情景参数!E4="原表",驱动复算!U5-驱动复算!W5,驱动复算!P5) -> 0 | H82: =IF(情景参数!E4="原表",驱动复算!W5,F82*情景参数!C4) -> 0 | I82: =IF(情景参数!E4="原表",驱动复算!U5,G82+H82) -> 0 | J82: =(F82-I82)*(1-情景参数!F4) -> 0 | K82: =偿债原表!C6 -> 0 | L82: =偿债原表!D6 -> 1093.2 | M82: =K82+L82 -> 1093.2 | N82: =J82-M82 -> -1093.2 | O82: =O81+N82 -> -5747 | P82: =MAX(0,-(R81+N82)) -> 1093.2 | Q82: =Q81+P82 -> 5747 | R82: =O82+Q82 -> 0
A83: 统一5% | B83: 早版 | C83: 5 | D83: 2028 | E83: =INDEX(驱动复算!A6:X6,1,情景参数!B4) -> 9234.58 | F83: =E83*(1-情景参数!D4) -> 9234.58 | G83: =IF(情景参数!E4="原表",驱动复算!U6-驱动复算!W6,驱动复算!P6) -> 7355 | H83: =IF(情景参数!E4="原表",驱动复算!W6,F83*情景参数!C4) -> 461.729 | I83: =IF(情景参数!E4="原表",驱动复算!U6,G83+H83) -> 7816.729 | J83: =(F83-I83)*(1-情景参数!F4) -> 1417.851 | K83: =偿债原表!C7 -> 11000 | L83: =偿债原表!D7 -> 1093.2 | M83: =K83+L83 -> 12093.2 | N83: =J83-M83 -> -10675.349 | O83: =O82+N83 -> -16422.349 | P83: =MAX(0,-(R82+N83)) -> 10675.349 | Q83: =Q82+P83 -> 16422.349 | R83: =O83+Q83 -> 0
A84: 统一5% | B84: 早版 | C84: 6 | D84: 2029 | E84: =INDEX(驱动复算!A7:X7,1,情景参数!B4) -> 10123.19 | F84: =E84*(1-情景参数!D4) -> 10123.19 | G84: =IF(情景参数!E4="原表",驱动复算!U7-驱动复算!W7,驱动复算!P7) -> 7575.65 | H84: =IF(情景参数!E4="原表",驱动复算!W7,F84*情景参数!C4) -> 506.1595 | I84: =IF(情景参数!E4="原表",驱动复算!U7,G84+H84) -> 8081.8095 | J84: =(F84-I84)*(1-情景参数!F4) -> 2041.3805 | K84: =偿债原表!C8 -> 0 | L84: =偿债原表!D8 -> 730.2 | M84: =K84+L84 -> 730.2 | N84: =J84-M84 -> 1311.1805 | O84: =O83+N84 -> -15111.168 | P84: =MAX(0,-(R83+N84)) -> 0 | Q84: =Q83+P84 -> 16422.349 | R84: =O84+Q84 -> 1311.1805
A85: 统一5% | B85: 早版 | C85: 7 | D85: 2030 | E85: =INDEX(驱动复算!A8:X8,1,情景参数!B4) -> 11041.69 | F85: =E85*(1-情景参数!D4) -> 11041.69 | G85: =IF(情景参数!E4="原表",驱动复算!U8-驱动复算!W8,驱动复算!P8) -> 7802.9195 | H85: =IF(情景参数!E4="原表",驱动复算!W8,F85*情景参数!C4) -> 552.0845 | I85: =IF(情景参数!E4="原表",驱动复算!U8,G85+H85) -> 8355.004 | J85: =(F85-I85)*(1-情景参数!F4) -> 2686.686 | K85: =偿债原表!C9 -> 0 | L85: =偿债原表!D9 -> 730.2 | M85: =K85+L85 -> 730.2 | N85: =J85-M85 -> 1956.486 | O85: =O84+N85 -> -13154.683 | P85: =MAX(0,-(R84+N85)) -> 0 | Q85: =Q84+P85 -> 16422.349 | R85: =O85+Q85 -> 3267.6665
A86: 统一5% | B86: 早版 | C86: 8 | D86: 2031 | E86: =INDEX(驱动复算!A9:X9,1,情景参数!B4) -> 12052.04 | F86: =E86*(1-情景参数!D4) -> 12052.04 | G86: =IF(情景参数!E4="原表",驱动复算!U9-驱动复算!W9,驱动复算!P9) -> 8037.0071 | H86: =IF(情景参数!E4="原表",驱动复算!W9,F86*情景参数!C4) -> 602.602 | I86: =IF(情景参数!E4="原表",驱动复算!U9,G86+H86) -> 8639.6091 | J86: =(F86-I86)*(1-情景参数!F4) -> 3412.4309 | K86: =偿债原表!C10 -> 0 | L86: =偿债原表!D10 -> 730.2 | M86: =K86+L86 -> 730.2 | N86: =J86-M86 -> 2682.2309 | O86: =O85+N86 -> -10472.452 | P86: =MAX(0,-(R85+N86)) -> 0 | Q86: =Q85+P86 -> 16422.349 | R86: =O86+Q86 -> 5949.8974
A87: 统一5% | B87: 早版 | C87: 9 | D87: 2032 | E87: =INDEX(驱动复算!A10:X10,1,情景参数!B4) -> 13163.43 | F87: =E87*(1-情景参数!D4) -> 13163.43 | G87: =IF(情景参数!E4="原表",驱动复算!U10-驱动复算!W10,驱动复算!P10) -> 8278.1173 | H87: =IF(情景参数!E4="原表",驱动复算!W10,F87*情景参数!C4) -> 658.1715 | I87: =IF(情景参数!E4="原表",驱动复算!U10,G87+H87) -> 8936.2888 | J87: =(F87-I87)*(1-情景参数!F4) -> 4227.1412 | K87: =偿债原表!C11 -> 2000 | L87: =偿债原表!D11 -> 730.2 | M87: =K87+L87 -> 2730.2 | N87: =J87-M87 -> 1496.9412 | O87: =O86+N87 -> -8975.5104 | P87: =MAX(0,-(R86+N87)) -> 0 | Q87: =Q86+P87 -> 16422.349 | R87: =O87+Q87 -> 7446.8386
A88: 统一5% | B88: 早版 | C88: 10 | D88: 2033 | E88: =INDEX(驱动复算!A11:X11,1,情景参数!B4) -> 14139.86 | F88: =E88*(1-情景参数!D4) -> 14139.86 | G88: =IF(情景参数!E4="原表",驱动复算!U11-驱动复算!W11,驱动复算!P11) -> 8526.4608 | H88: =IF(情景参数!E4="原表",驱动复算!W11,F88*情景参数!C4) -> 706.993 | I88: =IF(情景参数!E4="原表",驱动复算!U11,G88+H88) -> 9233.4538 | J88: =(F88-I88)*(1-情景参数!F4) -> 4906.4062 | K88: =偿债原表!C12 -> 0 | L88: =偿债原表!D12 -> 673.2 | M88: =K88+L88 -> 673.2 | N88: =J88-M88 -> 4233.2062 | O88: =O87+N88 -> -4742.3042 | P88: =MAX(0,-(R87+N88)) -> 0 | Q88: =Q87+P88 -> 16422.349 | R88: =O88+Q88 -> 11680.045
A89: 统一5% | B89: 早版 | C89: 11 | D89: 2034 | E89: =INDEX(驱动复算!A12:X12,1,情景参数!B4) -> 14781.69 | F89: =E89*(1-情景参数!D4) -> 14781.69 | G89: =IF(情景参数!E4="原表",驱动复算!U12-驱动复算!W12,驱动复算!P12) -> 8782.2546 | H89: =IF(情景参数!E4="原表",驱动复算!W12,F89*情景参数!C4) -> 739.0845 | I89: =IF(情景参数!E4="原表",驱动复算!U12,G89+H89) -> 9521.3391 | J89: =(F89-I89)*(1-情景参数!F4) -> 5260.3509 | K89: =偿债原表!C13 -> 0 | L89: =偿债原表!D13 -> 673.2 | M89: =K89+L89 -> 673.2 | N89: =J89-M89 -> 4587.1509 | O89: =O88+N89 -> -155.15334 | P89: =MAX(0,-(R88+N89)) -> 0 | Q89: =Q88+P89 -> 16422.349 | R89: =O89+Q89 -> 16267.196
A90: 统一5% | B90: 早版 | C90: 12 | D90: 2035 | E90: =INDEX(驱动复算!A13:X13,1,情景参数!B4) -> 15455.6 | F90: =E90*(1-情景参数!D4) -> 15455.6 | G90: =IF(情景参数!E4="原表",驱动复算!U13-驱动复算!W13,驱动复算!P13) -> 9045.7223 | H90: =IF(情景参数!E4="原表",驱动复算!W13,F90*情景参数!C4) -> 772.78 | I90: =IF(情景参数!E4="原表",驱动复算!U13,G90+H90) -> 9818.5023 | J90: =(F90-I90)*(1-情景参数!F4) -> 5637.0977 | K90: =偿债原表!C14 -> 0 | L90: =偿债原表!D14 -> 673.2 | M90: =K90+L90 -> 673.2 | N90: =J90-M90 -> 4963.8977 | O90: =O89+N90 -> 4808.7444 | P90: =MAX(0,-(R89+N90)) -> 0 | Q90: =Q89+P90 -> 16422.349 | R90: =O90+Q90 -> 21231.093
A91: 统一5% | B91: 早版 | C91: 13 | D91: 2036 | E91: =INDEX(驱动复算!A14:X14,1,情景参数!B4) -> 16163.21 | F91: =E91*(1-情景参数!D4) -> 16163.21 | G91: =IF(情景参数!E4="原表",驱动复算!U14-驱动复算!W14,驱动复算!P14) -> 9317.0939 | H91: =IF(情景参数!E4="原表",驱动复算!W14,F91*情景参数!C4) -> 808.1605 | I91: =IF(情景参数!E4="原表",驱动复算!U14,G91+H91) -> 10125.254 | J91: =(F91-I91)*(1-情景参数!F4) -> 6037.9556 | K91: =偿债原表!C15 -> 0 | L91: =偿债原表!D15 -> 673.2 | M91: =K91+L91 -> 673.2 | N91: =J91-M91 -> 5364.7556 | O91: =O90+N91 -> 10173.5 | P91: =MAX(0,-(R90+N91)) -> 0 | Q91: =Q90+P91 -> 16422.349 | R91: =O91+Q91 -> 26595.849
A92: 统一5% | B92: 早版 | C92: 14 | D92: 2037 | E92: =INDEX(驱动复算!A15:X15,1,情景参数!B4) -> 16906.2 | F92: =E92*(1-情景参数!D4) -> 16906.2 | G92: =IF(情景参数!E4="原表",驱动复算!U15-驱动复算!W15,驱动复算!P15) -> 9596.6068 | H92: =IF(情景参数!E4="原表",驱动复算!W15,F92*情景参数!C4) -> 845.31 | I92: =IF(情景参数!E4="原表",驱动复算!U15,G92+H92) -> 10441.917 | J92: =(F92-I92)*(1-情景参数!F4) -> 6464.2832 | K92: =偿债原表!C16 -> 1000 | L92: =偿债原表!D16 -> 673.2 | M92: =K92+L92 -> 1673.2 | N92: =J92-M92 -> 4791.0832 | O92: =O91+N92 -> 14964.583 | P92: =MAX(0,-(R91+N92)) -> 0 | Q92: =Q91+P92 -> 16422.349 | R92: =O92+Q92 -> 31386.932
A93: 统一5% | B93: 早版 | C93: 15 | D93: 2038 | E93: =INDEX(驱动复算!A16:X16,1,情景参数!B4) -> 17546.68 | F93: =E93*(1-情景参数!D4) -> 17546.68 | G93: =IF(情景参数!E4="原表",驱动复算!U16-驱动复算!W16,驱动复算!P16) -> 9884.505 | H93: =IF(情景参数!E4="原表",驱动复算!W16,F93*情景参数!C4) -> 877.334 | I93: =IF(情景参数!E4="原表",驱动复算!U16,G93+H93) -> 10761.839 | J93: =(F93-I93)*(1-情景参数!F4) -> 6784.841 | K93: =偿债原表!C17 -> 0 | L93: =偿债原表!D17 -> 644 | M93: =K93+L93 -> 644 | N93: =J93-M93 -> 6140.841 | O93: =O92+N93 -> 21105.424 | P93: =MAX(0,-(R92+N93)) -> 0 | Q93: =Q92+P93 -> 16422.349 | R93: =O93+Q93 -> 37527.773
A94: 统一5% | B94: 早版 | C94: 16 | D94: 2039 | E94: =INDEX(驱动复算!A17:X17,1,情景参数!B4) -> 17864.98 | F94: =E94*(1-情景参数!D4) -> 17864.98 | G94: =IF(情景参数!E4="原表",驱动复算!U17-驱动复算!W17,驱动复算!P17) -> 10181.04 | H94: =IF(情景参数!E4="原表",驱动复算!W17,F94*情景参数!C4) -> 893.249 | I94: =IF(情景参数!E4="原表",驱动复算!U17,G94+H94) -> 11074.289 | J94: =(F94-I94)*(1-情景参数!F4) -> 6790.6909 | K94: =偿债原表!C18 -> 0 | L94: =偿债原表!D18 -> 644 | M94: =K94+L94 -> 644 | N94: =J94-M94 -> 6146.6909 | O94: =O93+N94 -> 27252.115 | P94: =MAX(0,-(R93+N94)) -> 0 | Q94: =Q93+P94 -> 16422.349 | R94: =O94+Q94 -> 43674.464
A95: 统一5% | B95: 早版 | C95: 17 | D95: 2040 | E95: =INDEX(驱动复算!A18:X18,1,情景参数!B4) -> 18189.64 | F95: =E95*(1-情景参数!D4) -> 18189.64 | G95: =IF(情景参数!E4="原表",驱动复算!U18-驱动复算!W18,驱动复算!P18) -> 10486.471 | H95: =IF(情景参数!E4="原表",驱动复算!W18,F95*情景参数!C4) -> 909.482 | I95: =IF(情景参数!E4="原表",驱动复算!U18,G95+H95) -> 11395.953 | J95: =(F95-I95)*(1-情景参数!F4) -> 6793.6867 | K95: =偿债原表!C19 -> 0 | L95: =偿债原表!D19 -> 644 | M95: =K95+L95 -> 644 | N95: =J95-M95 -> 6149.6867 | O95: =O94+N95 -> 33401.802 | P95: =MAX(0,-(R94+N95)) -> 0 | Q95: =Q94+P95 -> 16422.349 | R95: =O95+Q95 -> 49824.151
A96: 统一5% | B96: 早版 | C96: 18 | D96: 2041 | E96: =INDEX(驱动复算!A19:X19,1,情景参数!B4) -> 18520.8 | F96: =E96*(1-情景参数!D4) -> 18520.8 | G96: =IF(情景参数!E4="原表",驱动复算!U19-驱动复算!W19,驱动复算!P19) -> 10801.065 | H96: =IF(情景参数!E4="原表",驱动复算!W19,F96*情景参数!C4) -> 926.04 | I96: =IF(情景参数!E4="原表",驱动复算!U19,G96+H96) -> 11727.105 | J96: =(F96-I96)*(1-情景参数!F4) -> 6793.6945 | K96: =偿债原表!C20 -> 20000 | L96: =偿债原表!D20 -> 644 | M96: =K96+L96 -> 20644 | N96: =J96-M96 -> -13850.305 | O96: =O95+N96 -> 19551.496 | P96: =MAX(0,-(R95+N96)) -> 0 | Q96: =Q95+P96 -> 16422.349 | R96: =O96+Q96 -> 35973.845
A97: 统一5% | B97: 晚版 | C97: 0 | D97: 已融资 | E97: =0 -> 0 | F97: =E97*(1-情景参数!D4) -> 0 | G97: =0 -> 0 | H97: =0 -> 0 | I97: =0 -> 0 | J97: =(F97-I97)*(1-情景参数!F4) -> 0 | K97: =偿债原表!F2 -> 0 | L97: =偿债原表!G2 -> 1374.2 | M97: =K97+L97 -> 1374.2 | N97: =J97-M97 -> -1374.2 | O97: =N97 -> -1374.2 | P97: =MAX(0,-N97) -> 1374.2 | Q97: =P97 -> 1374.2 | R97: =O97+Q97 -> 0
A98: 统一5% | B98: 晚版 | C98: 1 | D98: 2024 | E98: =INDEX(驱动复算!A2:X2,1,情景参数!B4) -> 0 | F98: =E98*(1-情景参数!D4) -> 0 | G98: =IF(情景参数!E4="原表",驱动复算!U2-驱动复算!W2,驱动复算!P2) -> 0 | H98: =IF(情景参数!E4="原表",驱动复算!W2,F98*情景参数!C4) -> 0 | I98: =IF(情景参数!E4="原表",驱动复算!U2,G98+H98) -> 0 | J98: =(F98-I98)*(1-情景参数!F4) -> 0 | K98: =偿债原表!F3 -> 0 | L98: =偿债原表!G3 -> 1107.58 | M98: =K98+L98 -> 1107.58 | N98: =J98-M98 -> -1107.58 | O98: =O97+N98 -> -2481.78 | P98: =MAX(0,-(R97+N98)) -> 1107.58 | Q98: =Q97+P98 -> 2481.78 | R98: =O98+Q98 -> 0
A99: 统一5% | B99: 晚版 | C99: 2 | D99: 2025 | E99: =INDEX(驱动复算!A3:X3,1,情景参数!B4) -> 0 | F99: =E99*(1-情景参数!D4) -> 0 | G99: =IF(情景参数!E4="原表",驱动复算!U3-驱动复算!W3,驱动复算!P3) -> 0 | H99: =IF(情景参数!E4="原表",驱动复算!W3,F99*情景参数!C4) -> 0 | I99: =IF(情景参数!E4="原表",驱动复算!U3,G99+H99) -> 0 | J99: =(F99-I99)*(1-情景参数!F4) -> 0 | K99: =偿债原表!F4 -> 0 | L99: =偿债原表!G4 -> 1107.58 | M99: =K99+L99 -> 1107.58 | N99: =J99-M99 -> -1107.58 | O99: =O98+N99 -> -3589.36 | P99: =MAX(0,-(R98+N99)) -> 1107.58 | Q99: =Q98+P99 -> 3589.36 | R99: =O99+Q99 -> 0
A100: 统一5% | B100: 晚版 | C100: 3 | D100: 2026 | E100: =INDEX(驱动复算!A4:X4,1,情景参数!B4) -> 0 | F100: =E100*(1-情景参数!D4) -> 0 | G100: =IF(情景参数!E4="原表",驱动复算!U4-驱动复算!W4,驱动复算!P4) -> 0 | H100: =IF(情景参数!E4="原表",驱动复算!W4,F100*情景参数!C4) -> 0 | I100: =IF(情景参数!E4="原表",驱动复算!U4,G100+H100) -> 0 | J100: =(F100-I100)*(1-情景参数!F4) -> 0 | K100: =偿债原表!F5 -> 0 | L100: =偿债原表!G5 -> 1107.58 | M100: =K100+L100 -> 1107.58 | N100: =J100-M100 -> -1107.58 | O100: =O99+N100 -> -4696.94 | P100: =MAX(0,-(R99+N100)) -> 1107.58 | Q100: =Q99+P100 -> 4696.94 | R100: =O100+Q100 -> 0
...

Sheet 复核问题
A1: 事项 | B1: 证据位置 | C1: 发现 | D1: 量化或处理 | E1: 应补正内容
A2: 版本 | B2: 三报告p1、3、12 | C2: 六十一与六十九逐字节相同；早版07-100、晚版07-237 | D2: 不得相加本金或收益 | E2: 形成版本对照，要求实际发行批次映射
A3: 公告与计划 | B3: 公告正文；报告p3 | C3: 6400为2024年募集额，11000/9600是计划 | D3: 不得用计划替代实际余额 | E3: 补充已发与拟发对应说明
A4: 管理费 | B4: 三报告费用正文和p6表 | C4: 首年184.69≈收入2%，正文5%；2037后连2%也不一致 | D4: 统一2%净收益75410.00；5%为69254.50 | E4: 确认管理费率及费用表生成公式
A5: 停车 | B5: 报告p4—5；停车标准副中心及外围行 | C5: 9小时夜停按18元等乘算，遗漏10元封顶；每5年提价0.5无文件授权 | D5: 首年应512.46；14年冻结单价7805.16 | E5: 补正封顶及调价假设，说明优惠车辆及单独核定情况
A6: 充电 | B6: 报告p5；2018通知第四条；2022目录及实施解读 | C6: 0.8是历史标准，目录外价格不能继续保留政府定价；表中2029涨25%早于五年周期 | D6: 保留0.8经营假设，甲乙周期单列 | E6: 说明需求增长与单价增长，不认定首年假设为已证实经营数据
A7: 压力 | B7: 晚版p10；早版p9—10 | C7: 原表71683.55实为净收益×95%，不是收入×95%再扣费 | D7: 正文5%管理费联动压力覆盖晚版1.1554 | E7: 收入/收益术语及压力口径补正
A8: 年度资金 | B8: 报告p8—9 | C8: 原表全周期覆盖为正但早期运营不足、到期集中偿本 | D8: 晚版原表最大累计缺口6617.21；主调整压力11169.23 | E8: 提供逐年外部资金来源、到位时点及留存机制
A9: 日历年 | B9: 报告p3—4、8 | C9: 第一年2024、第十八年2041，但2022+20=2042等晚一年 | D9: 报告年表不能替代真实兑付日历；未知2042收益不补造 | E9: 核对起息兑付日及会计计提与现金支付差异
A10: 证据边界 | B10: 三报告p12—13 | C10: 预测鉴证非实际经营审计；实际结果可不同 | D10: 不据测算缺口认定实际违约 | E10: 要求补正测算与安排说明，非直接作真实偿付断言
